Workbook

Sheet DAXX MIDIA PE
B1: DAXX MIDIA PE - cód. 1220 | D1: 46023 | E1: =D1+1 -> 46024 | F1: =E1+1 -> 46025 | G1: =F1+1 -> 46026 | H1: =G1+1 -> 46027 | I1: =H1+1 -> 46028 | J1: =I1+1 -> 46029 | K1: =J1+1 -> 46030 | L1: =K1+1 -> 46031 | ... AH1: =AG1+1 -> 46053 | AI1: TOTAL JAN | AK1: =EOMONTH(AE1,0)+1 -> 46054 | AL1: =AK1+1 -> 46055 | AM1: =AL1+1 -> 46056 | AN1: =AM1+1 -> 46057 | AO1: =AN1+1 -> 46058 | AP1: =AO1+1 -> 46059 | AQ1: =AP1+1 -> 46060 | AR1: =AQ1+1 -> 46061 | AS1: =AR1+1 -> 46062 | ... BL1: =BK1+1 -> 46081 | BN1: TOTAL FEV | BP1: =EOMONTH(BJ1,0)+1 -> 46082 | BQ1: =BP1+1 -> 46083 | BR1: =BQ1+1 -> 46084 | BS1: =BR1+1 -> 46085 | BT1: =BS1+1 -> 46086 | BU1: =BT1+1 -> 46087 | BV1: =BU1+1 -> 46088 | BW1: =BV1+1 -> 46089 | BX1: =BW1+1 -> 46090 | ... CT1: =CS1+1 -> 46112 | CU1: TOTAL MAR | CW1: =EOMONTH(CQ1,0)+1 -> 46113 | CX1: =CW1+1 -> 46114 | CY1: =CX1+1 -> 46115 | CZ1: =CY1+1 -> 46116 | DA1: =CZ1+1 -> 46117 | DB1: =DA1+1 -> 46118 | DC1: =DB1+1 -> 46119 | DD1: =DC1+1 -> 46120 | DE1: =DD1+1 -> 46121 | ... DZ1: =DY1+1 -> 46142 | EA1: TOTAL ABR | EC1: =EOMONTH(DW1,0)+1 -> 46143 | ED1: =EC1+1 -> 46144 | EE1: =ED1+1 -> 46145 | EF1: =EE1+1 -> 46146 | EG1: =EF1+1 -> 46147 | EH1: =EG1+1 -> 46148 | EI1: =EH1+1 -> 46149 | EJ1: =EI1+1 -> 46150 | EK1: =EJ1+1 -> 46151 | ... FG1: =FF1+1 -> 46173 | FH1: TOTAL MAI | FJ1: =EOMONTH(FD1,0)+1 -> 46174 | FK1: =FJ1+1 -> 46175 | FL1: =FK1+1 -> 46176 | FM1: =FL1+1 -> 46177 | FN1: =FM1+1 -> 46178 | FO1: =FN1+1 -> 46179 | FP1: =FO1+1 -> 46180 | FQ1: =FP1+1 -> 46181 | FR1: =FQ1+1 -> 46182 | ... GM1: =GL1+1 -> 46203 | GN1: TOTAL JUN | GP1: =EOMONTH(GJ1,0)+1 -> 46204 | GQ1: =GP1+1 -> 46205 | GR1: =GQ1+1 -> 46206 | GS1: =GR1+1 -> 46207 | GT1: =GS1+1 -> 46208 | GU1: =GT1+1 -> 46209 | GV1: =GU1+1 -> 46210 | GW1: =GV1+1 -> 46211 | GX1: =GW1+1 -> 46212 | ... HT1: =HS1+1 -> 46234 | HU1: TOTAL JUL | HW1: =EOMONTH(HQ1,0)+1 -> 46235 | HX1: =HW1+1 -> 46236 | HY1: =HX1+1 -> 46237 | HZ1: =HY1+1 -> 46238 | IA1: =HZ1+1 -> 46239 | IB1: =IA1+1 -> 46240 | IC1: =IB1+1 -> 46241 | ID1: =IC1+1 -> 46242 | IE1: =ID1+1 -> 46243 | ... JA1: =IZ1+1 -> 46265 | JB1: TOTAL AGO | JD1: =EOMONTH(IX1,0)+1 -> 46266 | JE1: =JD1+1 -> 46267 | JF1: =JE1+1 -> 46268 | JG1: =JF1+1 -> 46269 | JH1: =JG1+1 -> 46270 | JI1: =JH1+1 -> 46271 | JJ1: =JI1+1 -> 46272 | JK1: =JJ1+1 -> 46273 | JL1: =JK1+1 -> 46274 | ... KG1: =KF1+1 -> 46295 | KH1: TOTAL SET | KJ1: =EOMONTH(KD1,0)+1 -> 46296 | KK1: =KJ1+1 -> 46297 | KL1: =KK1+1 -> 46298 | KM1: =KL1+1 -> 46299 | KN1: =KM1+1 -> 46300 | KO1: =KN1+1 -> 46301 | KP1: =KO1+1 -> 46302 | KQ1: =KP1+1 -> 46303 | KR1: =KQ1+1 -> 46304 | ... LN1: =LM1+1 -> 46326 | LO1: TOTAL OUT | LQ1: =EOMONTH(LK1,0)+1 -> 46327 | LR1: =LQ1+1 -> 46328 | LS1: =LR1+1 -> 46329 | LT1: =LS1+1 -> 46330 | LU1: =LT1+1 -> 46331 | LV1: =LU1+1 -> 46332 | LW1: =LV1+1 -> 46333 | LX1: =LW1+1 -> 46334 | LY1: =LX1+1 -> 46335 | ... MT1: =MS1+1 -> 46356 | MU1: TOTAL NOV | MW1: =EOMONTH(MQ1,0)+1 -> 46357 | MX1: =MW1+1 -> 46358 | MY1: =MX1+1 -> 46359 | MZ1: =MY1+1 -> 46360 | NA1: =MZ1+1 -> 46361 | NB1: =NA1+1 -> 46362 | NC1: =NB1+1 -> 46363 | ND1: =NC1+1 -> 46364 | NE1: =ND1+1 -> 46365 | ... OA1: =NZ1+1 -> 46387 | OB1: TOTAL DEZ | OC1: ACUMULADO | OE1: =EOMONTH(NX1,0)+1 -> 46388 | OF1: =OE1+1 -> 46389 | OG1: =OF1+1 -> 46390 | OH1: =OG1+1 -> 46391 | OI1: =OH1+1 -> 46392 | OJ1: =OI1+1 -> 46393 | OK1: =OJ1+1 -> 46394 | OL1: =OK1+1 -> 46395 | OM1: =OL1+1 -> 46396 | ... PI1: =PH1+1 -> 46418 | PJ1: TOTAL JAN PA | PL1: =EOMONTH(PF1,0)+1 -> 46419 | PM1: =PL1+1 -> 46420 | PN1: =PM1+1 -> 46421 | PO1: =PN1+1 -> 46422 | PP1: =PO1+1 -> 46423 | PQ1: =PP1+1 -> 46424 | PR1: =PQ1+1 -> 46425 | PS1: =PR1+1 -> 46426 | PT1: =PS1+1 -> 46427 | ... QM1: =QL1+1 -> 46446 | QO1: TOTAL FEV PA | QQ1: =EOMONTH(QK1,0)+1 -> 46447 | QR1: =QQ1+1 -> 46448 | QS1: =QR1+1 -> 46449 | QT1: =QS1+1 -> 46450 | QU1: =QT1+1 -> 46451 | QV1: =QU1+1 -> 46452 | QW1: =QV1+1 -> 46453 | QX1: =QW1+1 -> 46454 | QY1: =QX1+1 -> 46455 | ... RU1: =RT1+1 -> 46477 | RV1: TOTAL MAR PA | RW1: ACUMULADO PA
A3: 1 | B3: RECEITAS
B4: Outras Receitas | AI4: =SUM(D4:AH4) -> 0 | BN4: =SUM(AK4:BM4) -> 0 | CU4: =SUM(BP4:CT4) -> 0 | EA4: =SUM(CW4:DZ4) -> 0 | FH4: =SUM(EC4:FG4) -> 0 | GN4: =SUM(FJ4:GM4) -> 0 | HU4: =SUM(GP4:HT4) -> 0 | JB4: =SUM(HW4:JA4) -> 0 | KH4: =SUM(JD4:KG4) -> 0 | LO4: =SUM(KJ4:LN4) -> 0 | MU4: =SUM(LQ4:MT4) -> 0 | OB4: =SUM(MW4:OA4) -> 0 | OC4: =SUM(AI4,BN4,CU4,EA4,FH4,GN4,HU4,JB4,KH4,LO4,MU4,OB4) -> 0 | PJ4: =SUM(OE4:PI4) -> 0 | QO4: =SUM(PL4:QN4) -> 0 | RV4: =SUM(QQ4:RU4) -> 0 | RW4: =SUM(PJ4,QO4,RV4) -> 0
B5: Resgate Aplicação | AI5: =SUM(D5:AH5) -> 0 | BN5: =SUM(AK5:BM5) -> 0 | CU5: =SUM(BP5:CT5) -> 0 | EA5: =SUM(CW5:DZ5) -> 0 | FH5: =SUM(EC5:FG5) -> 0 | GN5: =SUM(FJ5:GM5) -> 0 | HU5: =SUM(GP5:HT5) -> 0 | JB5: =SUM(HW5:JA5) -> 0 | KH5: =SUM(JD5:KG5) -> 0 | LO5: =SUM(KJ5:LN5) -> 0 | MU5: =SUM(LQ5:MT5) -> 0 | OB5: =SUM(MW5:OA5) -> 0 | OC5: =SUM(AI5,BN5,CU5,EA5,FH5,GN5,HU5,JB5,KH5,LO5,MU5,OB5) -> 0 | PJ5: =SUM(OE5:PI5) -> 0 | QO5: =SUM(PL5:QN5) -> 0 | RV5: =SUM(QQ5:RU5) -> 0 | RW5: =SUM(PJ5,QO5,RV5) -> 0
B6: Empréstimos Sócios | AI6: =SUM(D6:AH6) -> 0 | BN6: =SUM(AK6:BM6) -> 0 | CU6: =SUM(BP6:CT6) -> 0 | EA6: =SUM(CW6:DZ6) -> 0 | FH6: =SUM(EC6:FG6) -> 0 | GN6: =SUM(FJ6:GM6) -> 0 | HU6: =SUM(GP6:HT6) -> 0 | JB6: =SUM(HW6:JA6) -> 0 | KH6: =SUM(JD6:KG6) -> 0 | LO6: =SUM(KJ6:LN6) -> 0 | MU6: =SUM(LQ6:MT6) -> 0 | OB6: =SUM(MW6:OA6) -> 0 | OC6: =SUM(AI6,BN6,CU6,EA6,FH6,GN6,HU6,JB6,KH6,LO6,MU6,OB6) -> 0 | PJ6: =SUM(OE6:PI6) -> 0 | QO6: =SUM(PL6:QN6) -> 0 | RV6: =SUM(QQ6:RU6) -> 0 | RW6: =SUM(PJ6,QO6,RV6) -> 0
B7: Mútuo Sócios | AI7: =SUM(D7:AH7) -> 0 | BN7: =SUM(AK7:BM7) -> 0 | CU7: =SUM(BP7:CT7) -> 0 | EA7: =SUM(CW7:DZ7) -> 0 | FH7: =SUM(EC7:FG7) -> 0 | GN7: =SUM(FJ7:GM7) -> 0 | HU7: =SUM(GP7:HT7) -> 0 | JB7: =SUM(HW7:JA7) -> 0 | KH7: =SUM(JD7:KG7) -> 0 | LO7: =SUM(KJ7:LN7) -> 0 | MU7: =SUM(LQ7:MT7) -> 0 | OB7: =SUM(MW7:OA7) -> 0 | OC7: =SUM(AI7,BN7,CU7,EA7,FH7,GN7,HU7,JB7,KH7,LO7,MU7,OB7) -> 0 | PJ7: =SUM(OE7:PI7) -> 0 | QO7: =SUM(PL7:QN7) -> 0 | RV7: =SUM(QQ7:RU7) -> 0 | RW7: =SUM(PJ7,QO7,RV7) -> 0
B8: Mútuo CNPJ - outras empresas Grupo | AI8: =SUM(D8:AH8) -> 0 | AO8: =20000 -> 20000 | BN8: =SUM(AK8:BM8) -> 20000 | CU8: =SUM(BP8:CT8) -> 0 | EA8: =SUM(CW8:DZ8) -> 0 | FH8: =SUM(EC8:FG8) -> 0 | GN8: =SUM(FJ8:GM8) -> 0 | HU8: =SUM(GP8:HT8) -> 0 | JB8: =SUM(HW8:JA8) -> 0 | KH8: =SUM(JD8:KG8) -> 0 | LO8: =SUM(KJ8:LN8) -> 0 | MU8: =SUM(LQ8:MT8) -> 0 | OB8: =SUM(MW8:OA8) -> 0 | OC8: =SUM(AI8,BN8,CU8,EA8,FH8,GN8,HU8,JB8,KH8,LO8,MU8,OB8) -> 20000 | PJ8: =SUM(OE8:PI8) -> 0 | QO8: =SUM(PL8:QN8) -> 0 | RV8: =SUM(QQ8:RU8) -> 0 | RW8: =SUM(PJ8,QO8,RV8) -> 0
B9: Empréstimos Bancário | AI9: =SUM(D9:AH9) -> 0 | BN9: =SUM(AK9:BM9) -> 0 | CU9: =SUM(BP9:CT9) -> 0 | EA9: =SUM(CW9:DZ9) -> 0 | FH9: =SUM(EC9:FG9) -> 0 | GN9: =SUM(FJ9:GM9) -> 0 | HU9: =SUM(GP9:HT9) -> 0 | JB9: =SUM(HW9:JA9) -> 0 | KH9: =SUM(JD9:KG9) -> 0 | LO9: =SUM(KJ9:LN9) -> 0 | MU9: =SUM(LQ9:MT9) -> 0 | OB9: =SUM(MW9:OA9) -> 0 | OC9: =SUM(AI9,BN9,CU9,EA9,FH9,GN9,HU9,JB9,KH9,LO9,MU9,OB9) -> 0 | PJ9: =SUM(OE9:PI9) -> 0 | QO9: =SUM(PL9:QN9) -> 0 | RV9: =SUM(QQ9:RU9) -> 0 | RW9: =SUM(PJ9,QO9,RV9) -> 0
B10: Rendimento Banco C/c | H10: 1.76 | Q10: 2.76 | W10: 0.04 | AC10: 0.61 | AG10: 3.52 | AI10: =SUM(D10:AH10) -> 8.69 | AT10: 2.99 | BI10: 0.03 | BK10: 0.03 | BN10: =SUM(AK10:BM10) -> 3.05 | BT10: 0.13 | CN10: 0.07 | CT10: 0.09 | CU10: =SUM(BP10:CT10) -> 0.29 | DB10: 0.27 | DZ10: 0.14 | EA10: =SUM(CW10:DZ10) -> 0.41 | EG10: 0.4 | EN10: 0.31 | EV10: 0.02 | FE10: 0.46 | FH10: =SUM(EC10:FG10) -> 1.19 | GN10: =SUM(FJ10:GM10) -> 0 | HU10: =SUM(GP10:HT10) -> 0 | JB10: =SUM(HW10:JA10) -> 0 | KH10: =SUM(JD10:KG10) -> 0 | LO10: =SUM(KJ10:LN10) -> 0 | MU10: =SUM(LQ10:MT10) -> 0 | OB10: =SUM(MW10:OA10) -> 0 | OC10: =SUM(AI10,BN10,CU10,EA10,FH10,GN10,HU10,JB10,KH10,LO10,MU10,OB10) -> 13.63 | PJ10: =SUM(OE10:PI10) -> 0 | QO10: =SUM(PL10:QN10) -> 0 | RV10: =SUM(QQ10:RU10) -> 0 | RW10: =SUM(PJ10,QO10,RV10) -> 0
B11: Receita Operacional - REFATURAMENTO VEÍCULO | AI11: =SUM(D11:AH11) -> 0 | BN11: =SUM(AK11:BM11) -> 0 | CU11: =SUM(BP11:CT11) -> 0 | EA11: =SUM(CW11:DZ11) -> 0 | FH11: =SUM(EC11:FG11) -> 0 | GN11: =SUM(FJ11:GM11) -> 0 | HU11: =SUM(GP11:HT11) -> 0 | JB11: =SUM(HW11:JA11) -> 0 | KH11: =SUM(JD11:KG11) -> 0 | LO11: =SUM(KJ11:LN11) -> 0 | MU11: =SUM(LQ11:MT11) -> 0 | OB11: =SUM(MW11:OA11) -> 0 | OC11: =SUM(AI11,BN11,CU11,EA11,FH11,GN11,HU11,JB11,KH11,LO11,MU11,OB11) -> 0 | PJ11: =SUM(OE11:PI11) -> 0 | QO11: =SUM(PL11:QN11) -> 0 | RV11: =SUM(QQ11:RU11) -> 0 | RW11: =SUM(PJ11,QO11,RV11) -> 0
B12: Receita Operacional - REFATURAMENTO VEÍCULO (CUSTO COMISSÃO DO REPASSE) | AI12: =SUM(D12:AH12) -> 0 | BN12: =SUM(AK12:BM12) -> 0 | CU12: =SUM(BP12:CT12) -> 0 | EA12: =SUM(CW12:DZ12) -> 0 | FH12: =SUM(EC12:FG12) -> 0 | GN12: =SUM(FJ12:GM12) -> 0 | HU12: =SUM(GP12:HT12) -> 0 | JB12: =SUM(HW12:JA12) -> 0 | KH12: =SUM(JD12:KG12) -> 0 | LO12: =SUM(KJ12:LN12) -> 0 | MU12: =SUM(LQ12:MT12) -> 0 | OB12: =SUM(MW12:OA12) -> 0 | OC12: =SUM(AI12,BN12,CU12,EA12,FH12,GN12,HU12,JB12,KH12,LO12,MU12,OB12) -> 0 | PJ12: =SUM(OE12:PI12) -> 0 | QO12: =SUM(PL12:QN12) -> 0 | RV12: =SUM(QQ12:RU12) -> 0 | RW12: =SUM(PJ12,QO12,RV12) -> 0
B13: Receita Operacional - VENDAS (CLIENTE) | AI13: =SUM(D13:AH13) -> 0 | BN13: =SUM(AK13:BM13) -> 0 | CU13: =SUM(BP13:CT13) -> 0 | EA13: =SUM(CW13:DZ13) -> 0 | FH13: =SUM(EC13:FG13) -> 0 | GN13: =SUM(FJ13:GM13) -> 0 | HU13: =SUM(GP13:HT13) -> 0 | JB13: =SUM(HW13:JA13) -> 0 | KH13: =SUM(JD13:KG13) -> 0 | LO13: =SUM(KJ13:LN13) -> 0 | MU13: =SUM(LQ13:MT13) -> 0 | OB13: =SUM(MW13:OA13) -> 0 | OC13: =SUM(AI13,BN13,CU13,EA13,FH13,GN13,HU13,JB13,KH13,LO13,MU13,OB13) -> 0 | PJ13: =SUM(OE13:PI13) -> 0 | QO13: =SUM(PL13:QN13) -> 0 | RV13: =SUM(QQ13:RU13) -> 0 | RW13: =SUM(PJ13,QO13,RV13) -> 0
B14: Receita Operacional - VENDAS (VEÍCULO) | AI14: =SUM(D14:AH14) -> 0 | BN14: =SUM(AK14:BM14) -> 0 | CU14: =SUM(BP14:CT14) -> 0 | EA14: =SUM(CW14:DZ14) -> 0 | FH14: =SUM(EC14:FG14) -> 0 | GN14: =SUM(FJ14:GM14) -> 0 | HU14: =SUM(GP14:HT14) -> 0 | JB14: =SUM(HW14:JA14) -> 0 | KH14: =SUM(JD14:KG14) -> 0 | LO14: =SUM(KJ14:LN14) -> 0 | MU14: =SUM(LQ14:MT14) -> 0 | OB14: =SUM(MW14:OA14) -> 0 | OC14: =SUM(AI14,BN14,CU14,EA14,FH14,GN14,HU14,JB14,KH14,LO14,MU14,OB14) -> 0 | PJ14: =SUM(OE14:PI14) -> 0 | QO14: =SUM(PL14:QN14) -> 0 | RV14: =SUM(QQ14:RU14) -> 0 | RW14: =SUM(PJ14,QO14,RV14) -> 0
B15: Receita Operacional - VENDAS (FEE) | AI15: =SUM(D15:AH15) -> 0 | BN15: =SUM(AK15:BM15) -> 0 | CU15: =SUM(BP15:CT15) -> 0 | EA15: =SUM(CW15:DZ15) -> 0 | FH15: =SUM(EC15:FG15) -> 0 | GN15: =SUM(FJ15:GM15) -> 0 | HU15: =SUM(GP15:HT15) -> 0 | JB15: =SUM(HW15:JA15) -> 0 | KH15: =SUM(JD15:KG15) -> 0 | LO15: =SUM(KJ15:LN15) -> 0 | MU15: =SUM(LQ15:MT15) -> 0 | OB15: =SUM(MW15:OA15) -> 0 | OC15: =SUM(AI15,BN15,CU15,EA15,FH15,GN15,HU15,JB15,KH15,LO15,MU15,OB15) -> 0 | PJ15: =SUM(OE15:PI15) -> 0 | QO15: =SUM(PL15:QN15) -> 0 | RV15: =SUM(QQ15:RU15) -> 0 | RW15: =SUM(PJ15,QO15,RV15) -> 0
B16: Receita Operacional - VENDAS (CONSULTORIA) | AI16: =SUM(D16:AH16) -> 0 | BN16: =SUM(AK16:BM16) -> 0 | CU16: =SUM(BP16:CT16) -> 0 | EA16: =SUM(CW16:DZ16) -> 0 | FH16: =SUM(EC16:FG16) -> 0 | GN16: =SUM(FJ16:GM16) -> 0 | HU16: =SUM(GP16:HT16) -> 0 | JB16: =SUM(HW16:JA16) -> 0 | KH16: =SUM(JD16:KG16) -> 0 | LO16: =SUM(KJ16:LN16) -> 0 | MU16: =SUM(LQ16:MT16) -> 0 | OB16: =SUM(MW16:OA16) -> 0 | OC16: =SUM(AI16,BN16,CU16,EA16,FH16,GN16,HU16,JB16,KH16,LO16,MU16,OB16) -> 0 | PJ16: =SUM(OE16:PI16) -> 0 | QO16: =SUM(PL16:QN16) -> 0 | RV16: =SUM(QQ16:RU16) -> 0 | RW16: =SUM(PJ16,QO16,RV16) -> 0
B17: Receita Operacional - VENDAS (CONVERSACIONAL) | AI17: =SUM(D17:AH17) -> 0 | BN17: =SUM(AK17:BM17) -> 0 | CU17: =SUM(BP17:CT17) -> 0 | EA17: =SUM(CW17:DZ17) -> 0 | FH17: =SUM(EC17:FG17) -> 0 | GN17: =SUM(FJ17:GM17) -> 0 | HU17: =SUM(GP17:HT17) -> 0 | JB17: =SUM(HW17:JA17) -> 0 | KH17: =SUM(JD17:KG17) -> 0 | LO17: =SUM(KJ17:LN17) -> 0 | MU17: =SUM(LQ17:MT17) -> 0 | OB17: =SUM(MW17:OA17) -> 0 | OC17: =SUM(AI17,BN17,CU17,EA17,FH17,GN17,HU17,JB17,KH17,LO17,MU17,OB17) -> 0 | PJ17: =SUM(OE17:PI17) -> 0 | QO17: =SUM(PL17:QN17) -> 0 | RV17: =SUM(QQ17:RU17) -> 0 | RW17: =SUM(PJ17,QO17,RV17) -> 0
B18: Receita Operacional - VENDAS (MENSAGERIA) | AI18: =SUM(D18:AH18) -> 0 | BN18: =SUM(AK18:BM18) -> 0 | CU18: =SUM(BP18:CT18) -> 0 | EA18: =SUM(CW18:DZ18) -> 0 | FH18: =SUM(EC18:FG18) -> 0 | GN18: =SUM(FJ18:GM18) -> 0 | HU18: =SUM(GP18:HT18) -> 0 | JB18: =SUM(HW18:JA18) -> 0 | KH18: =SUM(JD18:KG18) -> 0 | LO18: =SUM(KJ18:LN18) -> 0 | MU18: =SUM(LQ18:MT18) -> 0 | OB18: =SUM(MW18:OA18) -> 0 | OC18: =SUM(AI18,BN18,CU18,EA18,FH18,GN18,HU18,JB18,KH18,LO18,MU18,OB18) -> 0 | PJ18: =SUM(OE18:PI18) -> 0 | QO18: =SUM(PL18:QN18) -> 0 | RV18: =SUM(QQ18:RU18) -> 0 | RW18: =SUM(PJ18,QO18,RV18) -> 0
B19: Receita Operacional - VENDAS (PARCEIROS) | AI19: =SUM(D19:AH19) -> 0 | BN19: =SUM(AK19:BM19) -> 0 | CU19: =SUM(BP19:CT19) -> 0 | EA19: =SUM(CW19:DZ19) -> 0 | FH19: =SUM(EC19:FG19) -> 0 | GN19: =SUM(FJ19:GM19) -> 0 | HU19: =SUM(GP19:HT19) -> 0 | JB19: =SUM(HW19:JA19) -> 0 | KH19: =SUM(JD19:KG19) -> 0 | LO19: =SUM(KJ19:LN19) -> 0 | MU19: =SUM(LQ19:MT19) -> 0 | OB19: =SUM(MW19:OA19) -> 0 | OC19: =SUM(AI19,BN19,CU19,EA19,FH19,GN19,HU19,JB19,KH19,LO19,MU19,OB19) -> 0 | PJ19: =SUM(OE19:PI19) -> 0 | QO19: =SUM(PL19:QN19) -> 0 | RV19: =SUM(QQ19:RU19) -> 0 | RW19: =SUM(PJ19,QO19,RV19) -> 0
B20: Receita Operacional - CREDITOS | AI20: =SUM(D20:AH20) -> 0 | BN20: =SUM(AK20:BM20) -> 0 | CU20: =SUM(BP20:CT20) -> 0 | EA20: =SUM(CW20:DZ20) -> 0 | FH20: =SUM(EC20:FG20) -> 0 | GN20: =SUM(FJ20:GM20) -> 0 | HU20: =SUM(GP20:HT20) -> 0 | JB20: =SUM(HW20:JA20) -> 0 | KH20: =SUM(JD20:KG20) -> 0 | LO20: =SUM(KJ20:LN20) -> 0 | MU20: =SUM(LQ20:MT20) -> 0 | OB20: =SUM(MW20:OA20) -> 0 | OC20: =SUM(AI20,BN20,CU20,EA20,FH20,GN20,HU20,JB20,KH20,LO20,MU20,OB20) -> 0 | PJ20: =SUM(OE20:PI20) -> 0 | QO20: =SUM(PL20:QN20) -> 0 | RV20: =SUM(QQ20:RU20) -> 0 | RW20: =SUM(PJ20,QO20,RV20) -> 0
B21: Receita Operacional - CREDITOS (VALOR COMISSÃO DAXX DO CRÉDITO) | AI21: =SUM(D21:AH21) -> 0 | BN21: =SUM(AK21:BM21) -> 0 | CU21: =SUM(BP21:CT21) -> 0 | EA21: =SUM(CW21:DZ21) -> 0 | FH21: =SUM(EC21:FG21) -> 0 | GN21: =SUM(FJ21:GM21) -> 0 | HU21: =SUM(GP21:HT21) -> 0 | JB21: =SUM(HW21:JA21) -> 0 | KH21: =SUM(JD21:KG21) -> 0 | LO21: =SUM(KJ21:LN21) -> 0 | MU21: =SUM(LQ21:MT21) -> 0 | OB21: =SUM(MW21:OA21) -> 0 | OC21: =SUM(AI21,BN21,CU21,EA21,FH21,GN21,HU21,JB21,KH21,LO21,MU21,OB21) -> 0 | PJ21: =SUM(OE21:PI21) -> 0 | QO21: =SUM(PL21:QN21) -> 0 | RV21: =SUM(QQ21:RU21) -> 0 | RW21: =SUM(PJ21,QO21,RV21) -> 0
B22: Receita Operacional - BV | AI22: =SUM(D22:AH22) -> 0 | BN22: =SUM(AK22:BM22) -> 0 | CU22: =SUM(BP22:CT22) -> 0 | EA22: =SUM(CW22:DZ22) -> 0 | FH22: =SUM(EC22:FG22) -> 0 | GN22: =SUM(FJ22:GM22) -> 0 | HU22: =SUM(GP22:HT22) -> 0 | JB22: =SUM(HW22:JA22) -> 0 | KH22: =SUM(JD22:KG22) -> 0 | LO22: =SUM(KJ22:LN22) -> 0 | MU22: =SUM(LQ22:MT22) -> 0 | OB22: =SUM(MW22:OA22) -> 0 | OC22: =SUM(AI22,BN22,CU22,EA22,FH22,GN22,HU22,JB22,KH22,LO22,MU22,OB22) -> 0 | PJ22: =SUM(OE22:PI22) -> 0 | QO22: =SUM(PL22:QN22) -> 0 | RV22: =SUM(QQ22:RU22) -> 0 | RW22: =SUM(PJ22,QO22,RV22) -> 0
B23: TOTAL RECEITAS | D23: =SUM(D4:D22) -> 0 | E23: =SUM(E4:E22) -> 0 | F23: =SUM(F4:F22) -> 0 | G23: =SUM(G4:G22) -> 0 | H23: =SUM(H4:H22) -> 1.76 | I23: =SUM(I4:I22) -> 0 | J23: =SUM(J4:J22) -> 0 | K23: =SUM(K4:K22) -> 0 | ... AI23: =SUM(AI4:AI22) -> 8.69 | AK23: =SUM(AK4:AK22) -> 0 | AL23: =SUM(AL4:AL22) -> 0 | AM23: =SUM(AM4:AM22) -> 0 | AN23: =SUM(AN4:AN22) -> 0 | AO23: =SUM(AO4:AO22) -> 20000 | AP23: =SUM(AP4:AP22) -> 0 | AQ23: =SUM(AQ4:AQ22) -> 0 | AR23: =SUM(AR4:AR22) -> 0 | ... BN23: =SUM(BN4:BN22) -> 20003.05 | BP23: =SUM(BP4:BP22) -> 0 | BQ23: =SUM(BQ4:BQ22) -> 0 | BR23: =SUM(BR4:BR22) -> 0 | BS23: =SUM(BS4:BS22) -> 0 | BT23: =SUM(BT4:BT22) -> 0.13 | BU23: =SUM(BU4:BU22) -> 0 | BV23: =SUM(BV4:BV22) -> 0 | BW23: =SUM(BW4:BW22) -> 0 | ... CU23: =SUM(CU4:CU22) -> 0.29 | CW23: =SUM(CW4:CW22) -> 0 | CX23: =SUM(CX4:CX22) -> 0 | CY23: =SUM(CY4:CY22) -> 0 | CZ23: =SUM(CZ4:CZ22) -> 0 | DA23: =SUM(DA4:DA22) -> 0 | DB23: =SUM(DB4:DB22) -> 0.27 | DC23: =SUM(DC4:DC22) -> 0 | DD23: =SUM(DD4:DD22) -> 0 | ... EA23: =SUM(EA4:EA22) -> 0.41 | EC23: =SUM(EC4:EC22) -> 0 | ED23: =SUM(ED4:ED22) -> 0 | EE23: =SUM(EE4:EE22) -> 0 | EF23: =SUM(EF4:EF22) -> 0 | EG23: =SUM(EG4:EG22) -> 0.4 | EH23: =SUM(EH4:EH22) -> 0 | EI23: =SUM(EI4:EI22) -> 0 | EJ23: =SUM(EJ4:EJ22) -> 0 | ... FH23: =SUM(FH4:FH22) -> 1.19 | FJ23: =SUM(FJ4:FJ22) -> 0 | FK23: =SUM(FK4:FK22) -> 0 | FL23: =SUM(FL4:FL22) -> 0 | FM23: =SUM(FM4:FM22) -> 0 | FN23: =SUM(FN4:FN22) -> 0 | FO23: =SUM(FO4:FO22) -> 0 | FP23: =SUM(FP4:FP22) -> 0 | FQ23: =SUM(FQ4:FQ22) -> 0 | ... GN23: =SUM(GN4:GN22) -> 0 | GP23: =SUM(GP4:GP22) -> 0 | GQ23: =SUM(GQ4:GQ22) -> 0 | GR23: =SUM(GR4:GR22) -> 0 | GS23: =SUM(GS4:GS22) -> 0 | GT23: =SUM(GT4:GT22) -> 0 | GU23: =SUM(GU4:GU22) -> 0 | GV23: =SUM(GV4:GV22) -> 0 | GW23: =SUM(GW4:GW22) -> 0 | ... HU23: =SUM(HU4:HU22) -> 0 | HW23: =SUM(HW4:HW22) -> 0 | HX23: =SUM(HX4:HX22) -> 0 | HY23: =SUM(HY4:HY22) -> 0 | HZ23: =SUM(HZ4:HZ22) -> 0 | IA23: =SUM(IA4:IA22) -> 0 | IB23: =SUM(IB4:IB22) -> 0 | IC23: =SUM(IC4:IC22) -> 0 | ID23: =SUM(ID4:ID22) -> 0 | ... JB23: =SUM(JB4:JB22) -> 0 | JD23: =SUM(JD4:JD22) -> 0 | JE23: =SUM(JE4:JE22) -> 0 | JF23: =SUM(JF4:JF22) -> 0 | JG23: =SUM(JG4:JG22) -> 0 | JH23: =SUM(JH4:JH22) -> 0 | JI23: =SUM(JI4:JI22) -> 0 | JJ23: =SUM(JJ4:JJ22) -> 0 | JK23: =SUM(JK4:JK22) -> 0 | ... KH23: =SUM(KH4:KH22) -> 0 | KJ23: =SUM(KJ4:KJ22) -> 0 | KK23: =SUM(KK4:KK22) -> 0 | KL23: =SUM(KL4:KL22) -> 0 | KM23: =SUM(KM4:KM22) -> 0 | KN23: =SUM(KN4:KN22) -> 0 | KO23: =SUM(KO4:KO22) -> 0 | KP23: =SUM(KP4:KP22) -> 0 | KQ23: =SUM(KQ4:KQ22) -> 0 | ... LO23: =SUM(LO4:LO22) -> 0 | LQ23: =SUM(LQ4:LQ22) -> 0 | LR23: =SUM(LR4:LR22) -> 0 | LS23: =SUM(LS4:LS22) -> 0 | LT23: =SUM(LT4:LT22) -> 0 | LU23: =SUM(LU4:LU22) -> 0 | LV23: =SUM(LV4:LV22) -> 0 | LW23: =SUM(LW4:LW22) -> 0 | LX23: =SUM(LX4:LX22) -> 0 | ... MU23: =SUM(MU4:MU22) -> 0 | MW23: =SUM(MW4:MW22) -> 0 | MX23: =SUM(MX4:MX22) -> 0 | MY23: =SUM(MY4:MY22) -> 0 | MZ23: =SUM(MZ4:MZ22) -> 0 | NA23: =SUM(NA4:NA22) -> 0 | NB23: =SUM(NB4:NB22) -> 0 | NC23: =SUM(NC4:NC22) -> 0 | ND23: =SUM(ND4:ND22) -> 0 | ... OB23: =SUM(OB4:OB22) -> 0 | OC23: =SUM(AI23,BN23,CU23,EA23,FH23,GN23,HU23,JB23,KH23,LO23,MU23,OB23) -> 20013.63 | OE23: =SUM(OE4:OE22) -> 0 | OF23: =SUM(OF4:OF22) -> 0 | OG23: =SUM(OG4:OG22) -> 0 | OH23: =SUM(OH4:OH22) -> 0 | OI23: =SUM(OI4:OI22) -> 0 | OJ23: =SUM(OJ4:OJ22) -> 0 | OK23: =SUM(OK4:OK22) -> 0 | OL23: =SUM(OL4:OL22) -> 0 | ... PJ23: =SUM(PJ4:PJ22) -> 0 | PL23: =SUM(PL4:PL22) -> 0 | PM23: =SUM(PM4:PM22) -> 0 | PN23: =SUM(PN4:PN22) -> 0 | PO23: =SUM(PO4:PO22) -> 0 | PP23: =SUM(PP4:PP22) -> 0 | PQ23: =SUM(PQ4:PQ22) -> 0 | PR23: =SUM(PR4:PR22) -> 0 | PS23: =SUM(PS4:PS22) -> 0 | ... QO23: =SUM(QO4:QO22) -> 0 | QQ23: =SUM(QQ4:QQ22) -> 0 | QR23: =SUM(QR4:QR22) -> 0 | QS23: =SUM(QS4:QS22) -> 0 | QT23: =SUM(QT4:QT22) -> 0 | QU23: =SUM(QU4:QU22) -> 0 | QV23: =SUM(QV4:QV22) -> 0 | QW23: =SUM(QW4:QW22) -> 0 | QX23: =SUM(QX4:QX22) -> 0 | ... RV23: =SUM(RV4:RV22) -> 0 | RW23: =SUM(PJ23,QO23,RV23) -> 0
B24: COMPRA CRÉDITO EM VEÍCULO | AI24: =SUM(D24:AH24) -> 0 | BN24: =SUM(AK24:BM24) -> 0 | CU24: =SUM(BP24:CT24) -> 0 | EA24: =SUM(CW24:DZ24) -> 0 | FH24: =SUM(EC24:FG24) -> 0 | GN24: =SUM(FJ24:GM24) -> 0 | HU24: =SUM(GP24:HT24) -> 0 | JB24: =SUM(HW24:JA24) -> 0 | KH24: =SUM(JD24:KG24) -> 0 | LO24: =SUM(KJ24:LN24) -> 0 | MU24: =SUM(LQ24:MT24) -> 0 | OB24: =SUM(MW24:OA24) -> 0 | OC24: =SUM(AI24,BN24,CU24,EA24,FH24,GN24,HU24,JB24,KH24,LO24,MU24,OB24) -> 0 | PJ24: =SUM(OE24:PI24) -> 0 | QO24: =SUM(PL24:QN24) -> 0 | RV24: =SUM(QQ24:RU24) -> 0 | RW24: =SUM(PJ24,QO24,RV24) -> 0
B25: CUSTO REPASSE COM VEÍCULO | AI25: =SUM(D25:AH25) -> 0 | BN25: =SUM(AK25:BM25) -> 0 | CU25: =SUM(BP25:CT25) -> 0 | EA25: =SUM(CW25:DZ25) -> 0 | FH25: =SUM(EC25:FG25) -> 0 | GN25: =SUM(FJ25:GM25) -> 0 | HU25: =SUM(GP25:HT25) -> 0 | JB25: =SUM(HW25:JA25) -> 0 | KH25: =SUM(JD25:KG25) -> 0 | LO25: =SUM(KJ25:LN25) -> 0 | MU25: =SUM(LQ25:MT25) -> 0 | OB25: =SUM(MW25:OA25) -> 0 | OC25: =SUM(AI25,BN25,CU25,EA25,FH25,GN25,HU25,JB25,KH25,LO25,MU25,OB25) -> 0 | PJ25: =SUM(OE25:PI25) -> 0 | QO25: =SUM(PL25:QN25) -> 0 | RV25: =SUM(QQ25:RU25) -> 0 | RW25: =SUM(PJ25,QO25,RV25) -> 0
A27: 1 | B27: IMPOSTOS E TRIBUTOS SOBRE RECEITA DE VENDAS
B28: Simples Nacional | AI28: =SUM(D28:AH28) -> 0 | BN28: =SUM(AK28:BM28) -> 0 | CU28: =SUM(BP28:CT28) -> 0 | EA28: =SUM(CW28:DZ28) -> 0 | FH28: =SUM(EC28:FG28) -> 0 | GN28: =SUM(FJ28:GM28) -> 0 | HU28: =SUM(GP28:HT28) -> 0 | JB28: =SUM(HW28:JA28) -> 0 | KH28: =SUM(JD28:KG28) -> 0 | LO28: =SUM(KJ28:LN28) -> 0 | MU28: =SUM(LQ28:MT28) -> 0 | OB28: =SUM(MW28:OA28) -> 0 | OC28: =SUM(AI28,BN28,CU28,EA28,FH28,GN28,HU28,JB28,KH28,LO28,MU28,OB28) -> 0 | PJ28: =SUM(OE28:PI28) -> 0 | QO28: =SUM(PL28:QN28) -> 0 | RV28: =SUM(QQ28:RU28) -> 0 | RW28: =SUM(PJ28,QO28,RV28) -> 0
B29: PIS | AI29: =SUM(D29:AH29) -> 0 | BN29: =SUM(AK29:BM29) -> 0 | CU29: =SUM(BP29:CT29) -> 0 | EA29: =SUM(CW29:DZ29) -> 0 | FH29: =SUM(EC29:FG29) -> 0 | GN29: =SUM(FJ29:GM29) -> 0 | HU29: =SUM(GP29:HT29) -> 0 | JB29: =SUM(HW29:JA29) -> 0 | KH29: =SUM(JD29:KG29) -> 0 | LO29: =SUM(KJ29:LN29) -> 0 | MU29: =SUM(LQ29:MT29) -> 0 | OB29: =SUM(MW29:OA29) -> 0 | OC29: =SUM(AI29,BN29,CU29,EA29,FH29,GN29,HU29,JB29,KH29,LO29,MU29,OB29) -> 0 | PJ29: =SUM(OE29:PI29) -> 0 | QO29: =SUM(PL29:QN29) -> 0 | RV29: =SUM(QQ29:RU29) -> 0 | RW29: =SUM(PJ29,QO29,RV29) -> 0
B30: COFINS | AI30: =SUM(D30:AH30) -> 0 | BN30: =SUM(AK30:BM30) -> 0 | CU30: =SUM(BP30:CT30) -> 0 | EA30: =SUM(CW30:DZ30) -> 0 | FH30: =SUM(EC30:FG30) -> 0 | GN30: =SUM(FJ30:GM30) -> 0 | HU30: =SUM(GP30:HT30) -> 0 | JB30: =SUM(HW30:JA30) -> 0 | KH30: =SUM(JD30:KG30) -> 0 | LO30: =SUM(KJ30:LN30) -> 0 | MU30: =SUM(LQ30:MT30) -> 0 | OB30: =SUM(MW30:OA30) -> 0 | OC30: =SUM(AI30,BN30,CU30,EA30,FH30,GN30,HU30,JB30,KH30,LO30,MU30,OB30) -> 0 | PJ30: =SUM(OE30:PI30) -> 0 | QO30: =SUM(PL30:QN30) -> 0 | RV30: =SUM(QQ30:RU30) -> 0 | RW30: =SUM(PJ30,QO30,RV30) -> 0
B31: ISS | AI31: =SUM(D31:AH31) -> 0 | BN31: =SUM(AK31:BM31) -> 0 | CU31: =SUM(BP31:CT31) -> 0 | EA31: =SUM(CW31:DZ31) -> 0 | FH31: =SUM(EC31:FG31) -> 0 | GN31: =SUM(FJ31:GM31) -> 0 | HU31: =SUM(GP31:HT31) -> 0 | JB31: =SUM(HW31:JA31) -> 0 | KH31: =SUM(JD31:KG31) -> 0 | LO31: =SUM(KJ31:LN31) -> 0 | MU31: =SUM(LQ31:MT31) -> 0 | OB31: =SUM(MW31:OA31) -> 0 | OC31: =SUM(AI31,BN31,CU31,EA31,FH31,GN31,HU31,JB31,KH31,LO31,MU31,OB31) -> 0 | PJ31: =SUM(OE31:PI31) -> 0 | QO31: =SUM(PL31:QN31) -> 0 | RV31: =SUM(QQ31:RU31) -> 0 | RW31: =SUM(PJ31,QO31,RV31) -> 0
B32: CSLL | AI32: =SUM(D32:AH32) -> 0 | BN32: =SUM(AK32:BM32) -> 0 | CU32: =SUM(BP32:CT32) -> 0 | EA32: =SUM(CW32:DZ32) -> 0 | FH32: =SUM(EC32:FG32) -> 0 | GN32: =SUM(FJ32:GM32) -> 0 | HU32: =SUM(GP32:HT32) -> 0 | JB32: =SUM(HW32:JA32) -> 0 | KH32: =SUM(JD32:KG32) -> 0 | LO32: =SUM(KJ32:LN32) -> 0 | MU32: =SUM(LQ32:MT32) -> 0 | OB32: =SUM(MW32:OA32) -> 0 | OC32: =SUM(AI32,BN32,CU32,EA32,FH32,GN32,HU32,JB32,KH32,LO32,MU32,OB32) -> 0 | PJ32: =SUM(OE32:PI32) -> 0 | QO32: =SUM(PL32:QN32) -> 0 | RV32: =SUM(QQ32:RU32) -> 0 | RW32: =SUM(PJ32,QO32,RV32) -> 0
B33: IRPJ | AI33: =SUM(D33:AH33) -> 0 | BN33: =SUM(AK33:BM33) -> 0 | CU33: =SUM(BP33:CT33) -> 0 | EA33: =SUM(CW33:DZ33) -> 0 | FH33: =SUM(EC33:FG33) -> 0 | GN33: =SUM(FJ33:GM33) -> 0 | HU33: =SUM(GP33:HT33) -> 0 | JB33: =SUM(HW33:JA33) -> 0 | KH33: =SUM(JD33:KG33) -> 0 | LO33: =SUM(KJ33:LN33) -> 0 | MU33: =SUM(LQ33:MT33) -> 0 | OB33: =SUM(MW33:OA33) -> 0 | OC33: =SUM(AI33,BN33,CU33,EA33,FH33,GN33,HU33,JB33,KH33,LO33,MU33,OB33) -> 0 | PJ33: =SUM(OE33:PI33) -> 0 | QO33: =SUM(PL33:QN33) -> 0 | RV33: =SUM(QQ33:RU33) -> 0 | RW33: =SUM(PJ33,QO33,RV33) -> 0
B34: OUTRAS DESPESAS FISCAIS | W34: 14.01 | AI34: =SUM(D34:AH34) -> 14.01 | AT34: 535.54 | BD34: 14.01 | BN34: =SUM(AK34:BM34) -> 549.55 | CI34: 14.01 | CU34: =SUM(BP34:CT34) -> 14.01 | DP34: 14.01 | EA34: =SUM(CW34:DZ34) -> 14.01 | EV34: 14.01 | FH34: =SUM(EC34:FG34) -> 14.01 | FU34: =535.62 -> 535.62 | GC34: 14.01 | GN34: =SUM(FJ34:GM34) -> 549.63 | HI34: 14.01 | HU34: =SUM(GP34:HT34) -> 14.01 | IP34: 14.01 | JB34: =SUM(HW34:JA34) -> 14.01 | JW34: 14.01 | KH34: =SUM(JD34:KG34) -> 14.01 | LC34: 14.01 | LO34: =SUM(KJ34:LN34) -> 14.01 | MJ34: 14.01 | MU34: =SUM(LQ34:MT34) -> 14.01 | NP34: 14.01 | OB34: =SUM(MW34:OA34) -> 14.01 | OC34: =SUM(AI34,BN34,CU34,EA34,FH34,GN34,HU34,JB34,KH34,LO34,MU34,OB34) -> 1239.28 | PJ34: =SUM(OE34:PI34) -> 0 | QO34: =SUM(PL34:QN34) -> 0 | RV34: =SUM(QQ34:RU34) -> 0 | RW34: =SUM(PJ34,QO34,RV34) -> 0
B35: TOTAL IMPOSTOS E TRIBUTOS SOBRE VENDA | D35: =SUM(D28:D34) -> 0 | E35: =SUM(E28:E34) -> 0 | F35: =SUM(F28:F34) -> 0 | G35: =SUM(G28:G34) -> 0 | H35: =SUM(H28:H34) -> 0 | I35: =SUM(I28:I34) -> 0 | J35: =SUM(J28:J34) -> 0 | K35: =SUM(K28:K34) -> 0 | ... AI35: =SUM(AI28:AI34) -> 14.01 | AK35: =SUM(AK28:AK34) -> 0 | AL35: =SUM(AL28:AL34) -> 0 | AM35: =SUM(AM28:AM34) -> 0 | AN35: =SUM(AN28:AN34) -> 0 | AO35: =SUM(AO28:AO34) -> 0 | AP35: =SUM(AP28:AP34) -> 0 | AQ35: =SUM(AQ28:AQ34) -> 0 | AR35: =SUM(AR28:AR34) -> 0 | ... BN35: =SUM(BN28:BN34) -> 549.55 | BP35: =SUM(BP28:BP34) -> 0 | BQ35: =SUM(BQ28:BQ34) -> 0 | BR35: =SUM(BR28:BR34) -> 0 | BS35: =SUM(BS28:BS34) -> 0 | BT35: =SUM(BT28:BT34) -> 0 | BU35: =SUM(BU28:BU34) -> 0 | BV35: =SUM(BV28:BV34) -> 0 | BW35: =SUM(BW28:BW34) -> 0 | ... CU35: =SUM(CU28:CU34) -> 14.01 | CW35: =SUM(CW28:CW34) -> 0 | CX35: =SUM(CX28:CX34) -> 0 | CY35: =SUM(CY28:CY34) -> 0 | CZ35: =SUM(CZ28:CZ34) -> 0 | DA35: =SUM(DA28:DA34) -> 0 | DB35: =SUM(DB28:DB34) -> 0 | DC35: =SUM(DC28:DC34) -> 0 | DD35: =SUM(DD28:DD34) -> 0 | ... EA35: =SUM(EA28:EA34) -> 14.01 | EC35: =SUM(EC28:EC34) -> 0 | ED35: =SUM(ED28:ED34) -> 0 | EE35: =SUM(EE28:EE34) -> 0 | EF35: =SUM(EF28:EF34) -> 0 | EG35: =SUM(EG28:EG34) -> 0 | EH35: =SUM(EH28:EH34) -> 0 | EI35: =SUM(EI28:EI34) -> 0 | EJ35: =SUM(EJ28:EJ34) -> 0 | ... FH35: =SUM(FH28:FH34) -> 14.01 | FJ35: =SUM(FJ28:FJ34) -> 0 | FK35: =SUM(FK28:FK34) -> 0 | FL35: =SUM(FL28:FL34) -> 0 | FM35: =SUM(FM28:FM34) -> 0 | FN35: =SUM(FN28:FN34) -> 0 | FO35: =SUM(FO28:FO34) -> 0 | FP35: =SUM(FP28:FP34) -> 0 | FQ35: =SUM(FQ28:FQ34) -> 0 | ... GN35: =SUM(GN28:GN34) -> 549.63 | GP35: =SUM(GP28:GP34) -> 0 | GQ35: =SUM(GQ28:GQ34) -> 0 | GR35: =SUM(GR28:GR34) -> 0 | GS35: =SUM(GS28:GS34) -> 0 | GT35: =SUM(GT28:GT34) -> 0 | GU35: =SUM(GU28:GU34) -> 0 | GV35: =SUM(GV28:GV34) -> 0 | GW35: =SUM(GW28:GW34) -> 0 | ... HU35: =SUM(HU28:HU34) -> 14.01 | HW35: =SUM(HW28:HW34) -> 0 | HX35: =SUM(HX28:HX34) -> 0 | HY35: =SUM(HY28:HY34) -> 0 | HZ35: =SUM(HZ28:HZ34) -> 0 | IA35: =SUM(IA28:IA34) -> 0 | IB35: =SUM(IB28:IB34) -> 0 | IC35: =SUM(IC28:IC34) -> 0 | ID35: =SUM(ID28:ID34) -> 0 | ... JB35: =SUM(JB28:JB34) -> 14.01 | JD35: =SUM(JD28:JD34) -> 0 | JE35: =SUM(JE28:JE34) -> 0 | JF35: =SUM(JF28:JF34) -> 0 | JG35: =SUM(JG28:JG34) -> 0 | JH35: =SUM(JH28:JH34) -> 0 | JI35: =SUM(JI28:JI34) -> 0 | JJ35: =SUM(JJ28:JJ34) -> 0 | JK35: =SUM(JK28:JK34) -> 0 | ... KH35: =SUM(KH28:KH34) -> 14.01 | KJ35: =SUM(KJ28:KJ34) -> 0 | KK35: =SUM(KK28:KK34) -> 0 | KL35: =SUM(KL28:KL34) -> 0 | KM35: =SUM(KM28:KM34) -> 0 | KN35: =SUM(KN28:KN34) -> 0 | KO35: =SUM(KO28:KO34) -> 0 | KP35: =SUM(KP28:KP34) -> 0 | KQ35: =SUM(KQ28:KQ34) -> 0 | ... LO35: =SUM(LO28:LO34) -> 14.01 | LQ35: =SUM(LQ28:LQ34) -> 0 | LR35: =SUM(LR28:LR34) -> 0 | LS35: =SUM(LS28:LS34) -> 0 | LT35: =SUM(LT28:LT34) -> 0 | LU35: =SUM(LU28:LU34) -> 0 | LV35: =SUM(LV28:LV34) -> 0 | LW35: =SUM(LW28:LW34) -> 0 | LX35: =SUM(LX28:LX34) -> 0 | ... MU35: =SUM(MU28:MU34) -> 14.01 | MW35: =SUM(MW28:MW34) -> 0 | MX35: =SUM(MX28:MX34) -> 0 | MY35: =SUM(MY28:MY34) -> 0 | MZ35: =SUM(MZ28:MZ34) -> 0 | NA35: =SUM(NA28:NA34) -> 0 | NB35: =SUM(NB28:NB34) -> 0 | NC35: =SUM(NC28:NC34) -> 0 | ND35: =SUM(ND28:ND34) -> 0 | ... OB35: =SUM(OB28:OB34) -> 14.01 | OC35: =SUM(AI35,BN35,CU35,EA35,FH35,GN35,HU35,JB35,KH35,LO35,MU35,OB35) -> 1239.28 | OE35: =SUM(OE28:OE34) -> 0 | OF35: =SUM(OF28:OF34) -> 0 | OG35: =SUM(OG28:OG34) -> 0 | OH35: =SUM(OH28:OH34) -> 0 | OI35: =SUM(OI28:OI34) -> 0 | OJ35: =SUM(OJ28:OJ34) -> 0 | OK35: =SUM(OK28:OK34) -> 0 | OL35: =SUM(OL28:OL34) -> 0 | ... PJ35: =SUM(PJ28:PJ34) -> 0 | PL35: =SUM(PL28:PL34) -> 0 | PM35: =SUM(PM28:PM34) -> 0 | PN35: =SUM(PN28:PN34) -> 0 | PO35: =SUM(PO28:PO34) -> 0 | PP35: =SUM(PP28:PP34) -> 0 | PQ35: =SUM(PQ28:PQ34) -> 0 | PR35: =SUM(PR28:PR34) -> 0 | PS35: =SUM(PS28:PS34) -> 0 | ... QO35: =SUM(QO28:QO34) -> 0 | QQ35: =SUM(QQ28:QQ34) -> 0 | QR35: =SUM(QR28:QR34) -> 0 | QS35: =SUM(QS28:QS34) -> 0 | QT35: =SUM(QT28:QT34) -> 0 | QU35: =SUM(QU28:QU34) -> 0 | QV35: =SUM(QV28:QV34) -> 0 | QW35: =SUM(QW28:QW34) -> 0 | QX35: =SUM(QX28:QX34) -> 0 | ... RV35: =SUM(RV28:RV34) -> 0 | RW35: =SUM(PJ35,QO35,RV35) -> 0
A37: 1 | B37: DESPESAS COM PESSOAL
B38: Folha de Pagamento (PJ) | AI38: =SUM(D38:AH38) -> 0 | BN38: =SUM(AK38:BM38) -> 0 | CU38: =SUM(BP38:CT38) -> 0 | EA38: =SUM(CW38:DZ38) -> 0 | FH38: =SUM(EC38:FG38) -> 0 | GN38: =SUM(FJ38:GM38) -> 0 | HU38: =SUM(GP38:HT38) -> 0 | JB38: =SUM(HW38:JA38) -> 0 | KH38: =SUM(JD38:KG38) -> 0 | LO38: =SUM(KJ38:LN38) -> 0 | MU38: =SUM(LQ38:MT38) -> 0 | OB38: =SUM(MW38:OA38) -> 0 | OC38: =SUM(AI38,BN38,CU38,EA38,FH38,GN38,HU38,JB38,KH38,LO38,MU38,OB38) -> 0 | PJ38: =SUM(OE38:PI38) -> 0 | QO38: =SUM(PL38:QN38) -> 0 | RV38: =SUM(QQ38:RU38) -> 0 | RW38: =SUM(PJ38,QO38,RV38) -> 0
B39: Folha de Pagamento (ESTAGIÁRIO) | AI39: =SUM(D39:AH39) -> 0 | BN39: =SUM(AK39:BM39) -> 0 | CU39: =SUM(BP39:CT39) -> 0 | EA39: =SUM(CW39:DZ39) -> 0 | FH39: =SUM(EC39:FG39) -> 0 | GN39: =SUM(FJ39:GM39) -> 0 | HU39: =SUM(GP39:HT39) -> 0 | JB39: =SUM(HW39:JA39) -> 0 | KH39: =SUM(JD39:KG39) -> 0 | LO39: =SUM(KJ39:LN39) -> 0 | MU39: =SUM(LQ39:MT39) -> 0 | OB39: =SUM(MW39:OA39) -> 0 | OC39: =SUM(AI39,BN39,CU39,EA39,FH39,GN39,HU39,JB39,KH39,LO39,MU39,OB39) -> 0 | PJ39: =SUM(OE39:PI39) -> 0 | QO39: =SUM(PL39:QN39) -> 0 | RV39: =SUM(QQ39:RU39) -> 0 | RW39: =SUM(PJ39,QO39,RV39) -> 0
B40: 13º Salário | AI40: =SUM(D40:AH40) -> 0 | BN40: =SUM(AK40:BM40) -> 0 | CU40: =SUM(BP40:CT40) -> 0 | EA40: =SUM(CW40:DZ40) -> 0 | FH40: =SUM(EC40:FG40) -> 0 | GN40: =SUM(FJ40:GM40) -> 0 | HU40: =SUM(GP40:HT40) -> 0 | JB40: =SUM(HW40:JA40) -> 0 | KH40: =SUM(JD40:KG40) -> 0 | LO40: =SUM(KJ40:LN40) -> 0 | MU40: =SUM(LQ40:MT40) -> 0 | OB40: =SUM(MW40:OA40) -> 0 | OC40: =SUM(AI40,BN40,CU40,EA40,FH40,GN40,HU40,JB40,KH40,LO40,MU40,OB40) -> 0 | PJ40: =SUM(OE40:PI40) -> 0 | QO40: =SUM(PL40:QN40) -> 0 | RV40: =SUM(QQ40:RU40) -> 0 | RW40: =SUM(PJ40,QO40,RV40) -> 0
B41: Vale Refeição | AI41: =SUM(D41:AH41) -> 0 | BN41: =SUM(AK41:BM41) -> 0 | CU41: =SUM(BP41:CT41) -> 0 | EA41: =SUM(CW41:DZ41) -> 0 | FH41: =SUM(EC41:FG41) -> 0 | GN41: =SUM(FJ41:GM41) -> 0 | HU41: =SUM(GP41:HT41) -> 0 | JB41: =SUM(HW41:JA41) -> 0 | KH41: =SUM(JD41:KG41) -> 0 | LO41: =SUM(KJ41:LN41) -> 0 | MU41: =SUM(LQ41:MT41) -> 0 | OB41: =SUM(MW41:OA41) -> 0 | OC41: =SUM(AI41,BN41,CU41,EA41,FH41,GN41,HU41,JB41,KH41,LO41,MU41,OB41) -> 0 | PJ41: =SUM(OE41:PI41) -> 0 | QO41: =SUM(PL41:QN41) -> 0 | RV41: =SUM(QQ41:RU41) -> 0 | RW41: =SUM(PJ41,QO41,RV41) -> 0
B42: Vale Transporte | AI42: =SUM(D42:AH42) -> 0 | BN42: =SUM(AK42:BM42) -> 0 | CU42: =SUM(BP42:CT42) -> 0 | EA42: =SUM(CW42:DZ42) -> 0 | FH42: =SUM(EC42:FG42) -> 0 | GN42: =SUM(FJ42:GM42) -> 0 | HU42: =SUM(GP42:HT42) -> 0 | JB42: =SUM(HW42:JA42) -> 0 | KH42: =SUM(JD42:KG42) -> 0 | LO42: =SUM(KJ42:LN42) -> 0 | MU42: =SUM(LQ42:MT42) -> 0 | OB42: =SUM(MW42:OA42) -> 0 | OC42: =SUM(AI42,BN42,CU42,EA42,FH42,GN42,HU42,JB42,KH42,LO42,MU42,OB42) -> 0 | PJ42: =SUM(OE42:PI42) -> 0 | QO42: =SUM(PL42:QN42) -> 0 | RV42: =SUM(QQ42:RU42) -> 0 | RW42: =SUM(PJ42,QO42,RV42) -> 0
B43: Assistência Médica | AI43: =SUM(D43:AH43) -> 0 | BN43: =SUM(AK43:BM43) -> 0 | CU43: =SUM(BP43:CT43) -> 0 | EA43: =SUM(CW43:DZ43) -> 0 | FH43: =SUM(EC43:FG43) -> 0 | GN43: =SUM(FJ43:GM43) -> 0 | HU43: =SUM(GP43:HT43) -> 0 | JB43: =SUM(HW43:JA43) -> 0 | KH43: =SUM(JD43:KG43) -> 0 | LO43: =SUM(KJ43:LN43) -> 0 | MU43: =SUM(LQ43:MT43) -> 0 | OB43: =SUM(MW43:OA43) -> 0 | OC43: =SUM(AI43,BN43,CU43,EA43,FH43,GN43,HU43,JB43,KH43,LO43,MU43,OB43) -> 0 | PJ43: =SUM(OE43:PI43) -> 0 | QO43: =SUM(PL43:QN43) -> 0 | RV43: =SUM(QQ43:RU43) -> 0 | RW43: =SUM(PJ43,QO43,RV43) -> 0
B44: Seguro de Vida | AI44: =SUM(D44:AH44) -> 0 | BN44: =SUM(AK44:BM44) -> 0 | CU44: =SUM(BP44:CT44) -> 0 | EA44: =SUM(CW44:DZ44) -> 0 | FH44: =SUM(EC44:FG44) -> 0 | GN44: =SUM(FJ44:GM44) -> 0 | HU44: =SUM(GP44:HT44) -> 0 | JB44: =SUM(HW44:JA44) -> 0 | KH44: =SUM(JD44:KG44) -> 0 | LO44: =SUM(KJ44:LN44) -> 0 | MU44: =SUM(LQ44:MT44) -> 0 | OB44: =SUM(MW44:OA44) -> 0 | OC44: =SUM(AI44,BN44,CU44,EA44,FH44,GN44,HU44,JB44,KH44,LO44,MU44,OB44) -> 0 | PJ44: =SUM(OE44:PI44) -> 0 | QO44: =SUM(PL44:QN44) -> 0 | RV44: =SUM(QQ44:RU44) -> 0 | RW44: =SUM(PJ44,QO44,RV44) -> 0
B45: Rescisões | AI45: =SUM(D45:AH45) -> 0 | BN45: =SUM(AK45:BM45) -> 0 | CU45: =SUM(BP45:CT45) -> 0 | EA45: =SUM(CW45:DZ45) -> 0 | FH45: =SUM(EC45:FG45) -> 0 | GN45: =SUM(FJ45:GM45) -> 0 | HU45: =SUM(GP45:HT45) -> 0 | JB45: =SUM(HW45:JA45) -> 0 | KH45: =SUM(JD45:KG45) -> 0 | LO45: =SUM(KJ45:LN45) -> 0 | MU45: =SUM(LQ45:MT45) -> 0 | OB45: =SUM(MW45:OA45) -> 0 | OC45: =SUM(AI45,BN45,CU45,EA45,FH45,GN45,HU45,JB45,KH45,LO45,MU45,OB45) -> 0 | PJ45: =SUM(OE45:PI45) -> 0 | QO45: =SUM(PL45:QN45) -> 0 | RV45: =SUM(QQ45:RU45) -> 0 | RW45: =SUM(PJ45,QO45,RV45) -> 0
B46: INSS - GPS | AI46: =SUM(D46:AH46) -> 0 | BN46: =SUM(AK46:BM46) -> 0 | CU46: =SUM(BP46:CT46) -> 0 | EA46: =SUM(CW46:DZ46) -> 0 | FH46: =SUM(EC46:FG46) -> 0 | GN46: =SUM(FJ46:GM46) -> 0 | HU46: =SUM(GP46:HT46) -> 0 | JB46: =SUM(HW46:JA46) -> 0 | KH46: =SUM(JD46:KG46) -> 0 | LO46: =SUM(KJ46:LN46) -> 0 | MU46: =SUM(LQ46:MT46) -> 0 | OB46: =SUM(MW46:OA46) -> 0 | OC46: =SUM(AI46,BN46,CU46,EA46,FH46,GN46,HU46,JB46,KH46,LO46,MU46,OB46) -> 0 | PJ46: =SUM(OE46:PI46) -> 0 | QO46: =SUM(PL46:QN46) -> 0 | RV46: =SUM(QQ46:RU46) -> 0 | RW46: =SUM(PJ46,QO46,RV46) -> 0
B47: Outras Despesas com Pessoal | AI47: =SUM(D47:AH47) -> 0 | BN47: =SUM(AK47:BM47) -> 0 | CU47: =SUM(BP47:CT47) -> 0 | EA47: =SUM(CW47:DZ47) -> 0 | FH47: =SUM(EC47:FG47) -> 0 | GN47: =SUM(FJ47:GM47) -> 0 | HU47: =SUM(GP47:HT47) -> 0 | JB47: =SUM(HW47:JA47) -> 0 | KH47: =SUM(JD47:KG47) -> 0 | LO47: =SUM(KJ47:LN47) -> 0 | MU47: =SUM(LQ47:MT47) -> 0 | OB47: =SUM(MW47:OA47) -> 0 | OC47: =SUM(AI47,BN47,CU47,EA47,FH47,GN47,HU47,JB47,KH47,LO47,MU47,OB47) -> 0 | PJ47: =SUM(OE47:PI47) -> 0 | QO47: =SUM(PL47:QN47) -> 0 | RV47: =SUM(QQ47:RU47) -> 0 | RW47: =SUM(PJ47,QO47,RV47) -> 0
B48: TOTAL DESPESA COM PESSOAL | D48: =SUM(D38:D47) -> 0 | E48: =SUM(E38:E47) -> 0 | F48: =SUM(F38:F47) -> 0 | G48: =SUM(G38:G47) -> 0 | H48: =SUM(H38:H47) -> 0 | I48: =SUM(I38:I47) -> 0 | J48: =SUM(J38:J47) -> 0 | K48: =SUM(K38:K47) -> 0 | ... AI48: =SUM(AI38:AI47) -> 0 | AK48: =SUM(AK38:AK47) -> 0 | AL48: =SUM(AL38:AL47) -> 0 | AM48: =SUM(AM38:AM47) -> 0 | AN48: =SUM(AN38:AN47) -> 0 | AO48: =SUM(AO38:AO47) -> 0 | AP48: =SUM(AP38:AP47) -> 0 | AQ48: =SUM(AQ38:AQ47) -> 0 | AR48: =SUM(AR38:AR47) -> 0 | ... BN48: =SUM(BN38:BN47) -> 0 | BP48: =SUM(BP38:BP47) -> 0 | BQ48: =SUM(BQ38:BQ47) -> 0 | BR48: =SUM(BR38:BR47) -> 0 | BS48: =SUM(BS38:BS47) -> 0 | BT48: =SUM(BT38:BT47) -> 0 | BU48: =SUM(BU38:BU47) -> 0 | BV48: =SUM(BV38:BV47) -> 0 | BW48: =SUM(BW38:BW47) -> 0 | ... CU48: =SUM(CU38:CU47) -> 0 | CW48: =SUM(CW38:CW47) -> 0 | CX48: =SUM(CX38:CX47) -> 0 | CY48: =SUM(CY38:CY47) -> 0 | CZ48: =SUM(CZ38:CZ47) -> 0 | DA48: =SUM(DA38:DA47) -> 0 | DB48: =SUM(DB38:DB47) -> 0 | DC48: =SUM(DC38:DC47) -> 0 | DD48: =SUM(DD38:DD47) -> 0 | ... EA48: =SUM(EA38:EA47) -> 0 | EC48: =SUM(EC38:EC47) -> 0 | ED48: =SUM(ED38:ED47) -> 0 | EE48: =SUM(EE38:EE47) -> 0 | EF48: =SUM(EF38:EF47) -> 0 | EG48: =SUM(EG38:EG47) -> 0 | EH48: =SUM(EH38:EH47) -> 0 | EI48: =SUM(EI38:EI47) -> 0 | EJ48: =SUM(EJ38:EJ47) -> 0 | ... FH48: =SUM(FH38:FH47) -> 0 | FJ48: =SUM(FJ38:FJ47) -> 0 | FK48: =SUM(FK38:FK47) -> 0 | FL48: =SUM(FL38:FL47) -> 0 | FM48: =SUM(FM38:FM47) -> 0 | FN48: =SUM(FN38:FN47) -> 0 | FO48: =SUM(FO38:FO47) -> 0 | FP48: =SUM(FP38:FP47) -> 0 | FQ48: =SUM(FQ38:FQ47) -> 0 | ... GN48: =SUM(GN38:GN47) -> 0 | GP48: =SUM(GP38:GP47) -> 0 | GQ48: =SUM(GQ38:GQ47) -> 0 | GR48: =SUM(GR38:GR47) -> 0 | GS48: =SUM(GS38:GS47) -> 0 | GT48: =SUM(GT38:GT47) -> 0 | GU48: =SUM(GU38:GU47) -> 0 | GV48: =SUM(GV38:GV47) -> 0 | GW48: =SUM(GW38:GW47) -> 0 | ... HU48: =SUM(HU38:HU47) -> 0 | HW48: =SUM(HW38:HW47) -> 0 | HX48: =SUM(HX38:HX47) -> 0 | HY48: =SUM(HY38:HY47) -> 0 | HZ48: =SUM(HZ38:HZ47) -> 0 | IA48: =SUM(IA38:IA47) -> 0 | IB48: =SUM(IB38:IB47) -> 0 | IC48: =SUM(IC38:IC47) -> 0 | ID48: =SUM(ID38:ID47) -> 0 | ... JB48: =SUM(JB38:JB47) -> 0 | JD48: =SUM(JD38:JD47) -> 0 | JE48: =SUM(JE38:JE47) -> 0 | JF48: =SUM(JF38:JF47) -> 0 | JG48: =SUM(JG38:JG47) -> 0 | JH48: =SUM(JH38:JH47) -> 0 | JI48: =SUM(JI38:JI47) -> 0 | JJ48: =SUM(JJ38:JJ47) -> 0 | JK48: =SUM(JK38:JK47) -> 0 | ... KH48: =SUM(KH38:KH47) -> 0 | KJ48: =SUM(KJ38:KJ47) -> 0 | KK48: =SUM(KK38:KK47) -> 0 | KL48: =SUM(KL38:KL47) -> 0 | KM48: =SUM(KM38:KM47) -> 0 | KN48: =SUM(KN38:KN47) -> 0 | KO48: =SUM(KO38:KO47) -> 0 | KP48: =SUM(KP38:KP47) -> 0 | KQ48: =SUM(KQ38:KQ47) -> 0 | ... LO48: =SUM(LO38:LO47) -> 0 | LQ48: =SUM(LQ38:LQ47) -> 0 | LR48: =SUM(LR38:LR47) -> 0 | LS48: =SUM(LS38:LS47) -> 0 | LT48: =SUM(LT38:LT47) -> 0 | LU48: =SUM(LU38:LU47) -> 0 | LV48: =SUM(LV38:LV47) -> 0 | LW48: =SUM(LW38:LW47) -> 0 | LX48: =SUM(LX38:LX47) -> 0 | ... MU48: =SUM(MU38:MU47) -> 0 | MW48: =SUM(MW38:MW47) -> 0 | MX48: =SUM(MX38:MX47) -> 0 | MY48: =SUM(MY38:MY47) -> 0 | MZ48: =SUM(MZ38:MZ47) -> 0 | NA48: =SUM(NA38:NA47) -> 0 | NB48: =SUM(NB38:NB47) -> 0 | NC48: =SUM(NC38:NC47) -> 0 | ND48: =SUM(ND38:ND47) -> 0 | ... OB48: =SUM(OB38:OB47) -> 0 | OC48: =SUM(AI48,BN48,CU48,EA48,FH48,GN48,HU48,JB48,KH48,LO48,MU48,OB48) -> 0 | OE48: =SUM(OE38:OE47) -> 0 | OF48: =SUM(OF38:OF47) -> 0 | OG48: =SUM(OG38:OG47) -> 0 | OH48: =SUM(OH38:OH47) -> 0 | OI48: =SUM(OI38:OI47) -> 0 | OJ48: =SUM(OJ38:OJ47) -> 0 | OK48: =SUM(OK38:OK47) -> 0 | OL48: =SUM(OL38:OL47) -> 0 | ... PJ48: =SUM(PJ38:PJ47) -> 0 | PL48: =SUM(PL38:PL47) -> 0 | PM48: =SUM(PM38:PM47) -> 0 | PN48: =SUM(PN38:PN47) -> 0 | PO48: =SUM(PO38:PO47) -> 0 | PP48: =SUM(PP38:PP47) -> 0 | PQ48: =SUM(PQ38:PQ47) -> 0 | PR48: =SUM(PR38:PR47) -> 0 | PS48: =SUM(PS38:PS47) -> 0 | ... QO48: =SUM(QO38:QO47) -> 0 | QQ48: =SUM(QQ38:QQ47) -> 0 | QR48: =SUM(QR38:QR47) -> 0 | QS48: =SUM(QS38:QS47) -> 0 | QT48: =SUM(QT38:QT47) -> 0 | QU48: =SUM(QU38:QU47) -> 0 | QV48: =SUM(QV38:QV47) -> 0 | QW48: =SUM(QW38:QW47) -> 0 | QX48: =SUM(QX38:QX47) -> 0 | ... RV48: =SUM(RV38:RV47) -> 0 | RW48: =SUM(PJ48,QO48,RV48) -> 0
A50: 1 | B50: DESPESAS COM FREELANCER
B51: Freelancer Fixo | AI51: =SUM(D51:AH51) -> 0 | BN51: =SUM(AK51:BM51) -> 0 | CU51: =SUM(BP51:CT51) -> 0 | EA51: =SUM(CW51:DZ51) -> 0 | FH51: =SUM(EC51:FG51) -> 0 | GN51: =SUM(FJ51:GM51) -> 0 | HU51: =SUM(GP51:HT51) -> 0 | JB51: =SUM(HW51:JA51) -> 0 | KH51: =SUM(JD51:KG51) -> 0 | LO51: =SUM(KJ51:LN51) -> 0 | MU51: =SUM(LQ51:MT51) -> 0 | OB51: =SUM(MW51:OA51) -> 0 | OC51: =SUM(AI51,BN51,CU51,EA51,FH51,GN51,HU51,JB51,KH51,LO51,MU51,OB51) -> 0 | PJ51: =SUM(OE51:PI51) -> 0 | QO51: =SUM(PL51:QN51) -> 0 | RV51: =SUM(QQ51:RU51) -> 0 | RW51: =SUM(PJ51,QO51,RV51) -> 0
B52: Freelancer Variável | AI52: =SUM(D52:AH52) -> 0 | BN52: =SUM(AK52:BM52) -> 0 | CU52: =SUM(BP52:CT52) -> 0 | EA52: =SUM(CW52:DZ52) -> 0 | FH52: =SUM(EC52:FG52) -> 0 | GN52: =SUM(FJ52:GM52) -> 0 | HU52: =SUM(GP52:HT52) -> 0 | JB52: =SUM(HW52:JA52) -> 0 | KH52: =SUM(JD52:KG52) -> 0 | LO52: =SUM(KJ52:LN52) -> 0 | MU52: =SUM(LQ52:MT52) -> 0 | OB52: =SUM(MW52:OA52) -> 0 | OC52: =SUM(AI52,BN52,CU52,EA52,FH52,GN52,HU52,JB52,KH52,LO52,MU52,OB52) -> 0 | PJ52: =SUM(OE52:PI52) -> 0 | QO52: =SUM(PL52:QN52) -> 0 | RV52: =SUM(QQ52:RU52) -> 0 | RW52: =SUM(PJ52,QO52,RV52) -> 0
B53: TOTAL DESPESA FREELANCER | D53: =SUM(D51:D52) -> 0 | E53: =SUM(E51:E52) -> 0 | F53: =SUM(F51:F52) -> 0 | G53: =SUM(G51:G52) -> 0 | H53: =SUM(H51:H52) -> 0 | I53: =SUM(I51:I52) -> 0 | J53: =SUM(J51:J52) -> 0 | K53: =SUM(K51:K52) -> 0 | ... AI53: =SUM(AI51:AI52) -> 0 | AK53: =SUM(AK51:AK52) -> 0 | AL53: =SUM(AL51:AL52) -> 0 | AM53: =SUM(AM51:AM52) -> 0 | AN53: =SUM(AN51:AN52) -> 0 | AO53: =SUM(AO51:AO52) -> 0 | AP53: =SUM(AP51:AP52) -> 0 | AQ53: =SUM(AQ51:AQ52) -> 0 | AR53: =SUM(AR51:AR52) -> 0 | ... BN53: =SUM(BN51:BN52) -> 0 | BP53: =SUM(BP51:BP52) -> 0 | BQ53: =SUM(BQ51:BQ52) -> 0 | BR53: =SUM(BR51:BR52) -> 0 | BS53: =SUM(BS51:BS52) -> 0 | BT53: =SUM(BT51:BT52) -> 0 | BU53: =SUM(BU51:BU52) -> 0 | BV53: =SUM(BV51:BV52) -> 0 | BW53: =SUM(BW51:BW52) -> 0 | ... CU53: =SUM(CU51:CU52) -> 0 | CW53: =SUM(CW51:CW52) -> 0 | CX53: =SUM(CX51:CX52) -> 0 | CY53: =SUM(CY51:CY52) -> 0 | CZ53: =SUM(CZ51:CZ52) -> 0 | DA53: =SUM(DA51:DA52) -> 0 | DB53: =SUM(DB51:DB52) -> 0 | DC53: =SUM(DC51:DC52) -> 0 | DD53: =SUM(DD51:DD52) -> 0 | ... EA53: =SUM(EA51:EA52) -> 0 | EC53: =SUM(EC51:EC52) -> 0 | ED53: =SUM(ED51:ED52) -> 0 | EE53: =SUM(EE51:EE52) -> 0 | EF53: =SUM(EF51:EF52) -> 0 | EG53: =SUM(EG51:EG52) -> 0 | EH53: =SUM(EH51:EH52) -> 0 | EI53: =SUM(EI51:EI52) -> 0 | EJ53: =SUM(EJ51:EJ52) -> 0 | ... FH53: =SUM(FH51:FH52) -> 0 | FJ53: =SUM(FJ51:FJ52) -> 0 | FK53: =SUM(FK51:FK52) -> 0 | FL53: =SUM(FL51:FL52) -> 0 | FM53: =SUM(FM51:FM52) -> 0 | FN53: =SUM(FN51:FN52) -> 0 | FO53: =SUM(FO51:FO52) -> 0 | FP53: =SUM(FP51:FP52) -> 0 | FQ53: =SUM(FQ51:FQ52) -> 0 | ... GN53: =SUM(GN51:GN52) -> 0 | GP53: =SUM(GP51:GP52) -> 0 | GQ53: =SUM(GQ51:GQ52) -> 0 | GR53: =SUM(GR51:GR52) -> 0 | GS53: =SUM(GS51:GS52) -> 0 | GT53: =SUM(GT51:GT52) -> 0 | GU53: =SUM(GU51:GU52) -> 0 | GV53: =SUM(GV51:GV52) -> 0 | GW53: =SUM(GW51:GW52) -> 0 | ... HU53: =SUM(HU51:HU52) -> 0 | HW53: =SUM(HW51:HW52) -> 0 | HX53: =SUM(HX51:HX52) -> 0 | HY53: =SUM(HY51:HY52) -> 0 | HZ53: =SUM(HZ51:HZ52) -> 0 | IA53: =SUM(IA51:IA52) -> 0 | IB53: =SUM(IB51:IB52) -> 0 | IC53: =SUM(IC51:IC52) -> 0 | ID53: =SUM(ID51:ID52) -> 0 | ... JB53: =SUM(JB51:JB52) -> 0 | JD53: =SUM(JD51:JD52) -> 0 | JE53: =SUM(JE51:JE52) -> 0 | JF53: =SUM(JF51:JF52) -> 0 | JG53: =SUM(JG51:JG52) -> 0 | JH53: =SUM(JH51:JH52) -> 0 | JI53: =SUM(JI51:JI52) -> 0 | JJ53: =SUM(JJ51:JJ52) -> 0 | JK53: =SUM(JK51:JK52) -> 0 | ... KH53: =SUM(KH51:KH52) -> 0 | KJ53: =SUM(KJ51:KJ52) -> 0 | KK53: =SUM(KK51:KK52) -> 0 | KL53: =SUM(KL51:KL52) -> 0 | KM53: =SUM(KM51:KM52) -> 0 | KN53: =SUM(KN51:KN52) -> 0 | KO53: =SUM(KO51:KO52) -> 0 | KP53: =SUM(KP51:KP52) -> 0 | KQ53: =SUM(KQ51:KQ52) -> 0 | ... LO53: =SUM(LO51:LO52) -> 0 | LQ53: =SUM(LQ51:LQ52) -> 0 | LR53: =SUM(LR51:LR52) -> 0 | LS53: =SUM(LS51:LS52) -> 0 | LT53: =SUM(LT51:LT52) -> 0 | LU53: =SUM(LU51:LU52) -> 0 | LV53: =SUM(LV51:LV52) -> 0 | LW53: =SUM(LW51:LW52) -> 0 | LX53: =SUM(LX51:LX52) -> 0 | ... MU53: =SUM(MU51:MU52) -> 0 | MW53: =SUM(MW51:MW52) -> 0 | MX53: =SUM(MX51:MX52) -> 0 | MY53: =SUM(MY51:MY52) -> 0 | MZ53: =SUM(MZ51:MZ52) -> 0 | NA53: =SUM(NA51:NA52) -> 0 | NB53: =SUM(NB51:NB52) -> 0 | NC53: =SUM(NC51:NC52) -> 0 | ND53: =SUM(ND51:ND52) -> 0 | ... OB53: =SUM(OB51:OB52) -> 0 | OC53: =SUM(AI53,BN53,CU53,EA53,FH53,GN53,HU53,JB53,KH53,LO53,MU53,OB53) -> 0 | OE53: =SUM(OE51:OE52) -> 0 | OF53: =SUM(OF51:OF52) -> 0 | OG53: =SUM(OG51:OG52) -> 0 | OH53: =SUM(OH51:OH52) -> 0 | OI53: =SUM(OI51:OI52) -> 0 | OJ53: =SUM(OJ51:OJ52) -> 0 | OK53: =SUM(OK51:OK52) -> 0 | OL53: =SUM(OL51:OL52) -> 0 | ... PJ53: =SUM(PJ51:PJ52) -> 0 | PL53: =SUM(PL51:PL52) -> 0 | PM53: =SUM(PM51:PM52) -> 0 | PN53: =SUM(PN51:PN52) -> 0 | PO53: =SUM(PO51:PO52) -> 0 | PP53: =SUM(PP51:PP52) -> 0 | PQ53: =SUM(PQ51:PQ52) -> 0 | PR53: =SUM(PR51:PR52) -> 0 | PS53: =SUM(PS51:PS52) -> 0 | ... QO53: =SUM(QO51:QO52) -> 0 | QQ53: =SUM(QQ51:QQ52) -> 0 | QR53: =SUM(QR51:QR52) -> 0 | QS53: =SUM(QS51:QS52) -> 0 | QT53: =SUM(QT51:QT52) -> 0 | QU53: =SUM(QU51:QU52) -> 0 | QV53: =SUM(QV51:QV52) -> 0 | QW53: =SUM(QW51:QW52) -> 0 | QX53: =SUM(QX51:QX52) -> 0 | ... RV53: =SUM(RV51:RV52) -> 0 | RW53: =SUM(PJ53,QO53,RV53) -> 0
A55: 1 | B55: DESPESAS DE SOCIOS - PAULO E CAROL
B56: Distribuição de Lucros - Sócios | AI56: =SUM(D56:AH56) -> 0 | BN56: =SUM(AK56:BM56) -> 0 | CU56: =SUM(BP56:CT56) -> 0 | EA56: =SUM(CW56:DZ56) -> 0 | FH56: =SUM(EC56:FG56) -> 0 | GN56: =SUM(FJ56:GM56) -> 0 | HU56: =SUM(GP56:HT56) -> 0 | JB56: =SUM(HW56:JA56) -> 0 | KH56: =SUM(JD56:KG56) -> 0 | LO56: =SUM(KJ56:LN56) -> 0 | MU56: =SUM(LQ56:MT56) -> 0 | OB56: =SUM(MW56:OA56) -> 0 | OC56: =SUM(AI56,BN56,CU56,EA56,FH56,GN56,HU56,JB56,KH56,LO56,MU56,OB56) -> 0 | PJ56: =SUM(OE56:PI56) -> 0 | QO56: =SUM(PL56:QN56) -> 0 | RV56: =SUM(QQ56:RU56) -> 0 | RW56: =SUM(PJ56,QO56,RV56) -> 0
B57: Distribuição de Lucros - Sócios - BV | AI57: =SUM(D57:AH57) -> 0 | BN57: =SUM(AK57:BM57) -> 0 | CU57: =SUM(BP57:CT57) -> 0 | EA57: =SUM(CW57:DZ57) -> 0 | FH57: =SUM(EC57:FG57) -> 0 | GN57: =SUM(FJ57:GM57) -> 0 | HU57: =SUM(GP57:HT57) -> 0 | JB57: =SUM(HW57:JA57) -> 0 | KH57: =SUM(JD57:KG57) -> 0 | LO57: =SUM(KJ57:LN57) -> 0 | MU57: =SUM(LQ57:MT57) -> 0 | OB57: =SUM(MW57:OA57) -> 0 | OC57: =SUM(AI57,BN57,CU57,EA57,FH57,GN57,HU57,JB57,KH57,LO57,MU57,OB57) -> 0 | PJ57: =SUM(OE57:PI57) -> 0 | QO57: =SUM(PL57:QN57) -> 0 | RV57: =SUM(QQ57:RU57) -> 0 | RW57: =SUM(PJ57,QO57,RV57) -> 0
B58: Pro-Labore | AI58: =SUM(D58:AH58) -> 0 | BN58: =SUM(AK58:BM58) -> 0 | CU58: =SUM(BP58:CT58) -> 0 | EA58: =SUM(CW58:DZ58) -> 0 | FH58: =SUM(EC58:FG58) -> 0 | GN58: =SUM(FJ58:GM58) -> 0 | HU58: =SUM(GP58:HT58) -> 0 | JB58: =SUM(HW58:JA58) -> 0 | KH58: =SUM(JD58:KG58) -> 0 | LO58: =SUM(KJ58:LN58) -> 0 | MU58: =SUM(LQ58:MT58) -> 0 | OB58: =SUM(MW58:OA58) -> 0 | OC58: =SUM(AI58,BN58,CU58,EA58,FH58,GN58,HU58,JB58,KH58,LO58,MU58,OB58) -> 0 | PJ58: =SUM(OE58:PI58) -> 0 | QO58: =SUM(PL58:QN58) -> 0 | RV58: =SUM(QQ58:RU58) -> 0 | RW58: =SUM(PJ58,QO58,RV58) -> 0
B59: Outras Despesas de Sócios | AI59: =SUM(D59:AH59) -> 0 | BN59: =SUM(AK59:BM59) -> 0 | CU59: =SUM(BP59:CT59) -> 0 | EA59: =SUM(CW59:DZ59) -> 0 | FH59: =SUM(EC59:FG59) -> 0 | GN59: =SUM(FJ59:GM59) -> 0 | HU59: =SUM(GP59:HT59) -> 0 | JB59: =SUM(HW59:JA59) -> 0 | KH59: =SUM(JD59:KG59) -> 0 | LO59: =SUM(KJ59:LN59) -> 0 | MU59: =SUM(LQ59:MT59) -> 0 | OB59: =SUM(MW59:OA59) -> 0 | OC59: =SUM(AI59,BN59,CU59,EA59,FH59,GN59,HU59,JB59,KH59,LO59,MU59,OB59) -> 0 | PJ59: =SUM(OE59:PI59) -> 0 | QO59: =SUM(PL59:QN59) -> 0 | RV59: =SUM(QQ59:RU59) -> 0 | RW59: =SUM(PJ59,QO59,RV59) -> 0
A60: 2 | B60: Reembolso - Despesas | D60: =SUM(D61:D66) -> 0 | E60: =SUM(E61:E66) -> 0 | F60: =SUM(F61:F66) -> 0 | G60: =SUM(G61:G66) -> 0 | H60: =SUM(H61:H66) -> 0 | I60: =SUM(I61:I66) -> 0 | J60: =SUM(J61:J66) -> 0 | K60: =SUM(K61:K66) -> 0 | ... AH60: =SUM(AH61:AH66) -> 0 | AI60: =SUM(D60:AH60) -> 0 | AK60: =SUM(AK61:AK66) -> 0 | AL60: =SUM(AL61:AL66) -> 0 | AM60: =SUM(AM61:AM66) -> 0 | AN60: =SUM(AN61:AN66) -> 0 | AO60: =SUM(AO61:AO66) -> 0 | AP60: =SUM(AP61:AP66) -> 0 | AQ60: =SUM(AQ61:AQ66) -> 0 | AR60: =SUM(AR61:AR66) -> 0 | ... BM60: =SUM(BM61:BM66) -> 0 | BN60: =SUM(AK60:BM60) -> 0 | BP60: =SUM(BP61:BP66) -> 0 | BQ60: =SUM(BQ61:BQ66) -> 0 | BR60: =SUM(BR61:BR66) -> 0 | BS60: =SUM(BS61:BS66) -> 0 | BT60: =SUM(BT61:BT66) -> 0 | BU60: =SUM(BU61:BU66) -> 0 | BV60: =SUM(BV61:BV66) -> 0 | BW60: =SUM(BW61:BW66) -> 0 | ... CT60: =SUM(CT61:CT66) -> 0 | CU60: =SUM(BP60:CT60) -> 0 | CW60: =SUM(CW61:CW66) -> 0 | CX60: =SUM(CX61:CX66) -> 0 | CY60: =SUM(CY61:CY66) -> 0 | CZ60: =SUM(CZ61:CZ66) -> 0 | DA60: =SUM(DA61:DA66) -> 0 | DB60: =SUM(DB61:DB66) -> 0 | DC60: =SUM(DC61:DC66) -> 0 | DD60: =SUM(DD61:DD66) -> 0 | ... DZ60: =SUM(DZ61:DZ66) -> 0 | EA60: =SUM(CW60:DZ60) -> 0 | EC60: =SUM(EC61:EC66) -> 0 | ED60: =SUM(ED61:ED66) -> 0 | EE60: =SUM(EE61:EE66) -> 0 | EF60: =SUM(EF61:EF66) -> 0 | EG60: =SUM(EG61:EG66) -> 0 | EH60: =SUM(EH61:EH66) -> 0 | EI60: =SUM(EI61:EI66) -> 0 | EJ60: =SUM(EJ61:EJ66) -> 0 | ... FG60: =SUM(FG61:FG66) -> 0 | FH60: =SUM(EC60:FG60) -> 0 | FJ60: =SUM(FJ61:FJ66) -> 0 | FK60: =SUM(FK61:FK66) -> 0 | FL60: =SUM(FL61:FL66) -> 0 | FM60: =SUM(FM61:FM66) -> 0 | FN60: =SUM(FN61:FN66) -> 0 | FO60: =SUM(FO61:FO66) -> 0 | FP60: =SUM(FP61:FP66) -> 0 | FQ60: =SUM(FQ61:FQ66) -> 0 | ... GM60: =SUM(GM61:GM66) -> 0 | GN60: =SUM(FJ60:GM60) -> 0 | GP60: =SUM(GP61:GP66) -> 0 | GQ60: =SUM(GQ61:GQ66) -> 0 | GR60: =SUM(GR61:GR66) -> 0 | GS60: =SUM(GS61:GS66) -> 0 | GT60: =SUM(GT61:GT66) -> 0 | GU60: =SUM(GU61:GU66) -> 0 | GV60: =SUM(GV61:GV66) -> 0 | GW60: =SUM(GW61:GW66) -> 0 | ... HT60: =SUM(HT61:HT66) -> 0 | HU60: =SUM(GP60:HT60) -> 0 | HW60: =SUM(HW61:HW66) -> 0 | HX60: =SUM(HX61:HX66) -> 0 | HY60: =SUM(HY61:HY66) -> 0 | HZ60: =SUM(HZ61:HZ66) -> 0 | IA60: =SUM(IA61:IA66) -> 0 | IB60: =SUM(IB61:IB66) -> 0 | IC60: =SUM(IC61:IC66) -> 0 | ID60: =SUM(ID61:ID66) -> 0 | ... JA60: =SUM(JA61:JA66) -> 0 | JB60: =SUM(HW60:JA60) -> 0 | JD60: =SUM(JD61:JD66) -> 0 | JE60: =SUM(JE61:JE66) -> 0 | JF60: =SUM(JF61:JF66) -> 0 | JG60: =SUM(JG61:JG66) -> 0 | JH60: =SUM(JH61:JH66) -> 0 | JI60: =SUM(JI61:JI66) -> 0 | JJ60: =SUM(JJ61:JJ66) -> 0 | JK60: =SUM(JK61:JK66) -> 0 | ... KG60: =SUM(KG61:KG66) -> 0 | KH60: =SUM(JD60:KG60) -> 0 | KJ60: =SUM(KJ61:KJ66) -> 0 | KK60: =SUM(KK61:KK66) -> 0 | KL60: =SUM(KL61:KL66) -> 0 | KM60: =SUM(KM61:KM66) -> 0 | KN60: =SUM(KN61:KN66) -> 0 | KO60: =SUM(KO61:KO66) -> 0 | KP60: =SUM(KP61:KP66) -> 0 | KQ60: =SUM(KQ61:KQ66) -> 0 | ... LN60: =SUM(LN61:LN66) -> 0 | LO60: =SUM(KJ60:LN60) -> 0 | LQ60: =SUM(LQ61:LQ66) -> 0 | LR60: =SUM(LR61:LR66) -> 0 | LS60: =SUM(LS61:LS66) -> 0 | LT60: =SUM(LT61:LT66) -> 0 | LU60: =SUM(LU61:LU66) -> 0 | LV60: =SUM(LV61:LV66) -> 0 | LW60: =SUM(LW61:LW66) -> 0 | LX60: =SUM(LX61:LX66) -> 0 | ... MT60: =SUM(MT61:MT66) -> 0 | MU60: =SUM(LQ60:MT60) -> 0 | MW60: =SUM(MW61:MW66) -> 0 | MX60: =SUM(MX61:MX66) -> 0 | MY60: =SUM(MY61:MY66) -> 0 | MZ60: =SUM(MZ61:MZ66) -> 0 | NA60: =SUM(NA61:NA66) -> 0 | NB60: =SUM(NB61:NB66) -> 0 | NC60: =SUM(NC61:NC66) -> 0 | ND60: =SUM(ND61:ND66) -> 0 | ... OA60: =SUM(OA61:OA66) -> 0 | OB60: =SUM(MW60:OA60) -> 0 | OC60: =SUM(AI60,BN60,CU60,EA60,FH60,GN60,HU60,JB60,KH60,LO60,MU60,OB60) -> 0 | OE60: =SUM(OE61:OE66) -> 0 | OF60: =SUM(OF61:OF66) -> 0 | OG60: =SUM(OG61:OG66) -> 0 | OH60: =SUM(OH61:OH66) -> 0 | OI60: =SUM(OI61:OI66) -> 0 | OJ60: =SUM(OJ61:OJ66) -> 0 | OK60: =SUM(OK61:OK66) -> 0 | OL60: =SUM(OL61:OL66) -> 0 | ... PI60: =SUM(PI61:PI66) -> 0 | PJ60: =SUM(OE60:PI60) -> 0 | PL60: =SUM(PL61:PL66) -> 0 | PM60: =SUM(PM61:PM66) -> 0 | PN60: =SUM(PN61:PN66) -> 0 | PO60: =SUM(PO61:PO66) -> 0 | PP60: =SUM(PP61:PP66) -> 0 | PQ60: =SUM(PQ61:PQ66) -> 0 | PR60: =SUM(PR61:PR66) -> 0 | PS60: =SUM(PS61:PS66) -> 0 | ... QN60: =SUM(QN61:QN66) -> 0 | QO60: =SUM(PL60:QN60) -> 0 | QQ60: =SUM(QQ61:QQ66) -> 0 | QR60: =SUM(QR61:QR66) -> 0 | QS60: =SUM(QS61:QS66) -> 0 | QT60: =SUM(QT61:QT66) -> 0 | QU60: =SUM(QU61:QU66) -> 0 | QV60: =SUM(QV61:QV66) -> 0 | QW60: =SUM(QW61:QW66) -> 0 | QX60: =SUM(QX61:QX66) -> 0 | ... RU60: =SUM(RU61:RU66) -> 0 | RV60: =SUM(QQ60:RU60) -> 0 | RW60: =SUM(PJ60,QO60,RV60) -> 0
B61: *Passagem | AI61: =SUM(D61:AH61) -> 0 | BN61: =SUM(AK61:BM61) -> 0 | CU61: =SUM(BP61:CT61) -> 0 | EA61: =SUM(CW61:DZ61) -> 0 | FH61: =SUM(EC61:FG61) -> 0 | GN61: =SUM(FJ61:GM61) -> 0 | HU61: =SUM(GP61:HT61) -> 0 | JB61: =SUM(HW61:JA61) -> 0 | KH61: =SUM(JD61:KG61) -> 0 | LO61: =SUM(KJ61:LN61) -> 0 | MU61: =SUM(LQ61:MT61) -> 0 | OB61: =SUM(MW61:OA61) -> 0 | OC61: =SUM(AI61,BN61,CU61,EA61,FH61,GN61,HU61,JB61,KH61,LO61,MU61,OB61) -> 0 | PJ61: =SUM(OE61:PI61) -> 0 | QO61: =SUM(PL61:QN61) -> 0 | RV61: =SUM(QQ61:RU61) -> 0 | RW61: =SUM(PJ61,QO61,RV61) -> 0
B62: *Hospedagem | AI62: =SUM(D62:AH62) -> 0 | BN62: =SUM(AK62:BM62) -> 0 | CU62: =SUM(BP62:CT62) -> 0 | EA62: =SUM(CW62:DZ62) -> 0 | FH62: =SUM(EC62:FG62) -> 0 | GN62: =SUM(FJ62:GM62) -> 0 | HU62: =SUM(GP62:HT62) -> 0 | JB62: =SUM(HW62:JA62) -> 0 | KH62: =SUM(JD62:KG62) -> 0 | LO62: =SUM(KJ62:LN62) -> 0 | MU62: =SUM(LQ62:MT62) -> 0 | OB62: =SUM(MW62:OA62) -> 0 | OC62: =SUM(AI62,BN62,CU62,EA62,FH62,GN62,HU62,JB62,KH62,LO62,MU62,OB62) -> 0 | PJ62: =SUM(OE62:PI62) -> 0 | QO62: =SUM(PL62:QN62) -> 0 | RV62: =SUM(QQ62:RU62) -> 0 | RW62: =SUM(PJ62,QO62,RV62) -> 0
B63: *Estacionamento | AI63: =SUM(D63:AH63) -> 0 | BN63: =SUM(AK63:BM63) -> 0 | CU63: =SUM(BP63:CT63) -> 0 | EA63: =SUM(CW63:DZ63) -> 0 | FH63: =SUM(EC63:FG63) -> 0 | GN63: =SUM(FJ63:GM63) -> 0 | HU63: =SUM(GP63:HT63) -> 0 | JB63: =SUM(HW63:JA63) -> 0 | KH63: =SUM(JD63:KG63) -> 0 | LO63: =SUM(KJ63:LN63) -> 0 | MU63: =SUM(LQ63:MT63) -> 0 | OB63: =SUM(MW63:OA63) -> 0 | OC63: =SUM(AI63,BN63,CU63,EA63,FH63,GN63,HU63,JB63,KH63,LO63,MU63,OB63) -> 0 | PJ63: =SUM(OE63:PI63) -> 0 | QO63: =SUM(PL63:QN63) -> 0 | RV63: =SUM(QQ63:RU63) -> 0 | RW63: =SUM(PJ63,QO63,RV63) -> 0
B64: *Transporte (Uber) | AI64: =SUM(D64:AH64) -> 0 | BN64: =SUM(AK64:BM64) -> 0 | CU64: =SUM(BP64:CT64) -> 0 | EA64: =SUM(CW64:DZ64) -> 0 | FH64: =SUM(EC64:FG64) -> 0 | GN64: =SUM(FJ64:GM64) -> 0 | HU64: =SUM(GP64:HT64) -> 0 | JB64: =SUM(HW64:JA64) -> 0 | KH64: =SUM(JD64:KG64) -> 0 | LO64: =SUM(KJ64:LN64) -> 0 | MU64: =SUM(LQ64:MT64) -> 0 | OB64: =SUM(MW64:OA64) -> 0 | OC64: =SUM(AI64,BN64,CU64,EA64,FH64,GN64,HU64,JB64,KH64,LO64,MU64,OB64) -> 0 | PJ64: =SUM(OE64:PI64) -> 0 | QO64: =SUM(PL64:QN64) -> 0 | RV64: =SUM(QQ64:RU64) -> 0 | RW64: =SUM(PJ64,QO64,RV64) -> 0
B65: *Alimentação | AI65: =SUM(D65:AH65) -> 0 | BN65: =SUM(AK65:BM65) -> 0 | CU65: =SUM(BP65:CT65) -> 0 | EA65: =SUM(CW65:DZ65) -> 0 | FH65: =SUM(EC65:FG65) -> 0 | GN65: =SUM(FJ65:GM65) -> 0 | HU65: =SUM(GP65:HT65) -> 0 | JB65: =SUM(HW65:JA65) -> 0 | KH65: =SUM(JD65:KG65) -> 0 | LO65: =SUM(KJ65:LN65) -> 0 | MU65: =SUM(LQ65:MT65) -> 0 | OB65: =SUM(MW65:OA65) -> 0 | OC65: =SUM(AI65,BN65,CU65,EA65,FH65,GN65,HU65,JB65,KH65,LO65,MU65,OB65) -> 0 | PJ65: =SUM(OE65:PI65) -> 0 | QO65: =SUM(PL65:QN65) -> 0 | RV65: =SUM(QQ65:RU65) -> 0 | RW65: =SUM(PJ65,QO65,RV65) -> 0
B66: *Despesas Dvs | AI66: =SUM(D66:AH66) -> 0 | BN66: =SUM(AK66:BM66) -> 0 | CU66: =SUM(BP66:CT66) -> 0 | EA66: =SUM(CW66:DZ66) -> 0 | FH66: =SUM(EC66:FG66) -> 0 | GN66: =SUM(FJ66:GM66) -> 0 | HU66: =SUM(GP66:HT66) -> 0 | JB66: =SUM(HW66:JA66) -> 0 | KH66: =SUM(JD66:KG66) -> 0 | LO66: =SUM(KJ66:LN66) -> 0 | MU66: =SUM(LQ66:MT66) -> 0 | OB66: =SUM(MW66:OA66) -> 0 | OC66: =SUM(AI66,BN66,CU66,EA66,FH66,GN66,HU66,JB66,KH66,LO66,MU66,OB66) -> 0 | PJ66: =SUM(OE66:PI66) -> 0 | QO66: =SUM(PL66:QN66) -> 0 | RV66: =SUM(QQ66:RU66) -> 0 | RW66: =SUM(PJ66,QO66,RV66) -> 0
B67: TOTAL DESPESAS SÓCIOS - Paulo e Carol | D67: =SUM(D56:D59,D61:D66) -> 0 | E67: =SUM(E56:E59,E61:E66) -> 0 | F67: =SUM(F56:F59,F61:F66) -> 0 | G67: =SUM(G56:G59,G61:G66) -> 0 | H67: =SUM(H56:H59,H61:H66) -> 0 | I67: =SUM(I56:I59,I61:I66) -> 0 | J67: =SUM(J56:J59,J61:J66) -> 0 | K67: =SUM(K56:K59,K61:K66) -> 0 | ... AI67: =SUM(AI56:AI59,AI61:AI66) -> 0 | AK67: =SUM(AK56:AK59,AK61:AK66) -> 0 | AL67: =SUM(AL56:AL59,AL61:AL66) -> 0 | AM67: =SUM(AM56:AM59,AM61:AM66) -> 0 | AN67: =SUM(AN56:AN59,AN61:AN66) -> 0 | AO67: =SUM(AO56:AO59,AO61:AO66) -> 0 | AP67: =SUM(AP56:AP59,AP61:AP66) -> 0 | AQ67: =SUM(AQ56:AQ59,AQ61:AQ66) -> 0 | AR67: =SUM(AR56:AR59,AR61:AR66) -> 0 | ... BN67: =SUM(BN56:BN59,BN61:BN66) -> 0 | BP67: =SUM(BP56:BP59,BP61:BP66) -> 0 | BQ67: =SUM(BQ56:BQ59,BQ61:BQ66) -> 0 | BR67: =SUM(BR56:BR59,BR61:BR66) -> 0 | BS67: =SUM(BS56:BS59,BS61:BS66) -> 0 | BT67: =SUM(BT56:BT59,BT61:BT66) -> 0 | BU67: =SUM(BU56:BU59,BU61:BU66) -> 0 | BV67: =SUM(BV56:BV59,BV61:BV66) -> 0 | BW67: =SUM(BW56:BW59,BW61:BW66) -> 0 | ... CU67: =SUM(CU56:CU59,CU61:CU66) -> 0 | CW67: =SUM(CW56:CW59,CW61:CW66) -> 0 | CX67: =SUM(CX56:CX59,CX61:CX66) -> 0 | CY67: =SUM(CY56:CY59,CY61:CY66) -> 0 | CZ67: =SUM(CZ56:CZ59,CZ61:CZ66) -> 0 | DA67: =SUM(DA56:DA59,DA61:DA66) -> 0 | DB67: =SUM(DB56:DB59,DB61:DB66) -> 0 | DC67: =SUM(DC56:DC59,DC61:DC66) -> 0 | DD67: =SUM(DD56:DD59,DD61:DD66) -> 0 | ... EA67: =SUM(EA56:EA59,EA61:EA66) -> 0 | EC67: =SUM(EC56:EC59,EC61:EC66) -> 0 | ED67: =SUM(ED56:ED59,ED61:ED66) -> 0 | EE67: =SUM(EE56:EE59,EE61:EE66) -> 0 | EF67: =SUM(EF56:EF59,EF61:EF66) -> 0 | EG67: =SUM(EG56:EG59,EG61:EG66) -> 0 | EH67: =SUM(EH56:EH59,EH61:EH66) -> 0 | EI67: =SUM(EI56:EI59,EI61:EI66) -> 0 | EJ67: =SUM(EJ56:EJ59,EJ61:EJ66) -> 0 | ... FH67: =SUM(FH56:FH59,FH61:FH66) -> 0 | FJ67: =SUM(FJ56:FJ59,FJ61:FJ66) -> 0 | FK67: =SUM(FK56:FK59,FK61:FK66) -> 0 | FL67: =SUM(FL56:FL59,FL61:FL66) -> 0 | FM67: =SUM(FM56:FM59,FM61:FM66) -> 0 | FN67: =SUM(FN56:FN59,FN61:FN66) -> 0 | FO67: =SUM(FO56:FO59,FO61:FO66) -> 0 | FP67: =SUM(FP56:FP59,FP61:FP66) -> 0 | FQ67: =SUM(FQ56:FQ59,FQ61:FQ66) -> 0 | ... GN67: =SUM(GN56:GN59,GN61:GN66) -> 0 | GP67: =SUM(GP56:GP59,GP61:GP66) -> 0 | GQ67: =SUM(GQ56:GQ59,GQ61:GQ66) -> 0 | GR67: =SUM(GR56:GR59,GR61:GR66) -> 0 | GS67: =SUM(GS56:GS59,GS61:GS66) -> 0 | GT67: =SUM(GT56:GT59,GT61:GT66) -> 0 | GU67: =SUM(GU56:GU59,GU61:GU66) -> 0 | GV67: =SUM(GV56:GV59,GV61:GV66) -> 0 | GW67: =SUM(GW56:GW59,GW61:GW66) -> 0 | ... HU67: =SUM(HU56:HU59,HU61:HU66) -> 0 | HW67: =SUM(HW56:HW59,HW61:HW66) -> 0 | HX67: =SUM(HX56:HX59,HX61:HX66) -> 0 | HY67: =SUM(HY56:HY59,HY61:HY66) -> 0 | HZ67: =SUM(HZ56:HZ59,HZ61:HZ66) -> 0 | IA67: =SUM(IA56:IA59,IA61:IA66) -> 0 | IB67: =SUM(IB56:IB59,IB61:IB66) -> 0 | IC67: =SUM(IC56:IC59,IC61:IC66) -> 0 | ID67: =SUM(ID56:ID59,ID61:ID66) -> 0 | ... JB67: =SUM(JB56:JB59,JB61:JB66) -> 0 | JD67: =SUM(JD56:JD59,JD61:JD66) -> 0 | JE67: =SUM(JE56:JE59,JE61:JE66) -> 0 | JF67: =SUM(JF56:JF59,JF61:JF66) -> 0 | JG67: =SUM(JG56:JG59,JG61:JG66) -> 0 | JH67: =SUM(JH56:JH59,JH61:JH66) -> 0 | JI67: =SUM(JI56:JI59,JI61:JI66) -> 0 | JJ67: =SUM(JJ56:JJ59,JJ61:JJ66) -> 0 | JK67: =SUM(JK56:JK59,JK61:JK66) -> 0 | ... KH67: =SUM(KH56:KH59,KH61:KH66) -> 0 | KJ67: =SUM(KJ56:KJ59,KJ61:KJ66) -> 0 | KK67: =SUM(KK56:KK59,KK61:KK66) -> 0 | KL67: =SUM(KL56:KL59,KL61:KL66) -> 0 | KM67: =SUM(KM56:KM59,KM61:KM66) -> 0 | KN67: =SUM(KN56:KN59,KN61:KN66) -> 0 | KO67: =SUM(KO56:KO59,KO61:KO66) -> 0 | KP67: =SUM(KP56:KP59,KP61:KP66) -> 0 | KQ67: =SUM(KQ56:KQ59,KQ61:KQ66) -> 0 | ... LO67: =SUM(LO56:LO59,LO61:LO66) -> 0 | LQ67: =SUM(LQ56:LQ59,LQ61:LQ66) -> 0 | LR67: =SUM(LR56:LR59,LR61:LR66) -> 0 | LS67: =SUM(LS56:LS59,LS61:LS66) -> 0 | LT67: =SUM(LT56:LT59,LT61:LT66) -> 0 | LU67: =SUM(LU56:LU59,LU61:LU66) -> 0 | LV67: =SUM(LV56:LV59,LV61:LV66) -> 0 | LW67: =SUM(LW56:LW59,LW61:LW66) -> 0 | LX67: =SUM(LX56:LX59,LX61:LX66) -> 0 | ... MU67: =SUM(MU56:MU59,MU61:MU66) -> 0 | MW67: =SUM(MW56:MW59,MW61:MW66) -> 0 | MX67: =SUM(MX56:MX59,MX61:MX66) -> 0 | MY67: =SUM(MY56:MY59,MY61:MY66) -> 0 | MZ67: =SUM(MZ56:MZ59,MZ61:MZ66) -> 0 | NA67: =SUM(NA56:NA59,NA61:NA66) -> 0 | NB67: =SUM(NB56:NB59,NB61:NB66) -> 0 | NC67: =SUM(NC56:NC59,NC61:NC66) -> 0 | ND67: =SUM(ND56:ND59,ND61:ND66) -> 0 | ... OB67: =SUM(OB56:OB59,OB61:OB66) -> 0 | OC67: =SUM(AI67,BN67,CU67,EA67,FH67,GN67,HU67,JB67,KH67,LO67,MU67,OB67) -> 0 | OE67: =SUM(OE56:OE59,OE61:OE66) -> 0 | OF67: =SUM(OF56:OF59,OF61:OF66) -> 0 | OG67: =SUM(OG56:OG59,OG61:OG66) -> 0 | OH67: =SUM(OH56:OH59,OH61:OH66) -> 0 | OI67: =SUM(OI56:OI59,OI61:OI66) -> 0 | OJ67: =SUM(OJ56:OJ59,OJ61:OJ66) -> 0 | OK67: =SUM(OK56:OK59,OK61:OK66) -> 0 | OL67: =SUM(OL56:OL59,OL61:OL66) -> 0 | ... PJ67: =SUM(PJ56:PJ59,PJ61:PJ66) -> 0 | PL67: =SUM(PL56:PL59,PL61:PL66) -> 0 | PM67: =SUM(PM56:PM59,PM61:PM66) -> 0 | PN67: =SUM(PN56:PN59,PN61:PN66) -> 0 | PO67: =SUM(PO56:PO59,PO61:PO66) -> 0 | PP67: =SUM(PP56:PP59,PP61:PP66) -> 0 | PQ67: =SUM(PQ56:PQ59,PQ61:PQ66) -> 0 | PR67: =SUM(PR56:PR59,PR61:PR66) -> 0 | PS67: =SUM(PS56:PS59,PS61:PS66) -> 0 | ... QO67: =SUM(QO56:QO59,QO61:QO66) -> 0 | QQ67: =SUM(QQ56:QQ59,QQ61:QQ66) -> 0 | QR67: =SUM(QR56:QR59,QR61:QR66) -> 0 | QS67: =SUM(QS56:QS59,QS61:QS66) -> 0 | QT67: =SUM(QT56:QT59,QT61:QT66) -> 0 | QU67: =SUM(QU56:QU59,QU61:QU66) -> 0 | QV67: =SUM(QV56:QV59,QV61:QV66) -> 0 | QW67: =SUM(QW56:QW59,QW61:QW66) -> 0 | QX67: =SUM(QX56:QX59,QX61:QX66) -> 0 | ... RV67: =SUM(RV56:RV59,RV61:RV66) -> 0 | RW67: =SUM(PJ67,QO67,RV67) -> 0
A69: 1 | B69: DESPESAS DE INFRAESTRUTURA
B70: Água / Filtro | AI70: =SUM(D70:AH70) -> 0 | BN70: =SUM(AK70:BM70) -> 0 | CU70: =SUM(BP70:CT70) -> 0 | EA70: =SUM(CW70:DZ70) -> 0 | FH70: =SUM(EC70:FG70) -> 0 | GN70: =SUM(FJ70:GM70) -> 0 | HU70: =SUM(GP70:HT70) -> 0 | JB70: =SUM(HW70:JA70) -> 0 | KH70: =SUM(JD70:KG70) -> 0 | LO70: =SUM(KJ70:LN70) -> 0 | MU70: =SUM(LQ70:MT70) -> 0 | OB70: =SUM(MW70:OA70) -> 0 | OC70: =SUM(AI70,BN70,CU70,EA70,FH70,GN70,HU70,JB70,KH70,LO70,MU70,OB70) -> 0 | PJ70: =SUM(OE70:PI70) -> 0 | QO70: =SUM(PL70:QN70) -> 0 | RV70: =SUM(QQ70:RU70) -> 0 | RW70: =SUM(PJ70,QO70,RV70) -> 0
B71: Aluguel PE | AI71: =SUM(D71:AH71) -> 0 | BN71: =SUM(AK71:BM71) -> 0 | CU71: =SUM(BP71:CT71) -> 0 | EA71: =SUM(CW71:DZ71) -> 0 | FH71: =SUM(EC71:FG71) -> 0 | GN71: =SUM(FJ71:GM71) -> 0 | HU71: =SUM(GP71:HT71) -> 0 | JB71: =SUM(HW71:JA71) -> 0 | KH71: =SUM(JD71:KG71) -> 0 | LO71: =SUM(KJ71:LN71) -> 0 | MU71: =SUM(LQ71:MT71) -> 0 | OB71: =SUM(MW71:OA71) -> 0 | OC71: =SUM(AI71,BN71,CU71,EA71,FH71,GN71,HU71,JB71,KH71,LO71,MU71,OB71) -> 0 | PJ71: =SUM(OE71:PI71) -> 0 | QO71: =SUM(PL71:QN71) -> 0 | RV71: =SUM(QQ71:RU71) -> 0 | RW71: =SUM(PJ71,QO71,RV71) -> 0
B72: Aluguel PR | AI72: =SUM(D72:AH72) -> 0 | BN72: =SUM(AK72:BM72) -> 0 | CU72: =SUM(BP72:CT72) -> 0 | EA72: =SUM(CW72:DZ72) -> 0 | FH72: =SUM(EC72:FG72) -> 0 | GN72: =SUM(FJ72:GM72) -> 0 | HU72: =SUM(GP72:HT72) -> 0 | JB72: =SUM(HW72:JA72) -> 0 | KH72: =SUM(JD72:KG72) -> 0 | LO72: =SUM(KJ72:LN72) -> 0 | MU72: =SUM(LQ72:MT72) -> 0 | OB72: =SUM(MW72:OA72) -> 0 | OC72: =SUM(AI72,BN72,CU72,EA72,FH72,GN72,HU72,JB72,KH72,LO72,MU72,OB72) -> 0 | PJ72: =SUM(OE72:PI72) -> 0 | QO72: =SUM(PL72:QN72) -> 0 | RV72: =SUM(QQ72:RU72) -> 0 | RW72: =SUM(PJ72,QO72,RV72) -> 0
B73: Aluguel SP | AI73: =SUM(D73:AH73) -> 0 | BN73: =SUM(AK73:BM73) -> 0 | CU73: =SUM(BP73:CT73) -> 0 | EA73: =SUM(CW73:DZ73) -> 0 | FH73: =SUM(EC73:FG73) -> 0 | GN73: =SUM(FJ73:GM73) -> 0 | HU73: =SUM(GP73:HT73) -> 0 | JB73: =SUM(HW73:JA73) -> 0 | KH73: =SUM(JD73:KG73) -> 0 | LO73: =SUM(KJ73:LN73) -> 0 | MU73: =SUM(LQ73:MT73) -> 0 | OB73: =SUM(MW73:OA73) -> 0 | OC73: =SUM(AI73,BN73,CU73,EA73,FH73,GN73,HU73,JB73,KH73,LO73,MU73,OB73) -> 0 | PJ73: =SUM(OE73:PI73) -> 0 | QO73: =SUM(PL73:QN73) -> 0 | RV73: =SUM(QQ73:RU73) -> 0 | RW73: =SUM(PJ73,QO73,RV73) -> 0
B74: Aquisição de Equipamentos | AI74: =SUM(D74:AH74) -> 0 | BN74: =SUM(AK74:BM74) -> 0 | CU74: =SUM(BP74:CT74) -> 0 | EA74: =SUM(CW74:DZ74) -> 0 | FH74: =SUM(EC74:FG74) -> 0 | GN74: =SUM(FJ74:GM74) -> 0 | HU74: =SUM(GP74:HT74) -> 0 | JB74: =SUM(HW74:JA74) -> 0 | KH74: =SUM(JD74:KG74) -> 0 | LO74: =SUM(KJ74:LN74) -> 0 | MU74: =SUM(LQ74:MT74) -> 0 | OB74: =SUM(MW74:OA74) -> 0 | OC74: =SUM(AI74,BN74,CU74,EA74,FH74,GN74,HU74,JB74,KH74,LO74,MU74,OB74) -> 0 | PJ74: =SUM(OE74:PI74) -> 0 | QO74: =SUM(PL74:QN74) -> 0 | RV74: =SUM(QQ74:RU74) -> 0 | RW74: =SUM(PJ74,QO74,RV74) -> 0
B75: Aquisição de Móveis e Utensílios | AI75: =SUM(D75:AH75) -> 0 | BN75: =SUM(AK75:BM75) -> 0 | CU75: =SUM(BP75:CT75) -> 0 | EA75: =SUM(CW75:DZ75) -> 0 | FH75: =SUM(EC75:FG75) -> 0 | GN75: =SUM(FJ75:GM75) -> 0 | HU75: =SUM(GP75:HT75) -> 0 | JB75: =SUM(HW75:JA75) -> 0 | KH75: =SUM(JD75:KG75) -> 0 | LO75: =SUM(KJ75:LN75) -> 0 | MU75: =SUM(LQ75:MT75) -> 0 | OB75: =SUM(MW75:OA75) -> 0 | OC75: =SUM(AI75,BN75,CU75,EA75,FH75,GN75,HU75,JB75,KH75,LO75,MU75,OB75) -> 0 | PJ75: =SUM(OE75:PI75) -> 0 | QO75: =SUM(PL75:QN75) -> 0 | RV75: =SUM(QQ75:RU75) -> 0 | RW75: =SUM(PJ75,QO75,RV75) -> 0
B76: Condomínio | AI76: =SUM(D76:AH76) -> 0 | BN76: =SUM(AK76:BM76) -> 0 | CU76: =SUM(BP76:CT76) -> 0 | EA76: =SUM(CW76:DZ76) -> 0 | FH76: =SUM(EC76:FG76) -> 0 | GN76: =SUM(FJ76:GM76) -> 0 | HU76: =SUM(GP76:HT76) -> 0 | JB76: =SUM(HW76:JA76) -> 0 | KH76: =SUM(JD76:KG76) -> 0 | LO76: =SUM(KJ76:LN76) -> 0 | MU76: =SUM(LQ76:MT76) -> 0 | OB76: =SUM(MW76:OA76) -> 0 | OC76: =SUM(AI76,BN76,CU76,EA76,FH76,GN76,HU76,JB76,KH76,LO76,MU76,OB76) -> 0 | PJ76: =SUM(OE76:PI76) -> 0 | QO76: =SUM(PL76:QN76) -> 0 | RV76: =SUM(QQ76:RU76) -> 0 | RW76: =SUM(PJ76,QO76,RV76) -> 0
B77: Energia Elétrica - ENEL | AI77: =SUM(D77:AH77) -> 0 | BN77: =SUM(AK77:BM77) -> 0 | CU77: =SUM(BP77:CT77) -> 0 | EA77: =SUM(CW77:DZ77) -> 0 | FH77: =SUM(EC77:FG77) -> 0 | GN77: =SUM(FJ77:GM77) -> 0 | HU77: =SUM(GP77:HT77) -> 0 | JB77: =SUM(HW77:JA77) -> 0 | KH77: =SUM(JD77:KG77) -> 0 | LO77: =SUM(KJ77:LN77) -> 0 | MU77: =SUM(LQ77:MT77) -> 0 | OB77: =SUM(MW77:OA77) -> 0 | OC77: =SUM(AI77,BN77,CU77,EA77,FH77,GN77,HU77,JB77,KH77,LO77,MU77,OB77) -> 0 | PJ77: =SUM(OE77:PI77) -> 0 | QO77: =SUM(PL77:QN77) -> 0 | RV77: =SUM(QQ77:RU77) -> 0 | RW77: =SUM(PJ77,QO77,RV77) -> 0
B78: Internet | AI78: =SUM(D78:AH78) -> 0 | BN78: =SUM(AK78:BM78) -> 0 | CU78: =SUM(BP78:CT78) -> 0 | EA78: =SUM(CW78:DZ78) -> 0 | FH78: =SUM(EC78:FG78) -> 0 | GN78: =SUM(FJ78:GM78) -> 0 | HU78: =SUM(GP78:HT78) -> 0 | JB78: =SUM(HW78:JA78) -> 0 | KH78: =SUM(JD78:KG78) -> 0 | LO78: =SUM(KJ78:LN78) -> 0 | MU78: =SUM(LQ78:MT78) -> 0 | OB78: =SUM(MW78:OA78) -> 0 | OC78: =SUM(AI78,BN78,CU78,EA78,FH78,GN78,HU78,JB78,KH78,LO78,MU78,OB78) -> 0 | PJ78: =SUM(OE78:PI78) -> 0 | QO78: =SUM(PL78:QN78) -> 0 | RV78: =SUM(QQ78:RU78) -> 0 | RW78: =SUM(PJ78,QO78,RV78) -> 0
B79: IPTU | AI79: =SUM(D79:AH79) -> 0 | BN79: =SUM(AK79:BM79) -> 0 | CU79: =SUM(BP79:CT79) -> 0 | EA79: =SUM(CW79:DZ79) -> 0 | FH79: =SUM(EC79:FG79) -> 0 | GN79: =SUM(FJ79:GM79) -> 0 | HU79: =SUM(GP79:HT79) -> 0 | JB79: =SUM(HW79:JA79) -> 0 | KH79: =SUM(JD79:KG79) -> 0 | LO79: =SUM(KJ79:LN79) -> 0 | MU79: =SUM(LQ79:MT79) -> 0 | OB79: =SUM(MW79:OA79) -> 0 | OC79: =SUM(AI79,BN79,CU79,EA79,FH79,GN79,HU79,JB79,KH79,LO79,MU79,OB79) -> 0 | PJ79: =SUM(OE79:PI79) -> 0 | QO79: =SUM(PL79:QN79) -> 0 | RV79: =SUM(QQ79:RU79) -> 0 | RW79: =SUM(PJ79,QO79,RV79) -> 0
B80: Limpeza / Diarista | AI80: =SUM(D80:AH80) -> 0 | BN80: =SUM(AK80:BM80) -> 0 | CU80: =SUM(BP80:CT80) -> 0 | EA80: =SUM(CW80:DZ80) -> 0 | FH80: =SUM(EC80:FG80) -> 0 | GN80: =SUM(FJ80:GM80) -> 0 | HU80: =SUM(GP80:HT80) -> 0 | JB80: =SUM(HW80:JA80) -> 0 | KH80: =SUM(JD80:KG80) -> 0 | LO80: =SUM(KJ80:LN80) -> 0 | MU80: =SUM(LQ80:MT80) -> 0 | OB80: =SUM(MW80:OA80) -> 0 | OC80: =SUM(AI80,BN80,CU80,EA80,FH80,GN80,HU80,JB80,KH80,LO80,MU80,OB80) -> 0 | PJ80: =SUM(OE80:PI80) -> 0 | QO80: =SUM(PL80:QN80) -> 0 | RV80: =SUM(QQ80:RU80) -> 0 | RW80: =SUM(PJ80,QO80,RV80) -> 0
B81: Manutenção de Equipamentos | AI81: =SUM(D81:AH81) -> 0 | BN81: =SUM(AK81:BM81) -> 0 | CU81: =SUM(BP81:CT81) -> 0 | EA81: =SUM(CW81:DZ81) -> 0 | FH81: =SUM(EC81:FG81) -> 0 | GN81: =SUM(FJ81:GM81) -> 0 | HU81: =SUM(GP81:HT81) -> 0 | JB81: =SUM(HW81:JA81) -> 0 | KH81: =SUM(JD81:KG81) -> 0 | LO81: =SUM(KJ81:LN81) -> 0 | MU81: =SUM(LQ81:MT81) -> 0 | OB81: =SUM(MW81:OA81) -> 0 | OC81: =SUM(AI81,BN81,CU81,EA81,FH81,GN81,HU81,JB81,KH81,LO81,MU81,OB81) -> 0 | PJ81: =SUM(OE81:PI81) -> 0 | QO81: =SUM(PL81:QN81) -> 0 | RV81: =SUM(QQ81:RU81) -> 0 | RW81: =SUM(PJ81,QO81,RV81) -> 0
... B84: Telefone - Celular | AI84: =SUM(D84:AH84) -> 0 | BN84: =SUM(AK84:BM84) -> 0 | CU84: =SUM(BP84:CT84) -> 0 | EA84: =SUM(CW84:DZ84) -> 0 | FH84: =SUM(EC84:FG84) -> 0 | GN84: =SUM(FJ84:GM84) -> 0 | HU84: =SUM(GP84:HT84) -> 0 | JB84: =SUM(HW84:JA84) -> 0 | KH84: =SUM(JD84:KG84) -> 0 | LO84: =SUM(KJ84:LN84) -> 0 | MU84: =SUM(LQ84:MT84) -> 0 | OB84: =SUM(MW84:OA84) -> 0 | OC84: =SUM(AI84,BN84,CU84,EA84,FH84,GN84,HU84,JB84,KH84,LO84,MU84,OB84) -> 0 | PJ84: =SUM(OE84:PI84) -> 0 | QO84: =SUM(PL84:QN84) -> 0 | RV84: =SUM(QQ84:RU84) -> 0 | RW84: =SUM(PJ84,QO84,RV84) -> 0
B85: TOTAL DESPESAS DE INFRAESTRUTURA | D85: =SUM(D70:D84) -> 0 | E85: =SUM(E70:E84) -> 0 | F85: =SUM(F70:F84) -> 0 | G85: =SUM(G70:G84) -> 0 | H85: =SUM(H70:H84) -> 0 | I85: =SUM(I70:I84) -> 0 | J85: =SUM(J70:J84) -> 0 | K85: =SUM(K70:K84) -> 0 | ... AI85: =SUM(AI70:AI84) -> 0 | AK85: =SUM(AK70:AK84) -> 0 | AL85: =SUM(AL70:AL84) -> 0 | AM85: =SUM(AM70:AM84) -> 0 | AN85: =SUM(AN70:AN84) -> 0 | AO85: =SUM(AO70:AO84) -> 0 | AP85: =SUM(AP70:AP84) -> 0 | AQ85: =SUM(AQ70:AQ84) -> 0 | AR85: =SUM(AR70:AR84) -> 0 | ... BN85: =SUM(BN70:BN84) -> 0 | BP85: =SUM(BP70:BP84) -> 0 | BQ85: =SUM(BQ70:BQ84) -> 0 | BR85: =SUM(BR70:BR84) -> 0 | BS85: =SUM(BS70:BS84) -> 0 | BT85: =SUM(BT70:BT84) -> 0 | BU85: =SUM(BU70:BU84) -> 0 | BV85: =SUM(BV70:BV84) -> 0 | BW85: =SUM(BW70:BW84) -> 0 | ... CU85: =SUM(CU70:CU84) -> 0 | CW85: =SUM(CW70:CW84) -> 0 | CX85: =SUM(CX70:CX84) -> 0 | CY85: =SUM(CY70:CY84) -> 0 | CZ85: =SUM(CZ70:CZ84) -> 0 | DA85: =SUM(DA70:DA84) -> 0 | DB85: =SUM(DB70:DB84) -> 0 | DC85: =SUM(DC70:DC84) -> 0 | DD85: =SUM(DD70:DD84) -> 0 | ... EA85: =SUM(EA70:EA84) -> 0 | EC85: =SUM(EC70:EC84) -> 0 | ED85: =SUM(ED70:ED84) -> 0 | EE85: =SUM(EE70:EE84) -> 0 | EF85: =SUM(EF70:EF84) -> 0 | EG85: =SUM(EG70:EG84) -> 0 | EH85: =SUM(EH70:EH84) -> 0 | EI85: =SUM(EI70:EI84) -> 0 | EJ85: =SUM(EJ70:EJ84) -> 0 | ... FH85: =SUM(FH70:FH84) -> 0 | FJ85: =SUM(FJ70:FJ84) -> 0 | FK85: =SUM(FK70:FK84) -> 0 | FL85: =SUM(FL70:FL84) -> 0 | FM85: =SUM(FM70:FM84) -> 0 | FN85: =SUM(FN70:FN84) -> 0 | FO85: =SUM(FO70:FO84) -> 0 | FP85: =SUM(FP70:FP84) -> 0 | FQ85: =SUM(FQ70:FQ84) -> 0 | ... GN85: =SUM(GN70:GN84) -> 0 | GP85: =SUM(GP70:GP84) -> 0 | GQ85: =SUM(GQ70:GQ84) -> 0 | GR85: =SUM(GR70:GR84) -> 0 | GS85: =SUM(GS70:GS84) -> 0 | GT85: =SUM(GT70:GT84) -> 0 | GU85: =SUM(GU70:GU84) -> 0 | GV85: =SUM(GV70:GV84) -> 0 | GW85: =SUM(GW70:GW84) -> 0 | ... HU85: =SUM(HU70:HU84) -> 0 | HW85: =SUM(HW70:HW84) -> 0 | HX85: =SUM(HX70:HX84) -> 0 | HY85: =SUM(HY70:HY84) -> 0 | HZ85: =SUM(HZ70:HZ84) -> 0 | IA85: =SUM(IA70:IA84) -> 0 | IB85: =SUM(IB70:IB84) -> 0 | IC85: =SUM(IC70:IC84) -> 0 | ID85: =SUM(ID70:ID84) -> 0 | ... JB85: =SUM(JB70:JB84) -> 0 | JD85: =SUM(JD70:JD84) -> 0 | JE85: =SUM(JE70:JE84) -> 0 | JF85: =SUM(JF70:JF84) -> 0 | JG85: =SUM(JG70:JG84) -> 0 | JH85: =SUM(JH70:JH84) -> 0 | JI85: =SUM(JI70:JI84) -> 0 | JJ85: =SUM(JJ70:JJ84) -> 0 | JK85: =SUM(JK70:JK84) -> 0 | ... KH85: =SUM(KH70:KH84) -> 0 | KJ85: =SUM(KJ70:KJ84) -> 0 | KK85: =SUM(KK70:KK84) -> 0 | KL85: =SUM(KL70:KL84) -> 0 | KM85: =SUM(KM70:KM84) -> 0 | KN85: =SUM(KN70:KN84) -> 0 | KO85: =SUM(KO70:KO84) -> 0 | KP85: =SUM(KP70:KP84) -> 0 | KQ85: =SUM(KQ70:KQ84) -> 0 | ... LO85: =SUM(LO70:LO84) -> 0 | LQ85: =SUM(LQ70:LQ84) -> 0 | LR85: =SUM(LR70:LR84) -> 0 | LS85: =SUM(LS70:LS84) -> 0 | LT85: =SUM(LT70:LT84) -> 0 | LU85: =SUM(LU70:LU84) -> 0 | LV85: =SUM(LV70:LV84) -> 0 | LW85: =SUM(LW70:LW84) -> 0 | LX85: =SUM(LX70:LX84) -> 0 | ... MU85: =SUM(MU70:MU84) -> 0 | MW85: =SUM(MW70:MW84) -> 0 | MX85: =SUM(MX70:MX84) -> 0 | MY85: =SUM(MY70:MY84) -> 0 | MZ85: =SUM(MZ70:MZ84) -> 0 | NA85: =SUM(NA70:NA84) -> 0 | NB85: =SUM(NB70:NB84) -> 0 | NC85: =SUM(NC70:NC84) -> 0 | ND85: =SUM(ND70:ND84) -> 0 | ... OB85: =SUM(OB70:OB84) -> 0 | OC85: =SUM(AI85,BN85,CU85,EA85,FH85,GN85,HU85,JB85,KH85,LO85,MU85,OB85) -> 0 | OE85: =SUM(OE70:OE84) -> 0 | OF85: =SUM(OF70:OF84) -> 0 | OG85: =SUM(OG70:OG84) -> 0 | OH85: =SUM(OH70:OH84) -> 0 | OI85: =SUM(OI70:OI84) -> 0 | OJ85: =SUM(OJ70:OJ84) -> 0 | OK85: =SUM(OK70:OK84) -> 0 | OL85: =SUM(OL70:OL84) -> 0 | ... PJ85: =SUM(PJ70:PJ84) -> 0 | PL85: =SUM(PL70:PL84) -> 0 | PM85: =SUM(PM70:PM84) -> 0 | PN85: =SUM(PN70:PN84) -> 0 | PO85: =SUM(PO70:PO84) -> 0 | PP85: =SUM(PP70:PP84) -> 0 | PQ85: =SUM(PQ70:PQ84) -> 0 | PR85: =SUM(PR70:PR84) -> 0 | PS85: =SUM(PS70:PS84) -> 0 | ... QO85: =SUM(QO70:QO84) -> 0 | QQ85: =SUM(QQ70:QQ84) -> 0 | QR85: =SUM(QR70:QR84) -> 0 | QS85: =SUM(QS70:QS84) -> 0 | QT85: =SUM(QT70:QT84) -> 0 | QU85: =SUM(QU70:QU84) -> 0 | QV85: =SUM(QV70:QV84) -> 0 | QW85: =SUM(QW70:QW84) -> 0 | QX85: =SUM(QX70:QX84) -> 0 | ... RV85: =SUM(RV70:RV84) -> 0 | RW85: =SUM(PJ85,QO85,RV85) -> 0
A87: 1 | B87: DESPESAS DE SOFTWARE
B88: Licenças de Software | AI88: =SUM(D88:AH88) -> 0 | BN88: =SUM(AK88:BM88) -> 0 | CU88: =SUM(BP88:CT88) -> 0 | EA88: =SUM(CW88:DZ88) -> 0 | FH88: =SUM(EC88:FG88) -> 0 | GN88: =SUM(FJ88:GM88) -> 0 | HU88: =SUM(GP88:HT88) -> 0 | JB88: =SUM(HW88:JA88) -> 0 | KH88: =SUM(JD88:KG88) -> 0 | LO88: =SUM(KJ88:LN88) -> 0 | MU88: =SUM(LQ88:MT88) -> 0 | OB88: =SUM(MW88:OA88) -> 0 | OC88: =SUM(AI88,BN88,CU88,EA88,FH88,GN88,HU88,JB88,KH88,LO88,MU88,OB88) -> 0 | PJ88: =SUM(OE88:PI88) -> 0 | QO88: =SUM(PL88:QN88) -> 0 | RV88: =SUM(QQ88:RU88) -> 0 | RW88: =SUM(PJ88,QO88,RV88) -> 0
B89: Sistema - Publi | AG89: 287.25 | AI89: =SUM(D89:AH89) -> 287.25 | BK89: 287.25 | BN89: =SUM(AK89:BM89) -> 287.25 | CT89: 287.25 | CU89: =SUM(BP89:CT89) -> 287.25 | DZ89: 287.25 | EA89: =SUM(CW89:DZ89) -> 287.25 | FE89: 287.25 | FH89: =SUM(EC89:FG89) -> 287.25 | GM89: 287.25 | GN89: =SUM(FJ89:GM89) -> 287.25 | HS89: 287.25 | HU89: =SUM(GP89:HT89) -> 287.25 | IZ89: 287.25 | JB89: =SUM(HW89:JA89) -> 287.25 | KG89: 287.25 | KH89: =SUM(JD89:KG89) -> 287.25 | LM89: 287.25 | LO89: =SUM(KJ89:LN89) -> 287.25 | MT89: 287.25 | MU89: =SUM(LQ89:MT89) -> 287.25 | NZ89: 287.25 | OB89: =SUM(MW89:OA89) -> 287.25 | OC89: =SUM(AI89,BN89,CU89,EA89,FH89,GN89,HU89,JB89,KH89,LO89,MU89,OB89) -> 3447 | PJ89: =SUM(OE89:PI89) -> 0 | QO89: =SUM(PL89:QN89) -> 0 | RV89: =SUM(QQ89:RU89) -> 0 | RW89: =SUM(PJ89,QO89,RV89) -> 0
B90: Sistema - Tabela JOVE | AI90: =SUM(D90:AH90) -> 0 | BN90: =SUM(AK90:BM90) -> 0 | CU90: =SUM(BP90:CT90) -> 0 | EA90: =SUM(CW90:DZ90) -> 0 | FH90: =SUM(EC90:FG90) -> 0 | GN90: =SUM(FJ90:GM90) -> 0 | HU90: =SUM(GP90:HT90) -> 0 | JB90: =SUM(HW90:JA90) -> 0 | KH90: =SUM(JD90:KG90) -> 0 | LO90: =SUM(KJ90:LN90) -> 0 | MU90: =SUM(LQ90:MT90) -> 0 | OB90: =SUM(MW90:OA90) -> 0 | OC90: =SUM(AI90,BN90,CU90,EA90,FH90,GN90,HU90,JB90,KH90,LO90,MU90,OB90) -> 0 | PJ90: =SUM(OE90:PI90) -> 0 | QO90: =SUM(PL90:QN90) -> 0 | RV90: =SUM(QQ90:RU90) -> 0 | RW90: =SUM(PJ90,QO90,RV90) -> 0
B91: TOTAL DESPESAS SOFTWARE | D91: =SUM(D88:D90) -> 0 | E91: =SUM(E88:E90) -> 0 | F91: =SUM(F88:F90) -> 0 | G91: =SUM(G88:G90) -> 0 | H91: =SUM(H88:H90) -> 0 | I91: =SUM(I88:I90) -> 0 | J91: =SUM(J88:J90) -> 0 | K91: =SUM(K88:K90) -> 0 | ... AI91: =SUM(AI88:AI90) -> 287.25 | AK91: =SUM(AK88:AK90) -> 0 | AL91: =SUM(AL88:AL90) -> 0 | AM91: =SUM(AM88:AM90) -> 0 | AN91: =SUM(AN88:AN90) -> 0 | AO91: =SUM(AO88:AO90) -> 0 | AP91: =SUM(AP88:AP90) -> 0 | AQ91: =SUM(AQ88:AQ90) -> 0 | AR91: =SUM(AR88:AR90) -> 0 | ... BN91: =SUM(BN88:BN90) -> 287.25 | BP91: =SUM(BP88:BP90) -> 0 | BQ91: =SUM(BQ88:BQ90) -> 0 | BR91: =SUM(BR88:BR90) -> 0 | BS91: =SUM(BS88:BS90) -> 0 | BT91: =SUM(BT88:BT90) -> 0 | BU91: =SUM(BU88:BU90) -> 0 | BV91: =SUM(BV88:BV90) -> 0 | BW91: =SUM(BW88:BW90) -> 0 | ... CU91: =SUM(CU88:CU90) -> 287.25 | CW91: =SUM(CW88:CW90) -> 0 | CX91: =SUM(CX88:CX90) -> 0 | CY91: =SUM(CY88:CY90) -> 0 | CZ91: =SUM(CZ88:CZ90) -> 0 | DA91: =SUM(DA88:DA90) -> 0 | DB91: =SUM(DB88:DB90) -> 0 | DC91: =SUM(DC88:DC90) -> 0 | DD91: =SUM(DD88:DD90) -> 0 | ... EA91: =SUM(EA88:EA90) -> 287.25 | EC91: =SUM(EC88:EC90) -> 0 | ED91: =SUM(ED88:ED90) -> 0 | EE91: =SUM(EE88:EE90) -> 0 | EF91: =SUM(EF88:EF90) -> 0 | EG91: =SUM(EG88:EG90) -> 0 | EH91: =SUM(EH88:EH90) -> 0 | EI91: =SUM(EI88:EI90) -> 0 | EJ91: =SUM(EJ88:EJ90) -> 0 | ... FH91: =SUM(FH88:FH90) -> 287.25 | FJ91: =SUM(FJ88:FJ90) -> 0 | FK91: =SUM(FK88:FK90) -> 0 | FL91: =SUM(FL88:FL90) -> 0 | FM91: =SUM(FM88:FM90) -> 0 | FN91: =SUM(FN88:FN90) -> 0 | FO91: =SUM(FO88:FO90) -> 0 | FP91: =SUM(FP88:FP90) -> 0 | FQ91: =SUM(FQ88:FQ90) -> 0 | ... GN91: =SUM(GN88:GN90) -> 287.25 | GP91: =SUM(GP88:GP90) -> 0 | GQ91: =SUM(GQ88:GQ90) -> 0 | GR91: =SUM(GR88:GR90) -> 0 | GS91: =SUM(GS88:GS90) -> 0 | GT91: =SUM(GT88:GT90) -> 0 | GU91: =SUM(GU88:GU90) -> 0 | GV91: =SUM(GV88:GV90) -> 0 | GW91: =SUM(GW88:GW90) -> 0 | ... HU91: =SUM(HU88:HU90) -> 287.25 | HW91: =SUM(HW88:HW90) -> 0 | HX91: =SUM(HX88:HX90) -> 0 | HY91: =SUM(HY88:HY90) -> 0 | HZ91: =SUM(HZ88:HZ90) -> 0 | IA91: =SUM(IA88:IA90) -> 0 | IB91: =SUM(IB88:IB90) -> 0 | IC91: =SUM(IC88:IC90) -> 0 | ID91: =SUM(ID88:ID90) -> 0 | ... JB91: =SUM(JB88:JB90) -> 287.25 | JD91: =SUM(JD88:JD90) -> 0 | JE91: =SUM(JE88:JE90) -> 0 | JF91: =SUM(JF88:JF90) -> 0 | JG91: =SUM(JG88:JG90) -> 0 | JH91: =SUM(JH88:JH90) -> 0 | JI91: =SUM(JI88:JI90) -> 0 | JJ91: =SUM(JJ88:JJ90) -> 0 | JK91: =SUM(JK88:JK90) -> 0 | ... KH91: =SUM(KH88:KH90) -> 287.25 | KJ91: =SUM(KJ88:KJ90) -> 0 | KK91: =SUM(KK88:KK90) -> 0 | KL91: =SUM(KL88:KL90) -> 0 | KM91: =SUM(KM88:KM90) -> 0 | KN91: =SUM(KN88:KN90) -> 0 | KO91: =SUM(KO88:KO90) -> 0 | KP91: =SUM(KP88:KP90) -> 0 | KQ91: =SUM(KQ88:KQ90) -> 0 | ... LO91: =SUM(LO88:LO90) -> 287.25 | LQ91: =SUM(LQ88:LQ90) -> 0 | LR91: =SUM(LR88:LR90) -> 0 | LS91: =SUM(LS88:LS90) -> 0 | LT91: =SUM(LT88:LT90) -> 0 | LU91: =SUM(LU88:LU90) -> 0 | LV91: =SUM(LV88:LV90) -> 0 | LW91: =SUM(LW88:LW90) -> 0 | LX91: =SUM(LX88:LX90) -> 0 | ... MU91: =SUM(MU88:MU90) -> 287.25 | MW91: =SUM(MW88:MW90) -> 0 | MX91: =SUM(MX88:MX90) -> 0 | MY91: =SUM(MY88:MY90) -> 0 | MZ91: =SUM(MZ88:MZ90) -> 0 | NA91: =SUM(NA88:NA90) -> 0 | NB91: =SUM(NB88:NB90) -> 0 | NC91: =SUM(NC88:NC90) -> 0 | ND91: =SUM(ND88:ND90) -> 0 | ... OB91: =SUM(OB88:OB90) -> 287.25 | OC91: =SUM(AI91,BN91,CU91,EA91,FH91,GN91,HU91,JB91,KH91,LO91,MU91,OB91) -> 3447 | OE91: =SUM(OE88:OE90) -> 0 | OF91: =SUM(OF88:OF90) -> 0 | OG91: =SUM(OG88:OG90) -> 0 | OH91: =SUM(OH88:OH90) -> 0 | OI91: =SUM(OI88:OI90) -> 0 | OJ91: =SUM(OJ88:OJ90) -> 0 | OK91: =SUM(OK88:OK90) -> 0 | OL91: =SUM(OL88:OL90) -> 0 | ... PJ91: =SUM(PJ88:PJ90) -> 0 | PL91: =SUM(PL88:PL90) -> 0 | PM91: =SUM(PM88:PM90) -> 0 | PN91: =SUM(PN88:PN90) -> 0 | PO91: =SUM(PO88:PO90) -> 0 | PP91: =SUM(PP88:PP90) -> 0 | PQ91: =SUM(PQ88:PQ90) -> 0 | PR91: =SUM(PR88:PR90) -> 0 | PS91: =SUM(PS88:PS90) -> 0 | ... QO91: =SUM(QO88:QO90) -> 0 | QQ91: =SUM(QQ88:QQ90) -> 0 | QR91: =SUM(QR88:QR90) -> 0 | QS91: =SUM(QS88:QS90) -> 0 | QT91: =SUM(QT88:QT90) -> 0 | QU91: =SUM(QU88:QU90) -> 0 | QV91: =SUM(QV88:QV90) -> 0 | QW91: =SUM(QW88:QW90) -> 0 | QX91: =SUM(QX88:QX90) -> 0 | ... RV91: =SUM(RV88:RV90) -> 0 | RW91: =SUM(PJ91,QO91,RV91) -> 0
A93: 1 | B93: DESPESAS COM AUTOMÓVEL
B94: Financiamento | AI94: =SUM(D94:AH94) -> 0 | BN94: =SUM(AK94:BM94) -> 0 | CU94: =SUM(BP94:CT94) -> 0 | EA94: =SUM(CW94:DZ94) -> 0 | FH94: =SUM(EC94:FG94) -> 0 | GN94: =SUM(FJ94:GM94) -> 0 | HU94: =SUM(GP94:HT94) -> 0 | JB94: =SUM(HW94:JA94) -> 0 | KH94: =SUM(JD94:KG94) -> 0 | LO94: =SUM(KJ94:LN94) -> 0 | MU94: =SUM(LQ94:MT94) -> 0 | OB94: =SUM(MW94:OA94) -> 0 | OC94: =SUM(AI94,BN94,CU94,EA94,FH94,GN94,HU94,JB94,KH94,LO94,MU94,OB94) -> 0 | PJ94: =SUM(OE94:PI94) -> 0 | QO94: =SUM(PL94:QN94) -> 0 | RV94: =SUM(QQ94:RU94) -> 0 | RW94: =SUM(PJ94,QO94,RV94) -> 0
B95: IPVA | AI95: =SUM(D95:AH95) -> 0 | BN95: =SUM(AK95:BM95) -> 0 | CU95: =SUM(BP95:CT95) -> 0 | EA95: =SUM(CW95:DZ95) -> 0 | FH95: =SUM(EC95:FG95) -> 0 | GN95: =SUM(FJ95:GM95) -> 0 | HU95: =SUM(GP95:HT95) -> 0 | JB95: =SUM(HW95:JA95) -> 0 | KH95: =SUM(JD95:KG95) -> 0 | LO95: =SUM(KJ95:LN95) -> 0 | MU95: =SUM(LQ95:MT95) -> 0 | OB95: =SUM(MW95:OA95) -> 0 | OC95: =SUM(AI95,BN95,CU95,EA95,FH95,GN95,HU95,JB95,KH95,LO95,MU95,OB95) -> 0 | PJ95: =SUM(OE95:PI95) -> 0 | QO95: =SUM(PL95:QN95) -> 0 | RV95: =SUM(QQ95:RU95) -> 0 | RW95: =SUM(PJ95,QO95,RV95) -> 0
B96: Licenciamento | AI96: =SUM(D96:AH96) -> 0 | BN96: =SUM(AK96:BM96) -> 0 | CU96: =SUM(BP96:CT96) -> 0 | EA96: =SUM(CW96:DZ96) -> 0 | FH96: =SUM(EC96:FG96) -> 0 | GN96: =SUM(FJ96:GM96) -> 0 | HU96: =SUM(GP96:HT96) -> 0 | JB96: =SUM(HW96:JA96) -> 0 | KH96: =SUM(JD96:KG96) -> 0 | LO96: =SUM(KJ96:LN96) -> 0 | MU96: =SUM(LQ96:MT96) -> 0 | OB96: =SUM(MW96:OA96) -> 0 | OC96: =SUM(AI96,BN96,CU96,EA96,FH96,GN96,HU96,JB96,KH96,LO96,MU96,OB96) -> 0 | PJ96: =SUM(OE96:PI96) -> 0 | QO96: =SUM(PL96:QN96) -> 0 | RV96: =SUM(QQ96:RU96) -> 0 | RW96: =SUM(PJ96,QO96,RV96) -> 0
B97: Manutenção | AI97: =SUM(D97:AH97) -> 0 | BN97: =SUM(AK97:BM97) -> 0 | CU97: =SUM(BP97:CT97) -> 0 | EA97: =SUM(CW97:DZ97) -> 0 | FH97: =SUM(EC97:FG97) -> 0 | GN97: =SUM(FJ97:GM97) -> 0 | HU97: =SUM(GP97:HT97) -> 0 | JB97: =SUM(HW97:JA97) -> 0 | KH97: =SUM(JD97:KG97) -> 0 | LO97: =SUM(KJ97:LN97) -> 0 | MU97: =SUM(LQ97:MT97) -> 0 | OB97: =SUM(MW97:OA97) -> 0 | OC97: =SUM(AI97,BN97,CU97,EA97,FH97,GN97,HU97,JB97,KH97,LO97,MU97,OB97) -> 0 | PJ97: =SUM(OE97:PI97) -> 0 | QO97: =SUM(PL97:QN97) -> 0 | RV97: =SUM(QQ97:RU97) -> 0 | RW97: =SUM(PJ97,QO97,RV97) -> 0
B98: Multa | AI98: =SUM(D98:AH98) -> 0 | BN98: =SUM(AK98:BM98) -> 0 | CU98: =SUM(BP98:CT98) -> 0 | EA98: =SUM(CW98:DZ98) -> 0 | FH98: =SUM(EC98:FG98) -> 0 | GN98: =SUM(FJ98:GM98) -> 0 | HU98: =SUM(GP98:HT98) -> 0 | JB98: =SUM(HW98:JA98) -> 0 | KH98: =SUM(JD98:KG98) -> 0 | LO98: =SUM(KJ98:LN98) -> 0 | MU98: =SUM(LQ98:MT98) -> 0 | OB98: =SUM(MW98:OA98) -> 0 | OC98: =SUM(AI98,BN98,CU98,EA98,FH98,GN98,HU98,JB98,KH98,LO98,MU98,OB98) -> 0 | PJ98: =SUM(OE98:PI98) -> 0 | QO98: =SUM(PL98:QN98) -> 0 | RV98: =SUM(QQ98:RU98) -> 0 | RW98: =SUM(PJ98,QO98,RV98) -> 0
B99: Seguro Veículo | AI99: =SUM(D99:AH99) -> 0 | BN99: =SUM(AK99:BM99) -> 0 | CU99: =SUM(BP99:CT99) -> 0 | EA99: =SUM(CW99:DZ99) -> 0 | FH99: =SUM(EC99:FG99) -> 0 | GN99: =SUM(FJ99:GM99) -> 0 | HU99: =SUM(GP99:HT99) -> 0 | JB99: =SUM(HW99:JA99) -> 0 | KH99: =SUM(JD99:KG99) -> 0 | LO99: =SUM(KJ99:LN99) -> 0 | MU99: =SUM(LQ99:MT99) -> 0 | OB99: =SUM(MW99:OA99) -> 0 | OC99: =SUM(AI99,BN99,CU99,EA99,FH99,GN99,HU99,JB99,KH99,LO99,MU99,OB99) -> 0 | PJ99: =SUM(OE99:PI99) -> 0 | QO99: =SUM(PL99:QN99) -> 0 | RV99: =SUM(QQ99:RU99) -> 0 | RW99: =SUM(PJ99,QO99,RV99) -> 0
B100: Despachante | AI100: =SUM(D100:AH100) -> 0 | BN100: =SUM(AK100:BM100) -> 0 | CU100: =SUM(BP100:CT100) -> 0 | EA100: =SUM(CW100:DZ100) -> 0 | FH100: =SUM(EC100:FG100) -> 0 | GN100: =SUM(FJ100:GM100) -> 0 | HU100: =SUM(GP100:HT100) -> 0 | JB100: =SUM(HW100:JA100) -> 0 | KH100: =SUM(JD100:KG100) -> 0 | LO100: =SUM(KJ100:LN100) -> 0 | MU100: =SUM(LQ100:MT100) -> 0 | OB100: =SUM(MW100:OA100) -> 0 | OC100: =SUM(AI100,BN100,CU100,EA100,FH100,GN100,HU100,JB100,KH100,LO100,MU100,OB100) -> 0 | PJ100: =SUM(OE100:PI100) -> 0 | QO100: =SUM(PL100:QN100) -> 0 | RV100: =SUM(QQ100:RU100) -> 0 | RW100: =SUM(PJ100,QO100,RV100) -> 0
B101: TOTAL DESPESAS COM AUTOMÓVEL | D101: =SUM(D94:D100) -> 0 | E101: =SUM(E94:E100) -> 0 | F101: =SUM(F94:F100) -> 0 | G101: =SUM(G94:G100) -> 0 | H101: =SUM(H94:H100) -> 0 | I101: =SUM(I94:I100) -> 0 | J101: =SUM(J94:J100) -> 0 | K101: =SUM(K94:K100) -> 0 | ... AI101: =SUM(AI94:AI100) -> 0 | AK101: =SUM(AK94:AK100) -> 0 | AL101: =SUM(AL94:AL100) -> 0 | AM101: =SUM(AM94:AM100) -> 0 | AN101: =SUM(AN94:AN100) -> 0 | AO101: =SUM(AO94:AO100) -> 0 | AP101: =SUM(AP94:AP100) -> 0 | AQ101: =SUM(AQ94:AQ100) -> 0 | AR101: =SUM(AR94:AR100) -> 0 | ... BN101: =SUM(BN94:BN100) -> 0 | BP101: =SUM(BP94:BP100) -> 0 | BQ101: =SUM(BQ94:BQ100) -> 0 | BR101: =SUM(BR94:BR100) -> 0 | BS101: =SUM(BS94:BS100) -> 0 | BT101: =SUM(BT94:BT100) -> 0 | BU101: =SUM(BU94:BU100) -> 0 | BV101: =SUM(BV94:BV100) -> 0 | BW101: =SUM(BW94:BW100) -> 0 | ... CU101: =SUM(CU94:CU100) -> 0 | CW101: =SUM(CW94:CW100) -> 0 | CX101: =SUM(CX94:CX100) -> 0 | CY101: =SUM(CY94:CY100) -> 0 | CZ101: =SUM(CZ94:CZ100) -> 0 | DA101: =SUM(DA94:DA100) -> 0 | DB101: =SUM(DB94:DB100) -> 0 | DC101: =SUM(DC94:DC100) -> 0 | DD101: =SUM(DD94:DD100) -> 0 | ... EA101: =SUM(EA94:EA100) -> 0 | EC101: =SUM(EC94:EC100) -> 0 | ED101: =SUM(ED94:ED100) -> 0 | EE101: =SUM(EE94:EE100) -> 0 | EF101: =SUM(EF94:EF100) -> 0 | EG101: =SUM(EG94:EG100) -> 0 | EH101: =SUM(EH94:EH100) -> 0 | EI101: =SUM(EI94:EI100) -> 0 | EJ101: =SUM(EJ94:EJ100) -> 0 | ... FH101: =SUM(FH94:FH100) -> 0 | FJ101: =SUM(FJ94:FJ100) -> 0 | FK101: =SUM(FK94:FK100) -> 0 | FL101: =SUM(FL94:FL100) -> 0 | FM101: =SUM(FM94:FM100) -> 0 | FN101: =SUM(FN94:FN100) -> 0 | FO101: =SUM(FO94:FO100) -> 0 | FP101: =SUM(FP94:FP100) -> 0 | FQ101: =SUM(FQ94:FQ100) -> 0 | ... GN101: =SUM(GN94:GN100) -> 0 | GP101: =SUM(GP94:GP100) -> 0 | GQ101: =SUM(GQ94:GQ100) -> 0 | GR101: =SUM(GR94:GR100) -> 0 | GS101: =SUM(GS94:GS100) -> 0 | GT101: =SUM(GT94:GT100) -> 0 | GU101: =SUM(GU94:GU100) -> 0 | GV101: =SUM(GV94:GV100) -> 0 | GW101: =SUM(GW94:GW100) -> 0 | ... HU101: =SUM(HU94:HU100) -> 0 | HW101: =SUM(HW94:HW100) -> 0 | HX101: =SUM(HX94:HX100) -> 0 | HY101: =SUM(HY94:HY100) -> 0 | HZ101: =SUM(HZ94:HZ100) -> 0 | IA101: =SUM(IA94:IA100) -> 0 | IB101: =SUM(IB94:IB100) -> 0 | IC101: =SUM(IC94:IC100) -> 0 | ID101: =SUM(ID94:ID100) -> 0 | ... JB101: =SUM(JB94:JB100) -> 0 | JD101: =SUM(JD94:JD100) -> 0 | JE101: =SUM(JE94:JE100) -> 0 | JF101: =SUM(JF94:JF100) -> 0 | JG101: =SUM(JG94:JG100) -> 0 | JH101: =SUM(JH94:JH100) -> 0 | JI101: =SUM(JI94:JI100) -> 0 | JJ101: =SUM(JJ94:JJ100) -> 0 | JK101: =SUM(JK94:JK100) -> 0 | ... KH101: =SUM(KH94:KH100) -> 0 | KJ101: =SUM(KJ94:KJ100) -> 0 | KK101: =SUM(KK94:KK100) -> 0 | KL101: =SUM(KL94:KL100) -> 0 | KM101: =SUM(KM94:KM100) -> 0 | KN101: =SUM(KN94:KN100) -> 0 | KO101: =SUM(KO94:KO100) -> 0 | KP101: =SUM(KP94:KP100) -> 0 | KQ101: =SUM(KQ94:KQ100) -> 0 | ... LO101: =SUM(LO94:LO100) -> 0 | LQ101: =SUM(LQ94:LQ100) -> 0 | LR101: =SUM(LR94:LR100) -> 0 | LS101: =SUM(LS94:LS100) -> 0 | LT101: =SUM(LT94:LT100) -> 0 | LU101: =SUM(LU94:LU100) -> 0 | LV101: =SUM(LV94:LV100) -> 0 | LW101: =SUM(LW94:LW100) -> 0 | LX101: =SUM(LX94:LX100) -> 0 | ... MU101: =SUM(MU94:MU100) -> 0 | MW101: =SUM(MW94:MW100) -> 0 | MX101: =SUM(MX94:MX100) -> 0 | MY101: =SUM(MY94:MY100) -> 0 | MZ101: =SUM(MZ94:MZ100) -> 0 | NA101: =SUM(NA94:NA100) -> 0 | NB101: =SUM(NB94:NB100) -> 0 | NC101: =SUM(NC94:NC100) -> 0 | ND101: =SUM(ND94:ND100) -> 0 | ... OB101: =SUM(OB94:OB100) -> 0 | OC101: =SUM(AI101,BN101,CU101,EA101,FH101,GN101,HU101,JB101,KH101,LO101,MU101,OB101) -> 0 | OE101: =SUM(OE94:OE100) -> 0 | OF101: =SUM(OF94:OF100) -> 0 | OG101: =SUM(OG94:OG100) -> 0 | OH101: =SUM(OH94:OH100) -> 0 | OI101: =SUM(OI94:OI100) -> 0 | OJ101: =SUM(OJ94:OJ100) -> 0 | OK101: =SUM(OK94:OK100) -> 0 | OL101: =SUM(OL94:OL100) -> 0 | ... PJ101: =SUM(PJ94:PJ100) -> 0 | PL101: =SUM(PL94:PL100) -> 0 | PM101: =SUM(PM94:PM100) -> 0 | PN101: =SUM(PN94:PN100) -> 0 | PO101: =SUM(PO94:PO100) -> 0 | PP101: =SUM(PP94:PP100) -> 0 | PQ101: =SUM(PQ94:PQ100) -> 0 | PR101: =SUM(PR94:PR100) -> 0 | PS101: =SUM(PS94:PS100) -> 0 | ... QO101: =SUM(QO94:QO100) -> 0 | QQ101: =SUM(QQ94:QQ100) -> 0 | QR101: =SUM(QR94:QR100) -> 0 | QS101: =SUM(QS94:QS100) -> 0 | QT101: =SUM(QT94:QT100) -> 0 | QU101: =SUM(QU94:QU100) -> 0 | QV101: =SUM(QV94:QV100) -> 0 | QW101: =SUM(QW94:QW100) -> 0 | QX101: =SUM(QX94:QX100) -> 0 | ... RV101: =SUM(RV94:RV100) -> 0 | RW101: =SUM(PJ101,QO101,RV101) -> 0
A103: 1 | B103: SERVIÇOS DE TERCEIROS - FIXOS
B104: Consultoria Contábil | H104: 759 | AI104: =SUM(D104:AH104) -> 759 | AO104: =810.5 -> 810.5 | BN104: =SUM(AK104:BM104) -> 810.5 | BT104: =810.5 -> 810.5 | CU104: =SUM(BP104:CT104) -> 810.5 | DB104: =810.5 -> 810.5 | EA104: =SUM(CW104:DZ104) -> 810.5 | EG104: =810.5 -> 810.5 | FH104: =SUM(EC104:FG104) -> 810.5 | FN104: =810.5 -> 810.5 | GN104: =SUM(FJ104:GM104) -> 810.5 | GT104: =810.5 -> 810.5 | HU104: =SUM(GP104:HT104) -> 810.5 | IA104: =810.5 -> 810.5 | JB104: =SUM(HW104:JA104) -> 810.5 | JH104: =810.5 -> 810.5 | KH104: =SUM(JD104:KG104) -> 810.5 | KN104: =810.5 -> 810.5 | LO104: =SUM(KJ104:LN104) -> 810.5 | LU104: =810.5 -> 810.5 | MU104: =SUM(LQ104:MT104) -> 810.5 | NA104: =810.5+810.5 -> 1621 | OB104: =SUM(MW104:OA104) -> 1621 | OC104: =SUM(AI104,BN104,CU104,EA104,FH104,GN104,HU104,JB104,KH104,LO104,MU104,OB104) -> 10485 | PJ104: =SUM(OE104:PI104) -> 0 | QO104: =SUM(PL104:QN104) -> 0 | RV104: =SUM(QQ104:RU104) -> 0 | RW104: =SUM(PJ104,QO104,RV104) -> 0
B105: Consultoria de Gestão Empresarial | AI105: =SUM(D105:AH105) -> 0 | BN105: =SUM(AK105:BM105) -> 0 | CU105: =SUM(BP105:CT105) -> 0 | EA105: =SUM(CW105:DZ105) -> 0 | FH105: =SUM(EC105:FG105) -> 0 | GN105: =SUM(FJ105:GM105) -> 0 | HU105: =SUM(GP105:HT105) -> 0 | JB105: =SUM(HW105:JA105) -> 0 | KH105: =SUM(JD105:KG105) -> 0 | LO105: =SUM(KJ105:LN105) -> 0 | MU105: =SUM(LQ105:MT105) -> 0 | OB105: =SUM(MW105:OA105) -> 0 | OC105: =SUM(AI105,BN105,CU105,EA105,FH105,GN105,HU105,JB105,KH105,LO105,MU105,OB105) -> 0 | PJ105: =SUM(OE105:PI105) -> 0 | QO105: =SUM(PL105:QN105) -> 0 | RV105: =SUM(QQ105:RU105) -> 0 | RW105: =SUM(PJ105,QO105,RV105) -> 0
B106: Consultoria Financeira | AI106: =SUM(D106:AH106) -> 0 | BN106: =SUM(AK106:BM106) -> 0 | CU106: =SUM(BP106:CT106) -> 0 | EA106: =SUM(CW106:DZ106) -> 0 | FH106: =SUM(EC106:FG106) -> 0 | GN106: =SUM(FJ106:GM106) -> 0 | HU106: =SUM(GP106:HT106) -> 0 | JB106: =SUM(HW106:JA106) -> 0 | KH106: =SUM(JD106:KG106) -> 0 | LO106: =SUM(KJ106:LN106) -> 0 | MU106: =SUM(LQ106:MT106) -> 0 | OB106: =SUM(MW106:OA106) -> 0 | OC106: =SUM(AI106,BN106,CU106,EA106,FH106,GN106,HU106,JB106,KH106,LO106,MU106,OB106) -> 0 | PJ106: =SUM(OE106:PI106) -> 0 | QO106: =SUM(PL106:QN106) -> 0 | RV106: =SUM(QQ106:RU106) -> 0 | RW106: =SUM(PJ106,QO106,RV106) -> 0
B107: Consultoria Jurídica | AI107: =SUM(D107:AH107) -> 0 | BN107: =SUM(AK107:BM107) -> 0 | CU107: =SUM(BP107:CT107) -> 0 | EA107: =SUM(CW107:DZ107) -> 0 | FH107: =SUM(EC107:FG107) -> 0 | GN107: =SUM(FJ107:GM107) -> 0 | HU107: =SUM(GP107:HT107) -> 0 | JB107: =SUM(HW107:JA107) -> 0 | KH107: =SUM(JD107:KG107) -> 0 | LO107: =SUM(KJ107:LN107) -> 0 | MU107: =SUM(LQ107:MT107) -> 0 | OB107: =SUM(MW107:OA107) -> 0 | OC107: =SUM(AI107,BN107,CU107,EA107,FH107,GN107,HU107,JB107,KH107,LO107,MU107,OB107) -> 0 | PJ107: =SUM(OE107:PI107) -> 0 | QO107: =SUM(PL107:QN107) -> 0 | RV107: =SUM(QQ107:RU107) -> 0 | RW107: =SUM(PJ107,QO107,RV107) -> 0
B108: Serviços de TI | AI108: =SUM(D108:AH108) -> 0 | BN108: =SUM(AK108:BM108) -> 0 | CU108: =SUM(BP108:CT108) -> 0 | EA108: =SUM(CW108:DZ108) -> 0 | FH108: =SUM(EC108:FG108) -> 0 | GN108: =SUM(FJ108:GM108) -> 0 | HU108: =SUM(GP108:HT108) -> 0 | JB108: =SUM(HW108:JA108) -> 0 | KH108: =SUM(JD108:KG108) -> 0 | LO108: =SUM(KJ108:LN108) -> 0 | MU108: =SUM(LQ108:MT108) -> 0 | OB108: =SUM(MW108:OA108) -> 0 | OC108: =SUM(AI108,BN108,CU108,EA108,FH108,GN108,HU108,JB108,KH108,LO108,MU108,OB108) -> 0 | PJ108: =SUM(OE108:PI108) -> 0 | QO108: =SUM(PL108:QN108) -> 0 | RV108: =SUM(QQ108:RU108) -> 0 | RW108: =SUM(PJ108,QO108,RV108) -> 0
B109: TOTAL SERVIÇOS DE TERCEIROS - FIXO | D109: =SUM(D104:D108) -> 0 | E109: =SUM(E104:E108) -> 0 | F109: =SUM(F104:F108) -> 0 | G109: =SUM(G104:G108) -> 0 | H109: =SUM(H104:H108) -> 759 | I109: =SUM(I104:I108) -> 0 | J109: =SUM(J104:J108) -> 0 | K109: =SUM(K104:K108) -> 0 | ... AI109: =SUM(AI104:AI108) -> 759 | AK109: =SUM(AK104:AK108) -> 0 | AL109: =SUM(AL104:AL108) -> 0 | AM109: =SUM(AM104:AM108) -> 0 | AN109: =SUM(AN104:AN108) -> 0 | AO109: =SUM(AO104:AO108) -> 810.5 | AP109: =SUM(AP104:AP108) -> 0 | AQ109: =SUM(AQ104:AQ108) -> 0 | AR109: =SUM(AR104:AR108) -> 0 | ... BN109: =SUM(BN104:BN108) -> 810.5 | BP109: =SUM(BP104:BP108) -> 0 | BQ109: =SUM(BQ104:BQ108) -> 0 | BR109: =SUM(BR104:BR108) -> 0 | BS109: =SUM(BS104:BS108) -> 0 | BT109: =SUM(BT104:BT108) -> 810.5 | BU109: =SUM(BU104:BU108) -> 0 | BV109: =SUM(BV104:BV108) -> 0 | BW109: =SUM(BW104:BW108) -> 0 | ... CU109: =SUM(CU104:CU108) -> 810.5 | CW109: =SUM(CW104:CW108) -> 0 | CX109: =SUM(CX104:CX108) -> 0 | CY109: =SUM(CY104:CY108) -> 0 | CZ109: =SUM(CZ104:CZ108) -> 0 | DA109: =SUM(DA104:DA108) -> 0 | DB109: =SUM(DB104:DB108) -> 810.5 | DC109: =SUM(DC104:DC108) -> 0 | DD109: =SUM(DD104:DD108) -> 0 | ... EA109: =SUM(EA104:EA108) -> 810.5 | EC109: =SUM(EC104:EC108) -> 0 | ED109: =SUM(ED104:ED108) -> 0 | EE109: =SUM(EE104:EE108) -> 0 | EF109: =SUM(EF104:EF108) -> 0 | EG109: =SUM(EG104:EG108) -> 810.5 | EH109: =SUM(EH104:EH108) -> 0 | EI109: =SUM(EI104:EI108) -> 0 | EJ109: =SUM(EJ104:EJ108) -> 0 | ... FH109: =SUM(FH104:FH108) -> 810.5 | FJ109: =SUM(FJ104:FJ108) -> 0 | FK109: =SUM(FK104:FK108) -> 0 | FL109: =SUM(FL104:FL108) -> 0 | FM109: =SUM(FM104:FM108) -> 0 | FN109: =SUM(FN104:FN108) -> 810.5 | FO109: =SUM(FO104:FO108) -> 0 | FP109: =SUM(FP104:FP108) -> 0 | FQ109: =SUM(FQ104:FQ108) -> 0 | ... GN109: =SUM(GN104:GN108) -> 810.5 | GP109: =SUM(GP104:GP108) -> 0 | GQ109: =SUM(GQ104:GQ108) -> 0 | GR109: =SUM(GR104:GR108) -> 0 | GS109: =SUM(GS104:GS108) -> 0 | GT109: =SUM(GT104:GT108) -> 810.5 | GU109: =SUM(GU104:GU108) -> 0 | GV109: =SUM(GV104:GV108) -> 0 | GW109: =SUM(GW104:GW108) -> 0 | ... HU109: =SUM(HU104:HU108) -> 810.5 | HW109: =SUM(HW104:HW108) -> 0 | HX109: =SUM(HX104:HX108) -> 0 | HY109: =SUM(HY104:HY108) -> 0 | HZ109: =SUM(HZ104:HZ108) -> 0 | IA109: =SUM(IA104:IA108) -> 810.5 | IB109: =SUM(IB104:IB108) -> 0 | IC109: =SUM(IC104:IC108) -> 0 | ID109: =SUM(ID104:ID108) -> 0 | ... JB109: =SUM(JB104:JB108) -> 810.5 | JD109: =SUM(JD104:JD108) -> 0 | JE109: =SUM(JE104:JE108) -> 0 | JF109: =SUM(JF104:JF108) -> 0 | JG109: =SUM(JG104:JG108) -> 0 | JH109: =SUM(JH104:JH108) -> 810.5 | JI109: =SUM(JI104:JI108) -> 0 | JJ109: =SUM(JJ104:JJ108) -> 0 | JK109: =SUM(JK104:JK108) -> 0 | ... KH109: =SUM(KH104:KH108) -> 810.5 | KJ109: =SUM(KJ104:KJ108) -> 0 | KK109: =SUM(KK104:KK108) -> 0 | KL109: =SUM(KL104:KL108) -> 0 | KM109: =SUM(KM104:KM108) -> 0 | KN109: =SUM(KN104:KN108) -> 810.5 | KO109: =SUM(KO104:KO108) -> 0 | KP109: =SUM(KP104:KP108) -> 0 | KQ109: =SUM(KQ104:KQ108) -> 0 | ... LO109: =SUM(LO104:LO108) -> 810.5 | LQ109: =SUM(LQ104:LQ108) -> 0 | LR109: =SUM(LR104:LR108) -> 0 | LS109: =SUM(LS104:LS108) -> 0 | LT109: =SUM(LT104:LT108) -> 0 | LU109: =SUM(LU104:LU108) -> 810.5 | LV109: =SUM(LV104:LV108) -> 0 | LW109: =SUM(LW104:LW108) -> 0 | LX109: =SUM(LX104:LX108) -> 0 | ... MU109: =SUM(MU104:MU108) -> 810.5 | MW109: =SUM(MW104:MW108) -> 0 | MX109: =SUM(MX104:MX108) -> 0 | MY109: =SUM(MY104:MY108) -> 0 | MZ109: =SUM(MZ104:MZ108) -> 0 | NA109: =SUM(NA104:NA108) -> 1621 | NB109: =SUM(NB104:NB108) -> 0 | NC109: =SUM(NC104:NC108) -> 0 | ND109: =SUM(ND104:ND108) -> 0 | ... OB109: =SUM(OB104:OB108) -> 1621 | OC109: =SUM(AI109,BN109,CU109,EA109,FH109,GN109,HU109,JB109,KH109,LO109,MU109,OB109) -> 10485 | OE109: =SUM(OE104:OE108) -> 0 | OF109: =SUM(OF104:OF108) -> 0 | OG109: =SUM(OG104:OG108) -> 0 | OH109: =SUM(OH104:OH108) -> 0 | OI109: =SUM(OI104:OI108) -> 0 | OJ109: =SUM(OJ104:OJ108) -> 0 | OK109: =SUM(OK104:OK108) -> 0 | OL109: =SUM(OL104:OL108) -> 0 | ... PJ109: =SUM(PJ104:PJ108) -> 0 | PL109: =SUM(PL104:PL108) -> 0 | PM109: =SUM(PM104:PM108) -> 0 | PN109: =SUM(PN104:PN108) -> 0 | PO109: =SUM(PO104:PO108) -> 0 | PP109: =SUM(PP104:PP108) -> 0 | PQ109: =SUM(PQ104:PQ108) -> 0 | PR109: =SUM(PR104:PR108) -> 0 | PS109: =SUM(PS104:PS108) -> 0 | ... QO109: =SUM(QO104:QO108) -> 0 | QQ109: =SUM(QQ104:QQ108) -> 0 | QR109: =SUM(QR104:QR108) -> 0 | QS109: =SUM(QS104:QS108) -> 0 | QT109: =SUM(QT104:QT108) -> 0 | QU109: =SUM(QU104:QU108) -> 0 | QV109: =SUM(QV104:QV108) -> 0 | QW109: =SUM(QW104:QW108) -> 0 | QX109: =SUM(QX104:QX108) -> 0 | ... RV109: =SUM(RV104:RV108) -> 0 | RW109: =SUM(PJ109,QO109,RV109) -> 0
A111: 1 | B111: DESPESAS COM CARTÃO DE CRÉDITO
A112: 2 | B112: Cartão de Crédito - ITAU | D112: =SUM(D113:D130) -> 0 | E112: =SUM(E113:E130) -> 0 | F112: =SUM(F113:F130) -> 0 | G112: =SUM(G113:G130) -> 0 | H112: =SUM(H113:H130) -> 0 | I112: =SUM(I113:I130) -> 0 | J112: =SUM(J113:J130) -> 0 | K112: =SUM(K113:K130) -> 0 | ... AH112: =SUM(AH113:AH130) -> 0 | AI112: =SUM(D112:AH112) -> 0 | AK112: =SUM(AK113:AK130) -> 0 | AL112: =SUM(AL113:AL130) -> 0 | AM112: =SUM(AM113:AM130) -> 0 | AN112: =SUM(AN113:AN130) -> 0 | AO112: =SUM(AO113:AO130) -> 0 | AP112: =SUM(AP113:AP130) -> 0 | AQ112: =SUM(AQ113:AQ130) -> 0 | AR112: =SUM(AR113:AR130) -> 0 | ... BM112: =SUM(BM113:BM130) -> 0 | BN112: =SUM(AK112:BM112) -> 0 | BP112: =SUM(BP113:BP130) -> 0 | BQ112: =SUM(BQ113:BQ130) -> 0 | BR112: =SUM(BR113:BR130) -> 0 | BS112: =SUM(BS113:BS130) -> 0 | BT112: =SUM(BT113:BT130) -> 0 | BU112: =SUM(BU113:BU130) -> 0 | BV112: =SUM(BV113:BV130) -> 0 | BW112: =SUM(BW113:BW130) -> 0 | ... CT112: =SUM(CT113:CT130) -> 0 | CU112: =SUM(BP112:CT112) -> 0 | CW112: =SUM(CW113:CW130) -> 0 | CX112: =SUM(CX113:CX130) -> 0 | CY112: =SUM(CY113:CY130) -> 0 | CZ112: =SUM(CZ113:CZ130) -> 0 | DA112: =SUM(DA113:DA130) -> 0 | DB112: =SUM(DB113:DB130) -> 0 | DC112: =SUM(DC113:DC130) -> 0 | DD112: =SUM(DD113:DD130) -> 0 | ... DZ112: =SUM(DZ113:DZ130) -> 0 | EA112: =SUM(CW112:DZ112) -> 0 | EC112: =SUM(EC113:EC130) -> 0 | ED112: =SUM(ED113:ED130) -> 0 | EE112: =SUM(EE113:EE130) -> 0 | EF112: =SUM(EF113:EF130) -> 0 | EG112: =SUM(EG113:EG130) -> 0 | EH112: =SUM(EH113:EH130) -> 0 | EI112: =SUM(EI113:EI130) -> 0 | EJ112: =SUM(EJ113:EJ130) -> 0 | ... FG112: =SUM(FG113:FG130) -> 0 | FH112: =SUM(EC112:FG112) -> 0 | FJ112: =SUM(FJ113:FJ130) -> 0 | FK112: =SUM(FK113:FK130) -> 0 | FL112: =SUM(FL113:FL130) -> 0 | FM112: =SUM(FM113:FM130) -> 0 | FN112: =SUM(FN113:FN130) -> 0 | FO112: =SUM(FO113:FO130) -> 0 | FP112: =SUM(FP113:FP130) -> 0 | FQ112: =SUM(FQ113:FQ130) -> 0 | ... GM112: =SUM(GM113:GM130) -> 0 | GN112: =SUM(FJ112:GM112) -> 0 | GP112: =SUM(GP113:GP130) -> 0 | GQ112: =SUM(GQ113:GQ130) -> 0 | GR112: =SUM(GR113:GR130) -> 0 | GS112: =SUM(GS113:GS130) -> 0 | GT112: =SUM(GT113:GT130) -> 0 | GU112: =SUM(GU113:GU130) -> 0 | GV112: =SUM(GV113:GV130) -> 0 | GW112: =SUM(GW113:GW130) -> 0 | ... HT112: =SUM(HT113:HT130) -> 0 | HU112: =SUM(GP112:HT112) -> 0 | HW112: =SUM(HW113:HW130) -> 0 | HX112: =SUM(HX113:HX130) -> 0 | HY112: =SUM(HY113:HY130) -> 0 | HZ112: =SUM(HZ113:HZ130) -> 0 | IA112: =SUM(IA113:IA130) -> 0 | IB112: =SUM(IB113:IB130) -> 0 | IC112: =SUM(IC113:IC130) -> 0 | ID112: =SUM(ID113:ID130) -> 0 | ... JA112: =SUM(JA113:JA130) -> 0 | JB112: =SUM(HW112:JA112) -> 0 | JD112: =SUM(JD113:JD130) -> 0 | JE112: =SUM(JE113:JE130) -> 0 | JF112: =SUM(JF113:JF130) -> 0 | JG112: =SUM(JG113:JG130) -> 0 | JH112: =SUM(JH113:JH130) -> 0 | JI112: =SUM(JI113:JI130) -> 0 | JJ112: =SUM(JJ113:JJ130) -> 0 | JK112: =SUM(JK113:JK130) -> 0 | ... KG112: =SUM(KG113:KG130) -> 0 | KH112: =SUM(JD112:KG112) -> 0 | KJ112: =SUM(KJ113:KJ130) -> 0 | KK112: =SUM(KK113:KK130) -> 0 | KL112: =SUM(KL113:KL130) -> 0 | KM112: =SUM(KM113:KM130) -> 0 | KN112: =SUM(KN113:KN130) -> 0 | KO112: =SUM(KO113:KO130) -> 0 | KP112: =SUM(KP113:KP130) -> 0 | KQ112: =SUM(KQ113:KQ130) -> 0 | ... LN112: =SUM(LN113:LN130) -> 0 | LO112: =SUM(KJ112:LN112) -> 0 | LQ112: =SUM(LQ113:LQ130) -> 0 | LR112: =SUM(LR113:LR130) -> 0 | LS112: =SUM(LS113:LS130) -> 0 | LT112: =SUM(LT113:LT130) -> 0 | LU112: =SUM(LU113:LU130) -> 0 | LV112: =SUM(LV113:LV130) -> 0 | LW112: =SUM(LW113:LW130) -> 0 | LX112: =SUM(LX113:LX130) -> 0 | ... MT112: =SUM(MT113:MT130) -> 0 | MU112: =SUM(LQ112:MT112) -> 0 | MW112: =SUM(MW113:MW130) -> 0 | MX112: =SUM(MX113:MX130) -> 0 | MY112: =SUM(MY113:MY130) -> 0 | MZ112: =SUM(MZ113:MZ130) -> 0 | NA112: =SUM(NA113:NA130) -> 0 | NB112: =SUM(NB113:NB130) -> 0 | NC112: =SUM(NC113:NC130) -> 0 | ND112: =SUM(ND113:ND130) -> 0 | ... OA112: =SUM(OA113:OA130) -> 0 | OB112: =SUM(MW112:OA112) -> 0 | OC112: =SUM(AI112,BN112,CU112,EA112,FH112,GN112,HU112,JB112,KH112,LO112,MU112,OB112) -> 0 | OE112: =SUM(OE113:OE130) -> 0 | OF112: =SUM(OF113:OF130) -> 0 | OG112: =SUM(OG113:OG130) -> 0 | OH112: =SUM(OH113:OH130) -> 0 | OI112: =SUM(OI113:OI130) -> 0 | OJ112: =SUM(OJ113:OJ130) -> 0 | OK112: =SUM(OK113:OK130) -> 0 | OL112: =SUM(OL113:OL130) -> 0 | ... PI112: =SUM(PI113:PI130) -> 0 | PJ112: =SUM(OE112:PI112) -> 0 | PL112: =SUM(PL113:PL130) -> 0 | PM112: =SUM(PM113:PM130) -> 0 | PN112: =SUM(PN113:PN130) -> 0 | PO112: =SUM(PO113:PO130) -> 0 | PP112: =SUM(PP113:PP130) -> 0 | PQ112: =SUM(PQ113:PQ130) -> 0 | PR112: =SUM(PR113:PR130) -> 0 | PS112: =SUM(PS113:PS130) -> 0 | ... QN112: =SUM(QN113:QN130) -> 0 | QO112: =SUM(PL112:QN112) -> 0 | QQ112: =SUM(QQ113:QQ130) -> 0 | QR112: =SUM(QR113:QR130) -> 0 | QS112: =SUM(QS113:QS130) -> 0 | QT112: =SUM(QT113:QT130) -> 0 | QU112: =SUM(QU113:QU130) -> 0 | QV112: =SUM(QV113:QV130) -> 0 | QW112: =SUM(QW113:QW130) -> 0 | QX112: =SUM(QX113:QX130) -> 0 | ... RU112: =SUM(RU113:RU130) -> 0 | RV112: =SUM(QQ112:RU112) -> 0 | RW112: =SUM(PJ112,QO112,RV112) -> 0
...

Sheet SALDOS
C2: DAXX MIDIA PE
A3: DATA | C3: SALDO FINAL CC | D3: SALDO FINAL CDB | E3: SALDO FINAL TRUST DI | F3: C/ CORRENTE + APLICAÇÃO
A4: ='DAXX MIDIA PE'!$D1 -> 46023 | C4: ='DAXX MIDIA PE'!$D255 -> 3236.1 | D4: ='DAXX MIDIA PE'!$D261 -> 0 | E4: ='DAXX MIDIA PE'!$D267 -> 0 | F4: ='DAXX MIDIA PE'!$D269 -> 3236.1
A5: ='DAXX MIDIA PE'!$E1 -> 46024 | C5: ='DAXX MIDIA PE'!$E255 -> 3236.1 | D5: ='DAXX MIDIA PE'!$E261 -> 0 | E5: ='DAXX MIDIA PE'!$E267 -> 0 | F5: ='DAXX MIDIA PE'!$E269 -> 3236.1
A6: ='DAXX MIDIA PE'!$F1 -> 46025 | C6: ='DAXX MIDIA PE'!$F255 -> 3236.1 | D6: ='DAXX MIDIA PE'!$F261 -> 0 | E6: ='DAXX MIDIA PE'!$F267 -> 0 | F6: ='DAXX MIDIA PE'!$F269 -> 3236.1
A7: ='DAXX MIDIA PE'!$G1 -> 46026 | C7: ='DAXX MIDIA PE'!$G255 -> 3236.1 | D7: ='DAXX MIDIA PE'!$G261 -> 0 | E7: ='DAXX MIDIA PE'!$G267 -> 0 | F7: ='DAXX MIDIA PE'!$G269 -> 3236.1
A8: ='DAXX MIDIA PE'!$H1 -> 46027 | C8: ='DAXX MIDIA PE'!$H255 -> 2478.86 | D8: ='DAXX MIDIA PE'!$H261 -> 0 | E8: ='DAXX MIDIA PE'!$H267 -> 0 | F8: ='DAXX MIDIA PE'!$H269 -> 2478.86
A9: ='DAXX MIDIA PE'!$I1 -> 46028 | C9: ='DAXX MIDIA PE'!$I255 -> 2478.86 | D9: ='DAXX MIDIA PE'!$I261 -> 0 | E9: ='DAXX MIDIA PE'!$I267 -> 0 | F9: ='DAXX MIDIA PE'!$I269 -> 2478.86
A10: ='DAXX MIDIA PE'!$J1 -> 46029 | C10: ='DAXX MIDIA PE'!$J255 -> 2478.86 | D10: ='DAXX MIDIA PE'!$J261 -> 0 | E10: ='DAXX MIDIA PE'!$J267 -> 0 | F10: ='DAXX MIDIA PE'!$J269 -> 2478.86
A11: ='DAXX MIDIA PE'!$K1 -> 46030 | C11: ='DAXX MIDIA PE'!$K255 -> 2478.86 | D11: ='DAXX MIDIA PE'!$K261 -> 0 | E11: ='DAXX MIDIA PE'!$K267 -> 0 | F11: ='DAXX MIDIA PE'!$K269 -> 2478.86
A12: ='DAXX MIDIA PE'!$L1 -> 46031 | C12: ='DAXX MIDIA PE'!$L255 -> 2478.86 | D12: ='DAXX MIDIA PE'!$L261 -> 0 | E12: ='DAXX MIDIA PE'!$L267 -> 0 | F12: ='DAXX MIDIA PE'!$L269 -> 2478.86
A13: ='DAXX MIDIA PE'!$M1 -> 46032 | C13: ='DAXX MIDIA PE'!$M255 -> 2478.86 | D13: ='DAXX MIDIA PE'!$M261 -> 0 | E13: ='DAXX MIDIA PE'!$M267 -> 0 | F13: ='DAXX MIDIA PE'!$M269 -> 2478.86
A14: ='DAXX MIDIA PE'!$N1 -> 46033 | C14: ='DAXX MIDIA PE'!$N255 -> 2478.86 | D14: ='DAXX MIDIA PE'!$N261 -> 0 | E14: ='DAXX MIDIA PE'!$N267 -> 0 | F14: ='DAXX MIDIA PE'!$N269 -> 2478.86
A15: ='DAXX MIDIA PE'!$O1 -> 46034 | C15: ='DAXX MIDIA PE'!$O255 -> 2478.86 | D15: ='DAXX MIDIA PE'!$O261 -> 0 | E15: ='DAXX MIDIA PE'!$O267 -> 0 | F15: ='DAXX MIDIA PE'!$O269 -> 2478.86
A16: ='DAXX MIDIA PE'!$P1 -> 46035 | C16: ='DAXX MIDIA PE'!$P255 -> 2478.86 | D16: ='DAXX MIDIA PE'!$P261 -> 0 | E16: ='DAXX MIDIA PE'!$P267 -> 0 | F16: ='DAXX MIDIA PE'!$P269 -> 2478.86
A17: ='DAXX MIDIA PE'!$Q1 -> 46036 | C17: ='DAXX MIDIA PE'!$Q255 -> 1366.62 | D17: ='DAXX MIDIA PE'!$Q261 -> 0 | E17: ='DAXX MIDIA PE'!$Q267 -> 0 | F17: ='DAXX MIDIA PE'!$Q269 -> 1366.62
A18: ='DAXX MIDIA PE'!$R1 -> 46037 | C18: ='DAXX MIDIA PE'!$R255 -> 1366.62 | D18: ='DAXX MIDIA PE'!$R261 -> 0 | E18: ='DAXX MIDIA PE'!$R267 -> 0 | F18: ='DAXX MIDIA PE'!$R269 -> 1366.62
A19: ='DAXX MIDIA PE'!$S1 -> 46038 | C19: ='DAXX MIDIA PE'!$S255 -> 1366.62 | D19: ='DAXX MIDIA PE'!$S261 -> 0 | E19: ='DAXX MIDIA PE'!$S267 -> 0 | F19: ='DAXX MIDIA PE'!$S269 -> 1366.62
A20: ='DAXX MIDIA PE'!$T1 -> 46039 | C20: ='DAXX MIDIA PE'!$T255 -> 1366.62 | D20: ='DAXX MIDIA PE'!$T261 -> 0 | E20: ='DAXX MIDIA PE'!$T267 -> 0 | F20: ='DAXX MIDIA PE'!$T269 -> 1366.62
A21: ='DAXX MIDIA PE'!$U1 -> 46040 | C21: ='DAXX MIDIA PE'!$U255 -> 1366.62 | D21: ='DAXX MIDIA PE'!$U261 -> 0 | E21: ='DAXX MIDIA PE'!$U267 -> 0 | F21: ='DAXX MIDIA PE'!$U269 -> 1366.62
A22: ='DAXX MIDIA PE'!$V1 -> 46041 | C22: ='DAXX MIDIA PE'!$V255 -> 1366.62 | D22: ='DAXX MIDIA PE'!$V261 -> 0 | E22: ='DAXX MIDIA PE'!$V267 -> 0 | F22: ='DAXX MIDIA PE'!$V269 -> 1366.62
A23: ='DAXX MIDIA PE'!$W1 -> 46042 | C23: ='DAXX MIDIA PE'!$W255 -> 1352.65 | D23: ='DAXX MIDIA PE'!$W261 -> 0 | E23: ='DAXX MIDIA PE'!$W267 -> 0 | F23: ='DAXX MIDIA PE'!$W269 -> 1352.65
A24: ='DAXX MIDIA PE'!$X1 -> 46043 | C24: ='DAXX MIDIA PE'!$X255 -> 1352.65 | D24: ='DAXX MIDIA PE'!$X261 -> 0 | E24: ='DAXX MIDIA PE'!$X267 -> 0 | F24: ='DAXX MIDIA PE'!$X269 -> 1352.65
A25: ='DAXX MIDIA PE'!$Y1 -> 46044 | C25: ='DAXX MIDIA PE'!$Y255 -> 1352.65 | D25: ='DAXX MIDIA PE'!$Y261 -> 0 | E25: ='DAXX MIDIA PE'!$Y267 -> 0 | F25: ='DAXX MIDIA PE'!$Y269 -> 1352.65
A26: ='DAXX MIDIA PE'!$Z1 -> 46045 | C26: ='DAXX MIDIA PE'!$Z255 -> 1352.65 | D26: ='DAXX MIDIA PE'!$Z261 -> 0 | E26: ='DAXX MIDIA PE'!$Z267 -> 0 | F26: ='DAXX MIDIA PE'!$Z269 -> 1352.65
A27: ='DAXX MIDIA PE'!$AA1 -> 46046 | C27: ='DAXX MIDIA PE'!$AA255 -> 1352.65 | D27: ='DAXX MIDIA PE'!$AA261 -> 0 | E27: ='DAXX MIDIA PE'!$AA267 -> 0 | F27: ='DAXX MIDIA PE'!$AA269 -> 1352.65
A28: ='DAXX MIDIA PE'!$AB1 -> 46047 | C28: ='DAXX MIDIA PE'!$AB255 -> 1352.65 | D28: ='DAXX MIDIA PE'!$AB261 -> 0 | E28: ='DAXX MIDIA PE'!$AB267 -> 0 | F28: ='DAXX MIDIA PE'!$AB269 -> 1352.65
A29: ='DAXX MIDIA PE'!$AC1 -> 46048 | C29: ='DAXX MIDIA PE'!$AC255 -> 1123.26 | D29: ='DAXX MIDIA PE'!$AC261 -> 0 | E29: ='DAXX MIDIA PE'!$AC267 -> 0 | F29: ='DAXX MIDIA PE'!$AC269 -> 1123.26
A30: ='DAXX MIDIA PE'!$AD1 -> 46049 | C30: ='DAXX MIDIA PE'!$AD255 -> 1123.26 | D30: ='DAXX MIDIA PE'!$AD261 -> 0 | E30: ='DAXX MIDIA PE'!$AD267 -> 0 | F30: ='DAXX MIDIA PE'!$AD269 -> 1123.26
A31: ='DAXX MIDIA PE'!$AE1 -> 46050 | C31: ='DAXX MIDIA PE'!$AE255 -> 1123.26 | D31: ='DAXX MIDIA PE'!$AE261 -> 0 | E31: ='DAXX MIDIA PE'!$AE267 -> 0 | F31: ='DAXX MIDIA PE'!$AE269 -> 1123.26
A32: ='DAXX MIDIA PE'!$AF1 -> 46051 | C32: ='DAXX MIDIA PE'!$AF255 -> 1123.26 | D32: ='DAXX MIDIA PE'!$AF261 -> 0 | E32: ='DAXX MIDIA PE'!$AF267 -> 0 | F32: ='DAXX MIDIA PE'!$AF269 -> 1123.26
A33: ='DAXX MIDIA PE'!$AG1 -> 46052 | C33: ='DAXX MIDIA PE'!$AG255 -> 501.03 | D33: ='DAXX MIDIA PE'!$AG261 -> 0 | E33: ='DAXX MIDIA PE'!$AG267 -> 0 | F33: ='DAXX MIDIA PE'!$AG269 -> 501.03
A34: ='DAXX MIDIA PE'!$AH1 -> 46053 | C34: ='DAXX MIDIA PE'!$AH255 -> 501.03 | D34: ='DAXX MIDIA PE'!$AH261 -> 0 | E34: ='DAXX MIDIA PE'!$AH267 -> 0 | F34: ='DAXX MIDIA PE'!$AH269 -> 501.03
A35: ='DAXX MIDIA PE'!$AK1 -> 46054 | C35: ='DAXX MIDIA PE'!$AK255 -> 501.03 | D35: ='DAXX MIDIA PE'!$AK261 -> 0 | E35: ='DAXX MIDIA PE'!$AK267 -> 0 | F35: ='DAXX MIDIA PE'!$AK269 -> 501.03
A36: ='DAXX MIDIA PE'!$AL1 -> 46055 | C36: ='DAXX MIDIA PE'!$AL255 -> 501.03 | D36: ='DAXX MIDIA PE'!$AL261 -> 0 | E36: ='DAXX MIDIA PE'!$AL267 -> 0 | F36: ='DAXX MIDIA PE'!$AL269 -> 501.03
A37: ='DAXX MIDIA PE'!$AM1 -> 46056 | C37: ='DAXX MIDIA PE'!$AM255 -> 501.03 | D37: ='DAXX MIDIA PE'!$AM261 -> 0 | E37: ='DAXX MIDIA PE'!$AM267 -> 0 | F37: ='DAXX MIDIA PE'!$AM269 -> 501.03
A38: ='DAXX MIDIA PE'!$AN1 -> 46057 | C38: ='DAXX MIDIA PE'!$AN255 -> 501.03 | D38: ='DAXX MIDIA PE'!$AN261 -> 0 | E38: ='DAXX MIDIA PE'!$AN267 -> 0 | F38: ='DAXX MIDIA PE'!$AN269 -> 501.03
A39: ='DAXX MIDIA PE'!$AO1 -> 46058 | C39: ='DAXX MIDIA PE'!$AO255 -> 19690.53 | D39: ='DAXX MIDIA PE'!$AO261 -> 0 | E39: ='DAXX MIDIA PE'!$AO267 -> 0 | F39: ='DAXX MIDIA PE'!$AO269 -> 19690.53
A40: ='DAXX MIDIA PE'!$AP1 -> 46059 | C40: ='DAXX MIDIA PE'!$AP255 -> 19690.53 | D40: ='DAXX MIDIA PE'!$AP261 -> 0 | E40: ='DAXX MIDIA PE'!$AP267 -> 0 | F40: ='DAXX MIDIA PE'!$AP269 -> 19690.53
A41: ='DAXX MIDIA PE'!$AQ1 -> 46060 | C41: ='DAXX MIDIA PE'!$AQ255 -> 19690.53 | D41: ='DAXX MIDIA PE'!$AQ261 -> 0 | E41: ='DAXX MIDIA PE'!$AQ267 -> 0 | F41: ='DAXX MIDIA PE'!$AQ269 -> 19690.53
A42: ='DAXX MIDIA PE'!$AR1 -> 46061 | C42: ='DAXX MIDIA PE'!$AR255 -> 19690.53 | D42: ='DAXX MIDIA PE'!$AR261 -> 0 | E42: ='DAXX MIDIA PE'!$AR267 -> 0 | F42: ='DAXX MIDIA PE'!$AR269 -> 19690.53
A43: ='DAXX MIDIA PE'!$AS1 -> 46062 | C43: ='DAXX MIDIA PE'!$AS255 -> 19690.53 | D43: ='DAXX MIDIA PE'!$AS261 -> 0 | E43: ='DAXX MIDIA PE'!$AS267 -> 0 | F43: ='DAXX MIDIA PE'!$AS269 -> 19690.53
A44: ='DAXX MIDIA PE'!$AT1 -> 46063 | C44: ='DAXX MIDIA PE'!$AT255 -> 19157.98 | D44: ='DAXX MIDIA PE'!$AT261 -> 0 | E44: ='DAXX MIDIA PE'!$AT267 -> 0 | F44: ='DAXX MIDIA PE'!$AT269 -> 19157.98
A45: ='DAXX MIDIA PE'!$AU1 -> 46064 | C45: ='DAXX MIDIA PE'!$AU255 -> 19157.98 | D45: ='DAXX MIDIA PE'!$AU261 -> 0 | E45: ='DAXX MIDIA PE'!$AU267 -> 0 | F45: ='DAXX MIDIA PE'!$AU269 -> 19157.98
A46: ='DAXX MIDIA PE'!$AV1 -> 46065 | C46: ='DAXX MIDIA PE'!$AV255 -> 19157.98 | D46: ='DAXX MIDIA PE'!$AV261 -> 0 | E46: ='DAXX MIDIA PE'!$AV267 -> 0 | F46: ='DAXX MIDIA PE'!$AV269 -> 19157.98
A47: ='DAXX MIDIA PE'!$AW1 -> 46066 | C47: ='DAXX MIDIA PE'!$AW255 -> 19157.98 | D47: ='DAXX MIDIA PE'!$AW261 -> 0 | E47: ='DAXX MIDIA PE'!$AW267 -> 0 | F47: ='DAXX MIDIA PE'!$AW269 -> 19157.98
A48: ='DAXX MIDIA PE'!$AX1 -> 46067 | C48: ='DAXX MIDIA PE'!$AX255 -> 19157.98 | D48: ='DAXX MIDIA PE'!$AX261 -> 0 | E48: ='DAXX MIDIA PE'!$AX267 -> 0 | F48: ='DAXX MIDIA PE'!$AX269 -> 19157.98
A49: ='DAXX MIDIA PE'!$AY1 -> 46068 | C49: ='DAXX MIDIA PE'!$AY255 -> 19157.98 | D49: ='DAXX MIDIA PE'!$AY261 -> 0 | E49: ='DAXX MIDIA PE'!$AY267 -> 0 | F49: ='DAXX MIDIA PE'!$AY269 -> 19157.98
A50: ='DAXX MIDIA PE'!$AZ1 -> 46069 | C50: ='DAXX MIDIA PE'!$AZ255 -> 19157.98 | D50: ='DAXX MIDIA PE'!$AZ261 -> 0 | E50: ='DAXX MIDIA PE'!$AZ267 -> 0 | F50: ='DAXX MIDIA PE'!$AZ269 -> 19157.98
A51: ='DAXX MIDIA PE'!$BA1 -> 46070 | C51: ='DAXX MIDIA PE'!$BA255 -> 19157.98 | D51: ='DAXX MIDIA PE'!$BA261 -> 0 | E51: ='DAXX MIDIA PE'!$BA267 -> 0 | F51: ='DAXX MIDIA PE'!$BA269 -> 19157.98
A52: ='DAXX MIDIA PE'!$BB1 -> 46071 | C52: ='DAXX MIDIA PE'!$BB255 -> 19157.98 | D52: ='DAXX MIDIA PE'!$BB261 -> 0 | E52: ='DAXX MIDIA PE'!$BB267 -> 0 | F52: ='DAXX MIDIA PE'!$BB269 -> 19157.98
A53: ='DAXX MIDIA PE'!$BC1 -> 46072 | C53: ='DAXX MIDIA PE'!$BC255 -> 19157.98 | D53: ='DAXX MIDIA PE'!$BC261 -> 0 | E53: ='DAXX MIDIA PE'!$BC267 -> 0 | F53: ='DAXX MIDIA PE'!$BC269 -> 19157.98
A54: ='DAXX MIDIA PE'!$BD1 -> 46073 | C54: ='DAXX MIDIA PE'!$BD255 -> 19143.97 | D54: ='DAXX MIDIA PE'!$BD261 -> 0 | E54: ='DAXX MIDIA PE'!$BD267 -> 0 | F54: ='DAXX MIDIA PE'!$BD269 -> 19143.97
A55: ='DAXX MIDIA PE'!$BE1 -> 46074 | C55: ='DAXX MIDIA PE'!$BE255 -> 19143.97 | D55: ='DAXX MIDIA PE'!$BE261 -> 0 | E55: ='DAXX MIDIA PE'!$BE267 -> 0 | F55: ='DAXX MIDIA PE'!$BE269 -> 19143.97
A56: ='DAXX MIDIA PE'!$BF1 -> 46075 | C56: ='DAXX MIDIA PE'!$BF255 -> 19143.97 | D56: ='DAXX MIDIA PE'!$BF261 -> 0 | E56: ='DAXX MIDIA PE'!$BF267 -> 0 | F56: ='DAXX MIDIA PE'!$BF269 -> 19143.97
A57: ='DAXX MIDIA PE'!$BG1 -> 46076 | C57: ='DAXX MIDIA PE'!$BG255 -> 19143.97 | D57: ='DAXX MIDIA PE'!$BG261 -> 0 | E57: ='DAXX MIDIA PE'!$BG267 -> 0 | F57: ='DAXX MIDIA PE'!$BG269 -> 19143.97
A58: ='DAXX MIDIA PE'!$BH1 -> 46077 | C58: ='DAXX MIDIA PE'!$BH255 -> 19143.97 | D58: ='DAXX MIDIA PE'!$BH261 -> 0 | E58: ='DAXX MIDIA PE'!$BH267 -> 0 | F58: ='DAXX MIDIA PE'!$BH269 -> 19143.97
A59: ='DAXX MIDIA PE'!$BI1 -> 46078 | C59: ='DAXX MIDIA PE'!$BI255 -> 18914 | D59: ='DAXX MIDIA PE'!$BI261 -> 0 | E59: ='DAXX MIDIA PE'!$BI267 -> 0 | F59: ='DAXX MIDIA PE'!$BI269 -> 18914
A60: ='DAXX MIDIA PE'!$BJ1 -> 46079 | C60: ='DAXX MIDIA PE'!$BJ255 -> 18914 | D60: ='DAXX MIDIA PE'!$BJ261 -> 0 | E60: ='DAXX MIDIA PE'!$BJ267 -> 0 | F60: ='DAXX MIDIA PE'!$BJ269 -> 18914
A61: ='DAXX MIDIA PE'!$BK1 -> 46080 | C61: ='DAXX MIDIA PE'!$BK255 -> 18626.78 | D61: ='DAXX MIDIA PE'!$BK261 -> 0 | E61: ='DAXX MIDIA PE'!$BK267 -> 0 | F61: ='DAXX MIDIA PE'!$BK269 -> 18626.78
A62: ='DAXX MIDIA PE'!$BL1 -> 46081 | C62: ='DAXX MIDIA PE'!$BL255 -> 18626.78 | D62: ='DAXX MIDIA PE'!$BL261 -> 0 | E62: ='DAXX MIDIA PE'!$BL267 -> 0 | F62: ='DAXX MIDIA PE'!$BL269 -> 18626.78
A63: ='DAXX MIDIA PE'!$BM1 -> 0 | C63: ='DAXX MIDIA PE'!$BM255 -> 18626.78 | D63: ='DAXX MIDIA PE'!$BM261 -> 0 | E63: ='DAXX MIDIA PE'!$BM267 -> 0 | F63: ='DAXX MIDIA PE'!$BM269 -> 0
A64: ='DAXX MIDIA PE'!$BP1 -> 46082 | C64: ='DAXX MIDIA PE'!$BP255 -> 18626.78 | D64: ='DAXX MIDIA PE'!$BP261 -> 0 | E64: ='DAXX MIDIA PE'!$BP267 -> 0 | F64: ='DAXX MIDIA PE'!$BP269 -> 18626.78
A65: ='DAXX MIDIA PE'!$BQ1 -> 46083 | C65: ='DAXX MIDIA PE'!$BQ255 -> 18626.78 | D65: ='DAXX MIDIA PE'!$BQ261 -> 0 | E65: ='DAXX MIDIA PE'!$BQ267 -> 0 | F65: ='DAXX MIDIA PE'!$BQ269 -> 18626.78
A66: ='DAXX MIDIA PE'!$BR1 -> 46084 | C66: ='DAXX MIDIA PE'!$BR255 -> 18626.78 | D66: ='DAXX MIDIA PE'!$BR261 -> 0 | E66: ='DAXX MIDIA PE'!$BR267 -> 0 | F66: ='DAXX MIDIA PE'!$BR269 -> 18626.78
A67: ='DAXX MIDIA PE'!$BS1 -> 46085 | C67: ='DAXX MIDIA PE'!$BS255 -> 18626.78 | D67: ='DAXX MIDIA PE'!$BS261 -> 0 | E67: ='DAXX MIDIA PE'!$BS267 -> 0 | F67: ='DAXX MIDIA PE'!$BS269 -> 18626.78
A68: ='DAXX MIDIA PE'!$BT1 -> 46086 | C68: ='DAXX MIDIA PE'!$BT255 -> 17816.41 | D68: ='DAXX MIDIA PE'!$BT261 -> 0 | E68: ='DAXX MIDIA PE'!$BT267 -> 0 | F68: ='DAXX MIDIA PE'!$BT269 -> 17816.41
A69: ='DAXX MIDIA PE'!$BU1 -> 46087 | C69: ='DAXX MIDIA PE'!$BU255 -> 17816.41 | D69: ='DAXX MIDIA PE'!$BU261 -> 0 | E69: ='DAXX MIDIA PE'!$BU267 -> 0 | F69: ='DAXX MIDIA PE'!$BU269 -> 17816.41
A70: ='DAXX MIDIA PE'!$BV1 -> 46088 | C70: ='DAXX MIDIA PE'!$BV255 -> 17816.41 | D70: ='DAXX MIDIA PE'!$BV261 -> 0 | E70: ='DAXX MIDIA PE'!$BV267 -> 0 | F70: ='DAXX MIDIA PE'!$BV269 -> 17816.41
A71: ='DAXX MIDIA PE'!$BW1 -> 46089 | C71: ='DAXX MIDIA PE'!$BW255 -> 17816.41 | D71: ='DAXX MIDIA PE'!$BW261 -> 0 | E71: ='DAXX MIDIA PE'!$BW267 -> 0 | F71: ='DAXX MIDIA PE'!$BW269 -> 17816.41
A72: ='DAXX MIDIA PE'!$BX1 -> 46090 | C72: ='DAXX MIDIA PE'!$BX255 -> 17816.41 | D72: ='DAXX MIDIA PE'!$BX261 -> 0 | E72: ='DAXX MIDIA PE'!$BX267 -> 0 | F72: ='DAXX MIDIA PE'!$BX269 -> 17816.41
A73: ='DAXX MIDIA PE'!$BY1 -> 46091 | C73: ='DAXX MIDIA PE'!$BY255 -> 17816.41 | D73: ='DAXX MIDIA PE'!$BY261 -> 0 | E73: ='DAXX MIDIA PE'!$BY267 -> 0 | F73: ='DAXX MIDIA PE'!$BY269 -> 17816.41
A74: ='DAXX MIDIA PE'!$BZ1 -> 46092 | C74: ='DAXX MIDIA PE'!$BZ255 -> 17816.41 | D74: ='DAXX MIDIA PE'!$BZ261 -> 0 | E74: ='DAXX MIDIA PE'!$BZ267 -> 0 | F74: ='DAXX MIDIA PE'!$BZ269 -> 17816.41
A75: ='DAXX MIDIA PE'!$CA1 -> 46093 | C75: ='DAXX MIDIA PE'!$CA255 -> 17816.41 | D75: ='DAXX MIDIA PE'!$CA261 -> 0 | E75: ='DAXX MIDIA PE'!$CA267 -> 0 | F75: ='DAXX MIDIA PE'!$CA269 -> 17816.41
A76: ='DAXX MIDIA PE'!$CB1 -> 46094 | C76: ='DAXX MIDIA PE'!$CB255 -> 17816.41 | D76: ='DAXX MIDIA PE'!$CB261 -> 0 | E76: ='DAXX MIDIA PE'!$CB267 -> 0 | F76: ='DAXX MIDIA PE'!$CB269 -> 17816.41
A77: ='DAXX MIDIA PE'!$CC1 -> 46095 | C77: ='DAXX MIDIA PE'!$CC255 -> 17816.41 | D77: ='DAXX MIDIA PE'!$CC261 -> 0 | E77: ='DAXX MIDIA PE'!$CC267 -> 0 | F77: ='DAXX MIDIA PE'!$CC269 -> 17816.41
A78: ='DAXX MIDIA PE'!$CD1 -> 46096 | C78: ='DAXX MIDIA PE'!$CD255 -> 17816.41 | D78: ='DAXX MIDIA PE'!$CD261 -> 0 | E78: ='DAXX MIDIA PE'!$CD267 -> 0 | F78: ='DAXX MIDIA PE'!$CD269 -> 17816.41
A79: ='DAXX MIDIA PE'!$CE1 -> 46097 | C79: ='DAXX MIDIA PE'!$CE255 -> 17816.41 | D79: ='DAXX MIDIA PE'!$CE261 -> 0 | E79: ='DAXX MIDIA PE'!$CE267 -> 0 | F79: ='DAXX MIDIA PE'!$CE269 -> 17816.41
A80: ='DAXX MIDIA PE'!$CF1 -> 46098 | C80: ='DAXX MIDIA PE'!$CF255 -> 17816.41 | D80: ='DAXX MIDIA PE'!$CF261 -> 0 | E80: ='DAXX MIDIA PE'!$CF267 -> 0 | F80: ='DAXX MIDIA PE'!$CF269 -> 17816.41
A81: ='DAXX MIDIA PE'!$CG1 -> 46099 | C81: ='DAXX MIDIA PE'!$CG255 -> 17816.41 | D81: ='DAXX MIDIA PE'!$CG261 -> 0 | E81: ='DAXX MIDIA PE'!$CG267 -> 0 | F81: ='DAXX MIDIA PE'!$CG269 -> 17816.41
A82: ='DAXX MIDIA PE'!$CH1 -> 46100 | C82: ='DAXX MIDIA PE'!$CH255 -> 17816.41 | D82: ='DAXX MIDIA PE'!$CH261 -> 0 | E82: ='DAXX MIDIA PE'!$CH267 -> 0 | F82: ='DAXX MIDIA PE'!$CH269 -> 17816.41
A83: ='DAXX MIDIA PE'!$CI1 -> 46101 | C83: ='DAXX MIDIA PE'!$CI255 -> 17802.4 | D83: ='DAXX MIDIA PE'!$CI261 -> 0 | E83: ='DAXX MIDIA PE'!$CI267 -> 0 | F83: ='DAXX MIDIA PE'!$CI269 -> 17802.4
A84: ='DAXX MIDIA PE'!$CJ1 -> 46102 | C84: ='DAXX MIDIA PE'!$CJ255 -> 17802.4 | D84: ='DAXX MIDIA PE'!$CJ261 -> 0 | E84: ='DAXX MIDIA PE'!$CJ267 -> 0 | F84: ='DAXX MIDIA PE'!$CJ269 -> 17802.4
A85: ='DAXX MIDIA PE'!$CK1 -> 46103 | C85: ='DAXX MIDIA PE'!$CK255 -> 17802.4 | D85: ='DAXX MIDIA PE'!$CK261 -> 0 | E85: ='DAXX MIDIA PE'!$CK267 -> 0 | F85: ='DAXX MIDIA PE'!$CK269 -> 17802.4
A86: ='DAXX MIDIA PE'!$CL1 -> 46104 | C86: ='DAXX MIDIA PE'!$CL255 -> 17802.4 | D86: ='DAXX MIDIA PE'!$CL261 -> 0 | E86: ='DAXX MIDIA PE'!$CL267 -> 0 | F86: ='DAXX MIDIA PE'!$CL269 -> 17802.4
A87: ='DAXX MIDIA PE'!$CM1 -> 46105 | C87: ='DAXX MIDIA PE'!$CM255 -> 17802.4 | D87: ='DAXX MIDIA PE'!$CM261 -> 0 | E87: ='DAXX MIDIA PE'!$CM267 -> 0 | F87: ='DAXX MIDIA PE'!$CM269 -> 17802.4
A88: ='DAXX MIDIA PE'!$CN1 -> 46106 | C88: ='DAXX MIDIA PE'!$CN255 -> 17572.47 | D88: ='DAXX MIDIA PE'!$CN261 -> 0 | E88: ='DAXX MIDIA PE'!$CN267 -> 0 | F88: ='DAXX MIDIA PE'!$CN269 -> 17572.47
A89: ='DAXX MIDIA PE'!$CO1 -> 46107 | C89: ='DAXX MIDIA PE'!$CO255 -> 17572.47 | D89: ='DAXX MIDIA PE'!$CO261 -> 0 | E89: ='DAXX MIDIA PE'!$CO267 -> 0 | F89: ='DAXX MIDIA PE'!$CO269 -> 17572.47
A90: ='DAXX MIDIA PE'!$CP1 -> 46108 | C90: ='DAXX MIDIA PE'!$CP255 -> 17572.47 | D90: ='DAXX MIDIA PE'!$CP261 -> 0 | E90: ='DAXX MIDIA PE'!$CP267 -> 0 | F90: ='DAXX MIDIA PE'!$CP269 -> 17572.47
A91: ='DAXX MIDIA PE'!$CQ1 -> 46109 | C91: ='DAXX MIDIA PE'!$CQ255 -> 17572.47 | D91: ='DAXX MIDIA PE'!$CQ261 -> 0 | E91: ='DAXX MIDIA PE'!$CQ267 -> 0 | F91: ='DAXX MIDIA PE'!$CQ269 -> 17572.47
A92: ='DAXX MIDIA PE'!$CR1 -> 46110 | C92: ='DAXX MIDIA PE'!$CR255 -> 17572.47 | D92: ='DAXX MIDIA PE'!$CR261 -> 0 | E92: ='DAXX MIDIA PE'!$CR267 -> 0 | F92: ='DAXX MIDIA PE'!$CR269 -> 17572.47
A93: ='DAXX MIDIA PE'!$CS1 -> 46111 | C93: ='DAXX MIDIA PE'!$CS255 -> 17572.47 | D93: ='DAXX MIDIA PE'!$CS261 -> 0 | E93: ='DAXX MIDIA PE'!$CS267 -> 0 | F93: ='DAXX MIDIA PE'!$CS269 -> 17572.47
A94: ='DAXX MIDIA PE'!$CT1 -> 46112 | C94: ='DAXX MIDIA PE'!$CT255 -> 17285.31 | D94: ='DAXX MIDIA PE'!$CT261 -> 0 | E94: ='DAXX MIDIA PE'!$CT267 -> 0 | F94: ='DAXX MIDIA PE'!$CT269 -> 17285.31
A95: ='DAXX MIDIA PE'!$CW1 -> 46113 | C95: ='DAXX MIDIA PE'!$CW255 -> 17285.31 | D95: ='DAXX MIDIA PE'!$CW261 -> 0 | E95: ='DAXX MIDIA PE'!$CW267 -> 0 | F95: ='DAXX MIDIA PE'!$CW269 -> 17285.31
A96: ='DAXX MIDIA PE'!$CX1 -> 46114 | C96: ='DAXX MIDIA PE'!$CX255 -> 17285.31 | D96: ='DAXX MIDIA PE'!$CX261 -> 0 | E96: ='DAXX MIDIA PE'!$CX267 -> 0 | F96: ='DAXX MIDIA PE'!$CX269 -> 17285.31
A97: ='DAXX MIDIA PE'!$CY1 -> 46115 | C97: ='DAXX MIDIA PE'!$CY255 -> 17285.31 | D97: ='DAXX MIDIA PE'!$CY261 -> 0 | E97: ='DAXX MIDIA PE'!$CY267 -> 0 | F97: ='DAXX MIDIA PE'!$CY269 -> 17285.31
A98: ='DAXX MIDIA PE'!$CZ1 -> 46116 | C98: ='DAXX MIDIA PE'!$CZ255 -> 17285.31 | D98: ='DAXX MIDIA PE'!$CZ261 -> 0 | E98: ='DAXX MIDIA PE'!$CZ267 -> 0 | F98: ='DAXX MIDIA PE'!$CZ269 -> 17285.31
A99: ='DAXX MIDIA PE'!$DA1 -> 46117 | C99: ='DAXX MIDIA PE'!$DA255 -> 17285.31 | D99: ='DAXX MIDIA PE'!$DA261 -> 0 | E99: ='DAXX MIDIA PE'!$DA267 -> 0 | F99: ='DAXX MIDIA PE'!$DA269 -> 17285.31
A100: ='DAXX MIDIA PE'!$DB1 -> 46118 | C100: ='DAXX MIDIA PE'!$DB255 -> 16475.08 | D100: ='DAXX MIDIA PE'!$DB261 -> 0 | E100: ='DAXX MIDIA PE'!$DB267 -> 0 | F100: ='DAXX MIDIA PE'!$DB269 -> 16475.08
A101: ='DAXX MIDIA PE'!$DC1 -> 46119 | C101: ='DAXX MIDIA PE'!$DC255 -> 16475.08 | D101: ='DAXX MIDIA PE'!$DC261 -> 0 | E101: ='DAXX MIDIA PE'!$DC267 -> 0 | F101: ='DAXX MIDIA PE'!$DC269 -> 16475.08
...
